Workbook
Name Slicer_Departamento: #N/A
Name Slicer_Empresa: #N/A
Name Slicer_Responsável: #N/A
Name Slicer_Tipo: #N/A
Name Slicer_Unidade: #N/A

Sheet Centro de Custo
A11: Empresa | B11: Unidade | C11: Tipo | D11: Área | E11: Departamento | F11: CENTRO DE CUSTO | G11: Responsável
A12: Martini Meat | B12: Paranaguá | C12: Carga Geral | D12: Operação | E12: TI | F12: CG-PNG | TI | G12: Alexandre Ayabe
A13: Martini Meat | B13: Paranaguá | C13: Frigorífico | D13: Operação | E13: TI | F13: FG-PNG | TI | G13: Alexandre Ayabe
A14: Martini Meat | B14: Paranaguá | C14: Pátio | D14: Operação | E14: TI | F14: PT-PNG | TI | G14: Alexandre Ayabe
A15: Martini Meat | B15: Paranaguá | C15: RATEIO Unidade | D15: Operação | E15: TI | F15: PNG | TI | G15: Alexandre Ayabe
A16: Martini Meat | B16: Rio Grande | C16: Frigorífico | D16: Operação | E16: TI | F16: FG-RGD | TI | G16: Alexandre Ayabe
A17: Martini Meat | B17: Rio Grande | C17: Pátio | D17: Operação | E17: TI | F17: PT-RGD | TI | G17: Alexandre Ayabe
A18: Martini Meat | B18: Rio Grande | C18: RATEIO Unidade | D18: Operação | E18: TI | F18: RGD | TI | G18: Alexandre Ayabe
A19: Martini Meat | B19: Ponta Grossa | C19: Carga Geral | D19: Operação | E19: TI | F19: CG-PTG | TI | G19: Alexandre Ayabe
A20: Martini Meat | B20: Itajaí | C20: Frigorífico | D20: Operação | E20: TI | F20: FG-ITJ | TI | G20: Alexandre Ayabe
A21: Martini Meat | B21: Itajaí | C21: Pátio | D21: Operação | E21: TI | F21: PT-ITJ | TI | G21: Alexandre Ayabe
A22: Martini Meat | B22: Itajaí | C22: RATEIO Unidade | D22: Operação | E22: TI | F22: ITJ | TI | G22: Alexandre Ayabe
... A31: Cone Sul | B31: Plataforma | C31: G&A | D31: PL | E31: TI | F31: PL | TI | G31: Alexandre Ayabe

Sheet Budget
E1: Orçamento | F1: 2026 | AQ1: =SUM(AQ$5:AQ$328) -> 16192.876 | BE1: =SUM(BE$5:BE$352) -> 16739.988 | BS1: =SUM(BS$5:BT$352) -> 2846.9367
E2: Responsável | F2: Alexandre Ayabe
AE3: BRL'000 (sem Inflação) | AS3: BRL'000 | BG3: USD'000
A4: Cenário | B4: Ano | C4: Empresa | D4: Unidade | E4: Tipo | F4: Fornecedor | G4: Descrição Global | H4: Descrição | I4: Categoría | J4: Recorrência | K4: Prioridade | L4: Descr Centro de custo | M4: Responsável | N4: Despesa [ KPI ] | O4: Mes de reajuste (inflação) | P4: Moeda | Q4: 46023 | R4: =EDATE(Q4,1) -> 46054 | S4: =EDATE(R4,1) -> 46082 | T4: =EDATE(S4,1) -> 46113 | U4: =EDATE(T4,1) -> 46143 | V4: =EDATE(U4,1) -> 46174 | W4: =EDATE(V4,1) -> 46204 | X4: =EDATE(W4,1) -> 46235 | Y4: =EDATE(X4,1) -> 46266 | ... AB4: =EDATE(AA4,1) -> 46357 | AC4: BG.2026 | AD4: - | AE4: 46023 | AF4: =EDATE(AE4,1) -> 46054 | AG4: =EDATE(AF4,1) -> 46082 | AH4: =EDATE(AG4,1) -> 46113 | AI4: =EDATE(AH4,1) -> 46143 | AJ4: =EDATE(AI4,1) -> 46174 | AK4: =EDATE(AJ4,1) -> 46204 | AL4: =EDATE(AK4,1) -> 46235 | AM4: =EDATE(AL4,1) -> 46266 | ... AP4: =EDATE(AO4,1) -> 46357 | AQ4: BG.2026 | AR4: - | AS4: 46023 | AT4: =EDATE(AS4,1) -> 46054 | AU4: =EDATE(AT4,1) -> 46082 | AV4: =EDATE(AU4,1) -> 46113 | AW4: =EDATE(AV4,1) -> 46143 | AX4: =EDATE(AW4,1) -> 46174 | AY4: =EDATE(AX4,1) -> 46204 | AZ4: =EDATE(AY4,1) -> 46235 | BA4: =EDATE(AZ4,1) -> 46266 | ... BD4: =EDATE(BC4,1) -> 46357 | BE4: BG.2026 | BF4: - | BG4: 46023 | BH4: =EDATE(BG4,1) -> 46054 | BI4: =EDATE(BH4,1) -> 46082 | BJ4: =EDATE(BI4,1) -> 46113 | BK4: =EDATE(BJ4,1) -> 46143 | BL4: =EDATE(BK4,1) -> 46174 | BM4: =EDATE(BL4,1) -> 46204 | BN4: =EDATE(BM4,1) -> 46235 | BO4: =EDATE(BN4,1) -> 46266 | ... BR4: =EDATE(BQ4,1) -> 46357 | BS4: BG.2026 | BT4: DRE [ KPI ]
A5: =IF(ISBLANK($F5),"","Budget") -> Budget | B5: =IF(ISBLANK($F5),"",$F$1) -> 2026 | C5: =IF(ISBLANK($L5),"",_xlfn.XLOOKUP($L5,'CENTRO CUSTO'!$A:$A,'CENTRO CUSTO'!F:F,FALSE,0)) -> Transporte | D5: =IF(ISBLANK($L5),"",_xlfn.XLOOKUP($L5,'CENTRO CUSTO'!$A:$A,'CENTRO CUSTO'!G:G,FALSE,0)) -> BU-TR | E5: =IF(ISBLANK($L5),"",_xlfn.XLOOKUP($L5,'CENTRO CUSTO'!$A:$A,'CENTRO CUSTO'!H:H,FALSE,0)) -> G&A | F5: SPRO | G5: Applications support and maintenance | H5: SAP R3 - Licença | I5: Existente | J5: Mensal | K5: Contrato em Curso | L5: BU-MMTR | TI | M5: =IF(ISBLANK($L5),"",_xlfn.XLOOKUP($L5,'CENTRO CUSTO'!$A:$A,'CENTRO CUSTO'!D:D,FALSE,0)) -> Alexandre Ayabe | N5: Licença SAP | O5: 46023 | P5: BRL | Q5: =650000*Rateio!$E$3/12 -> 0 | R5: =650000*Rateio!$E$3/12 -> 0 | S5: =650000*Rateio!$E$3/12 -> 0 | T5: =650000*Rateio!$E$3/12 -> 0 | U5: =650000*Rateio!$E$3/12 -> 0 | V5: =650000*Rateio!$E$3/12 -> 0 | W5: =650000*Rateio!$E$3/12 -> 0 | X5: =650000*Rateio!$E$3/12 -> 0 | ... AB5: =650000*Rateio!$E$3/12 -> 0 | AC5: =IF(AND(ISBLANK($Q5),ISBLANK($R5),ISBLANK($S5),ISBLANK($T5),ISBLANK($U5),ISBLANK($V5),ISBLANK($W5),ISBLANK($X5),ISBLANK($Y5),ISBLANK($Z5),ISBLANK($AA5),ISBLANK($AB5)),"",SUM(Q5:AB5)) -> 0 | AE5: =IF(ISBLANK(Q5),"",IF($P5="BRL",Q5,Q5*Macroindicadores!B$2)/1000) -> 0 | AF5: =IF(ISBLANK(R5),"",IF($P5="BRL",R5,R5*Macroindicadores!C$2)/1000) -> 0 | AG5: =IF(ISBLANK(S5),"",IF($P5="BRL",S5,S5*Macroindicadores!D$2)/1000) -> 0 | AH5: =IF(ISBLANK(T5),"",IF($P5="BRL",T5,T5*Macroindicadores!E$2)/1000) -> 0 | AI5: =IF(ISBLANK(U5),"",IF($P5="BRL",U5,U5*Macroindicadores!F$2)/1000) -> 0 | AJ5: =IF(ISBLANK(V5),"",IF($P5="BRL",V5,V5*Macroindicadores!G$2)/1000) -> 0 | AK5: =IF(ISBLANK(W5),"",IF($P5="BRL",W5,W5*Macroindicadores!H$2)/1000) -> 0 | AL5: =IF(ISBLANK(X5),"",IF($P5="BRL",X5,X5*Macroindicadores!I$2)/1000) -> 0 | ... AP5: =IF(ISBLANK(AB5),"",IF($P5="BRL",AB5,AB5*Macroindicadores!M$2)/1000) -> 0 | AQ5: =IF(AND(ISBLANK(AE5),ISBLANK(AF5),ISBLANK(AG5),ISBLANK(AH5),ISBLANK(AI5),ISBLANK(AJ5),ISBLANK(AK5),ISBLANK(AL5),ISBLANK(AM5),ISBLANK(AN5),ISBLANK(AO5),ISBLANK(AP5)),"",SUM(AE5:AP5)) -> 0 | AS5: =IF(ISBLANK(Q5),"",IF(ISBLANK($O5),AE5,IF($J5="ANUAL",AE5*(1+Macroindicadores!B$7),IF(AND($I5="NOVO",MONTH($O5)=MONTH(AS$4)),AE5*(1+Macroindicadores!B$7),IF(AND($J5="PONTUAL",MONTH($O5)=MONTH(AS$4)),AE5*(1+Macroindicadores!B$7),IF(AND($J5="PONTUAL",MONTH($O5)<MONTH(AS$4)),MIN(AR5:$AS5),IF(AND($I5="NOVO",MONTH($O5)>MONTH(AS$4)),AE5,IF(MONTH($O5)>MONTH(AS$4),AE5,IF(MONTH($O5)=MONTH(AS$4),AE5*(1+Macroindicadores!B$7),AR5))))))))) -> 0 | AT5: =IF(ISBLANK(R5),"",IF(ISBLANK($O5),AF5,IF($J5="ANUAL",AF5*(1+Macroindicadores!C$7),IF(AND($I5="NOVO",MONTH($O5)=MONTH(AT$4)),AF5*(1+Macroindicadores!C$7),IF(AND($J5="PONTUAL",MONTH($O5)=MONTH(AT$4)),AF5*(1+Macroindicadores!C$7),IF(AND($J5="PONTUAL",MONTH($O5)<MONTH(AT$4)),MIN($AS5:AS5),IF(AND($I5="NOVO",MONTH($O5)>MONTH(AT$4)),AF5,IF(MONTH($O5)>MONTH(AT$4),AF5,IF(MONTH($O5)=MONTH(AT$4),AF5*(1+Macroindicadores!C$7),AS5))))))))) -> 0 | AU5: =IF(ISBLANK(S5),"",IF(ISBLANK($O5),AG5,IF($J5="ANUAL",AG5*(1+Macroindicadores!D$7),IF(AND($I5="NOVO",MONTH($O5)=MONTH(AU$4)),AG5*(1+Macroindicadores!D$7),IF(AND($J5="PONTUAL",MONTH($O5)=MONTH(AU$4)),AG5*(1+Macroindicadores!D$7),IF(AND($J5="PONTUAL",MONTH($O5)<MONTH(AU$4)),MIN($AS5:AT5),IF(AND($I5="NOVO",MONTH($O5)>MONTH(AU$4)),AG5,IF(MONTH($O5)>MONTH(AU$4),AG5,IF(MONTH($O5)=MONTH(AU$4),AG5*(1+Macroindicadores!D$7),AT5))))))))) -> 0 | AV5: =IF(ISBLANK(T5),"",IF(ISBLANK($O5),AH5,IF($J5="ANUAL",AH5*(1+Macroindicadores!E$7),IF(AND($I5="NOVO",MONTH($O5)=MONTH(AV$4)),AH5*(1+Macroindicadores!E$7),IF(AND($J5="PONTUAL",MONTH($O5)=MONTH(AV$4)),AH5*(1+Macroindicadores!E$7),IF(AND($J5="PONTUAL",MONTH($O5)<MONTH(AV$4)),MIN($AS5:AU5),IF(AND($I5="NOVO",MONTH($O5)>MONTH(AV$4)),AH5,IF(MONTH($O5)>MONTH(AV$4),AH5,IF(MONTH($O5)=MONTH(AV$4),AH5*(1+Macroindicadores!E$7),AU5))))))))) -> 0 | AW5: =IF(ISBLANK(U5),"",IF(ISBLANK($O5),AI5,IF($J5="ANUAL",AI5*(1+Macroindicadores!F$7),IF(AND($I5="NOVO",MONTH($O5)=MONTH(AW$4)),AI5*(1+Macroindicadores!F$7),IF(AND($J5="PONTUAL",MONTH($O5)=MONTH(AW$4)),AI5*(1+Macroindicadores!F$7),IF(AND($J5="PONTUAL",MONTH($O5)<MONTH(AW$4)),MIN($AS5:AV5),IF(AND($I5="NOVO",MONTH($O5)>MONTH(AW$4)),AI5,IF(MONTH($O5)>MONTH(AW$4),AI5,IF(MONTH($O5)=MONTH(AW$4),AI5*(1+Macroindicadores!F$7),AV5))))))))) -> 0 | AX5: =IF(ISBLANK(V5),"",IF(ISBLANK($O5),AJ5,IF($J5="ANUAL",AJ5*(1+Macroindicadores!G$7),IF(AND($I5="NOVO",MONTH($O5)=MONTH(AX$4)),AJ5*(1+Macroindicadores!G$7),IF(AND($J5="PONTUAL",MONTH($O5)=MONTH(AX$4)),AJ5*(1+Macroindicadores!G$7),IF(AND($J5="PONTUAL",MONTH($O5)<MONTH(AX$4)),MIN($AS5:AW5),IF(AND($I5="NOVO",MONTH($O5)>MONTH(AX$4)),AJ5,IF(MONTH($O5)>MONTH(AX$4),AJ5,IF(MONTH($O5)=MONTH(AX$4),AJ5*(1+Macroindicadores!G$7),AW5))))))))) -> 0 | AY5: =IF(ISBLANK(W5),"",IF(ISBLANK($O5),AK5,IF($J5="ANUAL",AK5*(1+Macroindicadores!H$7),IF(AND($I5="NOVO",MONTH($O5)=MONTH(AY$4)),AK5*(1+Macroindicadores!H$7),IF(AND($J5="PONTUAL",MONTH($O5)=MONTH(AY$4)),AK5*(1+Macroindicadores!H$7),IF(AND($J5="PONTUAL",MONTH($O5)<MONTH(AY$4)),MIN($AS5:AX5),IF(AND($I5="NOVO",MONTH($O5)>MONTH(AY$4)),AK5,IF(MONTH($O5)>MONTH(AY$4),AK5,IF(MONTH($O5)=MONTH(AY$4),AK5*(1+Macroindicadores!H$7),AX5))))))))) -> 0 | AZ5: =IF(ISBLANK(X5),"",IF(ISBLANK($O5),AL5,IF($J5="ANUAL",AL5*(1+Macroindicadores!I$7),IF(AND($I5="NOVO",MONTH($O5)=MONTH(AZ$4)),AL5*(1+Macroindicadores!I$7),IF(AND($J5="PONTUAL",MONTH($O5)=MONTH(AZ$4)),AL5*(1+Macroindicadores!I$7),IF(AND($J5="PONTUAL",MONTH($O5)<MONTH(AZ$4)),MIN($AS5:AY5),IF(AND($I5="NOVO",MONTH($O5)>MONTH(AZ$4)),AL5,IF(MONTH($O5)>MONTH(AZ$4),AL5,IF(MONTH($O5)=MONTH(AZ$4),AL5*(1+Macroindicadores!I$7),AY5))))))))) -> 0 | BA5: =IF(ISBLANK(Y5),"",IF(ISBLANK($O5),AM5,IF($J5="ANUAL",AM5*(1+Macroindicadores!J$7),IF(AND($I5="NOVO",MONTH($O5)=MONTH(BA$4)),AM5*(1+Macroindicadores!J$7),IF(AND($J5="PONTUAL",MONTH($O5)=MONTH(BA$4)),AM5*(1+Macroindicadores!J$7),IF(AND($J5="PONTUAL",MONTH($O5)<MONTH(BA$4)),MIN($AS5:AZ5),IF(AND($I5="NOVO",MONTH($O5)>MONTH(BA$4)),AM5,IF(MONTH($O5)>MONTH(BA$4),AM5,IF(MONTH($O5)=MONTH(BA$4),AM5*(1+Macroindicadores!J$7),AZ5))))))))) -> 0 | ... BD5: =IF(ISBLANK(AB5),"",IF(ISBLANK($O5),AP5,IF($J5="ANUAL",AP5*(1+Macroindicadores!M$7),IF(AND($I5="NOVO",MONTH($O5)=MONTH(BD$4)),AP5*(1+Macroindicadores!M$7),IF(AND($J5="PONTUAL",MONTH($O5)=MONTH(BD$4)),AP5*(1+Macroindicadores!M$7),IF(AND($J5="PONTUAL",MONTH($O5)<MONTH(BD$4)),MIN($AS5:BC5),IF(AND($I5="NOVO",MONTH($O5)>MONTH(BD$4)),AP5,IF(MONTH($O5)>MONTH(BD$4),AP5,IF(MONTH($O5)=MONTH(BD$4),AP5*(1+Macroindicadores!M$7),BC5))))))))) -> 0 | BE5: =IF(AND(ISBLANK($Q5),ISBLANK($R5),ISBLANK($S5),ISBLANK($T5),ISBLANK($U5),ISBLANK($V5),ISBLANK($W5),ISBLANK($X5),ISBLANK($Y5),ISBLANK($Z5),ISBLANK($AA5),ISBLANK($AB5)),"",SUM(AS5:BD5)) -> 0 | BG5: =IF(ISBLANK(Q5),"",AS5/Macroindicadores!B$2) -> 0 | BH5: =IF(ISBLANK(R5),"",AT5/Macroindicadores!C$2) -> 0 | BI5: =IF(ISBLANK(S5),"",AU5/Macroindicadores!D$2) -> 0 | BJ5: =IF(ISBLANK(T5),"",AV5/Macroindicadores!E$2) -> 0 | BK5: =IF(ISBLANK(U5),"",AW5/Macroindicadores!F$2) -> 0 | BL5: =IF(ISBLANK(V5),"",AX5/Macroindicadores!G$2) -> 0 | BM5: =IF(ISBLANK(W5),"",AY5/Macroindicadores!H$2) -> 0 | BN5: =IF(ISBLANK(X5),"",AZ5/Macroindicadores!I$2) -> 0 | ... BR5: =IF(ISBLANK(AB5),"",BD5/Macroindicadores!M$2) -> 0 | BS5: =IF(AND(ISBLANK($Q5),ISBLANK($R5),ISBLANK($S5),ISBLANK($T5),ISBLANK($U5),ISBLANK($V5),ISBLANK($W5),ISBLANK($X5),ISBLANK($Y5),ISBLANK($Z5),ISBLANK($AA5),ISBLANK($AB5)),"",SUM(BG5:BR5)) -> 0 | BT5: =IF(ISBLANK($L5),"",_xlfn.XLOOKUP($L5,'CENTRO CUSTO'!$A:$A,'CENTRO CUSTO'!$E:$E,FALSE,0)) -> G&A BU
A6: =IF(ISBLANK($F6),"","Budget") -> Budget | B6: =IF(ISBLANK($F6),"",$F$1) -> 2026 | C6: =IF(ISBLANK($L6),"",_xlfn.XLOOKUP($L6,'CENTRO CUSTO'!$A:$A,'CENTRO CUSTO'!F:F,FALSE,0)) -> Martini Meat | D6: =IF(ISBLANK($L6),"",_xlfn.XLOOKUP($L6,'CENTRO CUSTO'!$A:$A,'CENTRO CUSTO'!G:G,FALSE,0)) -> BU-MMAZ | E6: =IF(ISBLANK($L6),"",_xlfn.XLOOKUP($L6,'CENTRO CUSTO'!$A:$A,'CENTRO CUSTO'!H:H,FALSE,0)) -> G&A | F6: SPRO | G6: Applications support and maintenance | H6: SAP R3 - Licença | I6: Existente | J6: Mensal | K6: Contrato em Curso | L6: BU-MMAZ | TI | M6: =IF(ISBLANK($L6),"",_xlfn.XLOOKUP($L6,'CENTRO CUSTO'!$A:$A,'CENTRO CUSTO'!D:D,FALSE,0)) -> Alexandre Ayabe | N6: Licença SAP | O6: 46023 | P6: BRL | Q6: =650000*Rateio!$E$4/12 -> 54166.667 | R6: =650000*Rateio!$E$4/12 -> 54166.667 | S6: =650000*Rateio!$E$4/12 -> 54166.667 | T6: =650000*Rateio!$E$4/12 -> 54166.667 | U6: =650000*Rateio!$E$4/12 -> 54166.667 | V6: =650000*Rateio!$E$4/12 -> 54166.667 | W6: =650000*Rateio!$E$4/12 -> 54166.667 | X6: =650000*Rateio!$E$4/12 -> 54166.667 | ... AB6: =650000*Rateio!$E$4/12 -> 54166.667 | AC6: =IF(AND(ISBLANK($Q6),ISBLANK($R6),ISBLANK($S6),ISBLANK($T6),ISBLANK($U6),ISBLANK($V6),ISBLANK($W6),ISBLANK($X6),ISBLANK($Y6),ISBLANK($Z6),ISBLANK($AA6),ISBLANK($AB6)),"",SUM(Q6:AB6)) -> 650000 | AE6: =IF(ISBLANK(Q6),"",IF($P6="BRL",Q6,Q6*Macroindicadores!B$2)/1000) -> 54.166667 | AF6: =IF(ISBLANK(R6),"",IF($P6="BRL",R6,R6*Macroindicadores!C$2)/1000) -> 54.166667 | AG6: =IF(ISBLANK(S6),"",IF($P6="BRL",S6,S6*Macroindicadores!D$2)/1000) -> 54.166667 | AH6: =IF(ISBLANK(T6),"",IF($P6="BRL",T6,T6*Macroindicadores!E$2)/1000) -> 54.166667 | AI6: =IF(ISBLANK(U6),"",IF($P6="BRL",U6,U6*Macroindicadores!F$2)/1000) -> 54.166667 | AJ6: =IF(ISBLANK(V6),"",IF($P6="BRL",V6,V6*Macroindicadores!G$2)/1000) -> 54.166667 | AK6: =IF(ISBLANK(W6),"",IF($P6="BRL",W6,W6*Macroindicadores!H$2)/1000) -> 54.166667 | AL6: =IF(ISBLANK(X6),"",IF($P6="BRL",X6,X6*Macroindicadores!I$2)/1000) -> 54.166667 | ... AP6: =IF(ISBLANK(AB6),"",IF($P6="BRL",AB6,AB6*Macroindicadores!M$2)/1000) -> 54.166667 | AQ6: =IF(AND(ISBLANK($Q6),ISBLANK($R6),ISBLANK($S6),ISBLANK($T6),ISBLANK($U6),ISBLANK($V6),ISBLANK($W6),ISBLANK($X6),ISBLANK($Y6),ISBLANK($Z6),ISBLANK($AA6),ISBLANK($AB6)),"",SUM(AE6:AP6)) -> 650 | AS6: =IF(ISBLANK(Q6),"",IF(ISBLANK($O6),AE6,IF($J6="ANUAL",AE6*(1+Macroindicadores!B$7),IF(AND($I6="NOVO",MONTH($O6)=MONTH(AS$4)),AE6*(1+Macroindicadores!B$7),IF(AND($J6="PONTUAL",MONTH($O6)=MONTH(AS$4)),AE6*(1+Macroindicadores!B$7),IF(AND($J6="PONTUAL",MONTH($O6)<MONTH(AS$4)),MIN(AR6:$AS6),IF(AND($I6="NOVO",MONTH($O6)>MONTH(AS$4)),AE6,IF(MONTH($O6)>MONTH(AS$4),AE6,IF(MONTH($O6)=MONTH(AS$4),AE6*(1+Macroindicadores!B$7),AR6))))))))) -> 57.128233 | AT6: =IF(ISBLANK(R6),"",IF(ISBLANK($O6),AF6,IF($J6="ANUAL",AF6*(1+Macroindicadores!C$7),IF(AND($I6="NOVO",MONTH($O6)=MONTH(AT$4)),AF6*(1+Macroindicadores!C$7),IF(AND($J6="PONTUAL",MONTH($O6)=MONTH(AT$4)),AF6*(1+Macroindicadores!C$7),IF(AND($J6="PONTUAL",MONTH($O6)<MONTH(AT$4)),MIN($AS6:AS6),IF(AND($I6="NOVO",MONTH($O6)>MONTH(AT$4)),AF6,IF(MONTH($O6)>MONTH(AT$4),AF6,IF(MONTH($O6)=MONTH(AT$4),AF6*(1+Macroindicadores!C$7),AS6))))))))) -> 57.128233 | AU6: =IF(ISBLANK(S6),"",IF(ISBLANK($O6),AG6,IF($J6="ANUAL",AG6*(1+Macroindicadores!D$7),IF(AND($I6="NOVO",MONTH($O6)=MONTH(AU$4)),AG6*(1+Macroindicadores!D$7),IF(AND($J6="PONTUAL",MONTH($O6)=MONTH(AU$4)),AG6*(1+Macroindicadores!D$7),IF(AND($J6="PONTUAL",MONTH($O6)<MONTH(AU$4)),MIN($AS6:AT6),IF(AND($I6="NOVO",MONTH($O6)>MONTH(AU$4)),AG6,IF(MONTH($O6)>MONTH(AU$4),AG6,IF(MONTH($O6)=MONTH(AU$4),AG6*(1+Macroindicadores!D$7),AT6))))))))) -> 57.128233 | AV6: =IF(ISBLANK(T6),"",IF(ISBLANK($O6),AH6,IF($J6="ANUAL",AH6*(1+Macroindicadores!E$7),IF(AND($I6="NOVO",MONTH($O6)=MONTH(AV$4)),AH6*(1+Macroindicadores!E$7),IF(AND($J6="PONTUAL",MONTH($O6)=MONTH(AV$4)),AH6*(1+Macroindicadores!E$7),IF(AND($J6="PONTUAL",MONTH($O6)<MONTH(AV$4)),MIN($AS6:AU6),IF(AND($I6="NOVO",MONTH($O6)>MONTH(AV$4)),AH6,IF(MONTH($O6)>MONTH(AV$4),AH6,IF(MONTH($O6)=MONTH(AV$4),AH6*(1+Macroindicadores!E$7),AU6))))))))) -> 57.128233 | AW6: =IF(ISBLANK(U6),"",IF(ISBLANK($O6),AI6,IF($J6="ANUAL",AI6*(1+Macroindicadores!F$7),IF(AND($I6="NOVO",MONTH($O6)=MONTH(AW$4)),AI6*(1+Macroindicadores!F$7),IF(AND($J6="PONTUAL",MONTH($O6)=MONTH(AW$4)),AI6*(1+Macroindicadores!F$7),IF(AND($J6="PONTUAL",MONTH($O6)<MONTH(AW$4)),MIN($AS6:AV6),IF(AND($I6="NOVO",MONTH($O6)>MONTH(AW$4)),AI6,IF(MONTH($O6)>MONTH(AW$4),AI6,IF(MONTH($O6)=MONTH(AW$4),AI6*(1+Macroindicadores!F$7),AV6))))))))) -> 57.128233 | AX6: =IF(ISBLANK(V6),"",IF(ISBLANK($O6),AJ6,IF($J6="ANUAL",AJ6*(1+Macroindicadores!G$7),IF(AND($I6="NOVO",MONTH($O6)=MONTH(AX$4)),AJ6*(1+Macroindicadores!G$7),IF(AND($J6="PONTUAL",MONTH($O6)=MONTH(AX$4)),AJ6*(1+Macroindicadores!G$7),IF(AND($J6="PONTUAL",MONTH($O6)<MONTH(AX$4)),MIN($AS6:AW6),IF(AND($I6="NOVO",MONTH($O6)>MONTH(AX$4)),AJ6,IF(MONTH($O6)>MONTH(AX$4),AJ6,IF(MONTH($O6)=MONTH(AX$4),AJ6*(1+Macroindicadores!G$7),AW6))))))))) -> 57.128233 | AY6: =IF(ISBLANK(W6),"",IF(ISBLANK($O6),AK6,IF($J6="ANUAL",AK6*(1+Macroindicadores!H$7),IF(AND($I6="NOVO",MONTH($O6)=MONTH(AY$4)),AK6*(1+Macroindicadores!H$7),IF(AND($J6="PONTUAL",MONTH($O6)=MONTH(AY$4)),AK6*(1+Macroindicadores!H$7),IF(AND($J6="PONTUAL",MONTH($O6)<MONTH(AY$4)),MIN($AS6:AX6),IF(AND($I6="NOVO",MONTH($O6)>MONTH(AY$4)),AK6,IF(MONTH($O6)>MONTH(AY$4),AK6,IF(MONTH($O6)=MONTH(AY$4),AK6*(1+Macroindicadores!H$7),AX6))))))))) -> 57.128233 | AZ6: =IF(ISBLANK(X6),"",IF(ISBLANK($O6),AL6,IF($J6="ANUAL",AL6*(1+Macroindicadores!I$7),IF(AND($I6="NOVO",MONTH($O6)=MONTH(AZ$4)),AL6*(1+Macroindicadores!I$7),IF(AND($J6="PONTUAL",MONTH($O6)=MONTH(AZ$4)),AL6*(1+Macroindicadores!I$7),IF(AND($J6="PONTUAL",MONTH($O6)<MONTH(AZ$4)),MIN($AS6:AY6),IF(AND($I6="NOVO",MONTH($O6)>MONTH(AZ$4)),AL6,IF(MONTH($O6)>MONTH(AZ$4),AL6,IF(MONTH($O6)=MONTH(AZ$4),AL6*(1+Macroindicadores!I$7),AY6))))))))) -> 57.128233 | BA6: =IF(ISBLANK(Y6),"",IF(ISBLANK($O6),AM6,IF($J6="ANUAL",AM6*(1+Macroindicadores!J$7),IF(AND($I6="NOVO",MONTH($O6)=MONTH(BA$4)),AM6*(1+Macroindicadores!J$7),IF(AND($J6="PONTUAL",MONTH($O6)=MONTH(BA$4)),AM6*(1+Macroindicadores!J$7),IF(AND($J6="PONTUAL",MONTH($O6)<MONTH(BA$4)),MIN($AS6:AZ6),IF(AND($I6="NOVO",MONTH($O6)>MONTH(BA$4)),AM6,IF(MONTH($O6)>MONTH(BA$4),AM6,IF(MONTH($O6)=MONTH(BA$4),AM6*(1+Macroindicadores!J$7),AZ6))))))))) -> 57.128233 | ... BD6: =IF(ISBLANK(AB6),"",IF(ISBLANK($O6),AP6,IF($J6="ANUAL",AP6*(1+Macroindicadores!M$7),IF(AND($I6="NOVO",MONTH($O6)=MONTH(BD$4)),AP6*(1+Macroindicadores!M$7),IF(AND($J6="PONTUAL",MONTH($O6)=MONTH(BD$4)),AP6*(1+Macroindicadores!M$7),IF(AND($J6="PONTUAL",MONTH($O6)<MONTH(BD$4)),MIN($AS6:BC6),IF(AND($I6="NOVO",MONTH($O6)>MONTH(BD$4)),AP6,IF(MONTH($O6)>MONTH(BD$4),AP6,IF(MONTH($O6)=MONTH(BD$4),AP6*(1+Macroindicadores!M$7),BC6))))))))) -> 57.128233 | BE6: =IF(AND(ISBLANK($Q6),ISBLANK($R6),ISBLANK($S6),ISBLANK($T6),ISBLANK($U6),ISBLANK($V6),ISBLANK($W6),ISBLANK($X6),ISBLANK($Y6),ISBLANK($Z6),ISBLANK($AA6),ISBLANK($AB6)),"",SUM(AS6:BD6)) -> 685.5388 | BG6: =IF(ISBLANK(Q6),"",AS6/Macroindicadores!B$2) -> 9.715686 | BH6: =IF(ISBLANK(R6),"",AT6/Macroindicadores!C$2) -> 9.715686 | BI6: =IF(ISBLANK(S6),"",AU6/Macroindicadores!D$2) -> 9.715686 | BJ6: =IF(ISBLANK(T6),"",AV6/Macroindicadores!E$2) -> 9.715686 | BK6: =IF(ISBLANK(U6),"",AW6/Macroindicadores!F$2) -> 9.715686 | BL6: =IF(ISBLANK(V6),"",AX6/Macroindicadores!G$2) -> 9.715686 | BM6: =IF(ISBLANK(W6),"",AY6/Macroindicadores!H$2) -> 9.715686 | BN6: =IF(ISBLANK(X6),"",AZ6/Macroindicadores!I$2) -> 9.715686 | ... BR6: =IF(ISBLANK(AB6),"",BD6/Macroindicadores!M$2) -> 9.715686 | BS6: =IF(AND(ISBLANK($Q6),ISBLANK($R6),ISBLANK($S6),ISBLANK($T6),ISBLANK($U6),ISBLANK($V6),ISBLANK($W6),ISBLANK($X6),ISBLANK($Y6),ISBLANK($Z6),ISBLANK($AA6),ISBLANK($AB6)),"",SUM(BG6:BR6)) -> 116.58823 | BT6: =IF(ISBLANK($L6),"",_xlfn.XLOOKUP($L6,'CENTRO CUSTO'!$A:$A,'CENTRO CUSTO'!$E:$E,FALSE,0)) -> G&A BU | BV6: =AC6/BS6 -> 5575.1768
A7: =IF(ISBLANK($F7),"","Budget") -> Budget | B7: =IF(ISBLANK($F7),"",$F$1) -> 2026 | C7: =IF(ISBLANK($L7),"",_xlfn.XLOOKUP($L7,'CENTRO CUSTO'!$A:$A,'CENTRO CUSTO'!F:F,FALSE,0)) -> Martini Meat | D7: =IF(ISBLANK($L7),"",_xlfn.XLOOKUP($L7,'CENTRO CUSTO'!$A:$A,'CENTRO CUSTO'!G:G,FALSE,0)) -> BU-MMAZ | E7: =IF(ISBLANK($L7),"",_xlfn.XLOOKUP($L7,'CENTRO CUSTO'!$A:$A,'CENTRO CUSTO'!H:H,FALSE,0)) -> G&A | F7: OT/SCADA SYSTEMS | G7: Applications support and maintenance | H7: Cybersecurity | I7: Novo | J7: Annual | K7: Alta - Para a operação | L7: BU-MMAZ | TI | M7: =IF(ISBLANK($L7),"",_xlfn.XLOOKUP($L7,'CENTRO CUSTO'!$A:$A,'CENTRO CUSTO'!D:D,FALSE,0)) -> Alexandre Ayabe | N7: Outras licenças | P7: USD | Q7: =78368*Rateio!$E$4/12 -> 6530.6667 | R7: =78368*Rateio!$E$4/12 -> 6530.6667 | S7: =78368*Rateio!$E$4/12 -> 6530.6667 | T7: =78368*Rateio!$E$4/12 -> 6530.6667 | U7: =78368*Rateio!$E$4/12 -> 6530.6667 | V7: =78368*Rateio!$E$4/12 -> 6530.6667 | W7: =78368*Rateio!$E$4/12 -> 6530.6667 | X7: =78368*Rateio!$E$4/12 -> 6530.6667 | ... AB7: =78368*Rateio!$E$4/12 -> 6530.6667 | AC7: =IF(AND(ISBLANK($Q7),ISBLANK($R7),ISBLANK($S7),ISBLANK($T7),ISBLANK($U7),ISBLANK($V7),ISBLANK($W7),ISBLANK($X7),ISBLANK($Y7),ISBLANK($Z7),ISBLANK($AA7),ISBLANK($AB7)),"",SUM(Q7:AB7)) -> 78368 | AE7: =IF(ISBLANK(Q7),"",IF($P7="BRL",Q7,Q7*Macroindicadores!B$2)/1000) -> 38.40032 | AF7: =IF(ISBLANK(R7),"",IF($P7="BRL",R7,R7*Macroindicadores!C$2)/1000) -> 38.40032 | AG7: =IF(ISBLANK(S7),"",IF($P7="BRL",S7,S7*Macroindicadores!D$2)/1000) -> 38.40032 | AH7: =IF(ISBLANK(T7),"",IF($P7="BRL",T7,T7*Macroindicadores!E$2)/1000) -> 38.40032 | AI7: =IF(ISBLANK(U7),"",IF($P7="BRL",U7,U7*Macroindicadores!F$2)/1000) -> 38.40032 | AJ7: =IF(ISBLANK(V7),"",IF($P7="BRL",V7,V7*Macroindicadores!G$2)/1000) -> 38.40032 | AK7: =IF(ISBLANK(W7),"",IF($P7="BRL",W7,W7*Macroindicadores!H$2)/1000) -> 38.40032 | AL7: =IF(ISBLANK(X7),"",IF($P7="BRL",X7,X7*Macroindicadores!I$2)/1000) -> 38.40032 | ... AP7: =IF(ISBLANK(AB7),"",IF($P7="BRL",AB7,AB7*Macroindicadores!M$2)/1000) -> 38.40032 | AQ7: =IF(AND(ISBLANK($Q7),ISBLANK($R7),ISBLANK($S7),ISBLANK($T7),ISBLANK($U7),ISBLANK($V7),ISBLANK($W7),ISBLANK($X7),ISBLANK($Y7),ISBLANK($Z7),ISBLANK($AA7),ISBLANK($AB7)),"",SUM(AE7:AP7)) -> 460.80384 | AS7: =IF(ISBLANK(Q7),"",IF(ISBLANK($O7),AE7,IF($J7="ANUAL",AE7*(1+Macroindicadores!B$7),IF(AND($I7="NOVO",MONTH($O7)=MONTH(AS$4)),AE7*(1+Macroindicadores!B$7),IF(AND($J7="PONTUAL",MONTH($O7)=MONTH(AS$4)),AE7*(1+Macroindicadores!B$7),IF(AND($J7="PONTUAL",MONTH($O7)<MONTH(AS$4)),MIN(AR7:$AS7),IF(AND($I7="NOVO",MONTH($O7)>MONTH(AS$4)),AE7,IF(MONTH($O7)>MONTH(AS$4),AE7,IF(MONTH($O7)=MONTH(AS$4),AE7*(1+Macroindicadores!B$7),AR7))))))))) -> 38.40032 | AT7: =IF(ISBLANK(R7),"",IF(ISBLANK($O7),AF7,IF($J7="ANUAL",AF7*(1+Macroindicadores!C$7),IF(AND($I7="NOVO",MONTH($O7)=MONTH(AT$4)),AF7*(1+Macroindicadores!C$7),IF(AND($J7="PONTUAL",MONTH($O7)=MONTH(AT$4)),AF7*(1+Macroindicadores!C$7),IF(AND($J7="PONTUAL",MONTH($O7)<MONTH(AT$4)),MIN($AS7:AS7),IF(AND($I7="NOVO",MONTH($O7)>MONTH(AT$4)),AF7,IF(MONTH($O7)>MONTH(AT$4),AF7,IF(MONTH($O7)=MONTH(AT$4),AF7*(1+Macroindicadores!C$7),AS7))))))))) -> 38.40032 | AU7: =IF(ISBLANK(S7),"",IF(ISBLANK($O7),AG7,IF($J7="ANUAL",AG7*(1+Macroindicadores!D$7),IF(AND($I7="NOVO",MONTH($O7)=MONTH(AU$4)),AG7*(1+Macroindicadores!D$7),IF(AND($J7="PONTUAL",MONTH($O7)=MONTH(AU$4)),AG7*(1+Macroindicadores!D$7),IF(AND($J7="PONTUAL",MONTH($O7)<MONTH(AU$4)),MIN($AS7:AT7),IF(AND($I7="NOVO",MONTH($O7)>MONTH(AU$4)),AG7,IF(MONTH($O7)>MONTH(AU$4),AG7,IF(MONTH($O7)=MONTH(AU$4),AG7*(1+Macroindicadores!D$7),AT7))))))))) -> 38.40032 | AV7: =IF(ISBLANK(T7),"",IF(ISBLANK($O7),AH7,IF($J7="ANUAL",AH7*(1+Macroindicadores!E$7),IF(AND($I7="NOVO",MONTH($O7)=MONTH(AV$4)),AH7*(1+Macroindicadores!E$7),IF(AND($J7="PONTUAL",MONTH($O7)=MONTH(AV$4)),AH7*(1+Macroindicadores!E$7),IF(AND($J7="PONTUAL",MONTH($O7)<MONTH(AV$4)),MIN($AS7:AU7),IF(AND($I7="NOVO",MONTH($O7)>MONTH(AV$4)),AH7,IF(MONTH($O7)>MONTH(AV$4),AH7,IF(MONTH($O7)=MONTH(AV$4),AH7*(1+Macroindicadores!E$7),AU7))))))))) -> 38.40032 | AW7: =IF(ISBLANK(U7),"",IF(ISBLANK($O7),AI7,IF($J7="ANUAL",AI7*(1+Macroindicadores!F$7),IF(AND($I7="NOVO",MONTH($O7)=MONTH(AW$4)),AI7*(1+Macroindicadores!F$7),IF(AND($J7="PONTUAL",MONTH($O7)=MONTH(AW$4)),AI7*(1+Macroindicadores!F$7),IF(AND($J7="PONTUAL",MONTH($O7)<MONTH(AW$4)),MIN($AS7:AV7),IF(AND($I7="NOVO",MONTH($O7)>MONTH(AW$4)),AI7,IF(MONTH($O7)>MONTH(AW$4),AI7,IF(MONTH($O7)=MONTH(AW$4),AI7*(1+Macroindicadores!F$7),AV7))))))))) -> 38.40032 | AX7: =IF(ISBLANK(V7),"",IF(ISBLANK($O7),AJ7,IF($J7="ANUAL",AJ7*(1+Macroindicadores!G$7),IF(AND($I7="NOVO",MONTH($O7)=MONTH(AX$4)),AJ7*(1+Macroindicadores!G$7),IF(AND($J7="PONTUAL",MONTH($O7)=MONTH(AX$4)),AJ7*(1+Macroindicadores!G$7),IF(AND($J7="PONTUAL",MONTH($O7)<MONTH(AX$4)),MIN($AS7:AW7),IF(AND($I7="NOVO",MONTH($O7)>MONTH(AX$4)),AJ7,IF(MONTH($O7)>MONTH(AX$4),AJ7,IF(MONTH($O7)=MONTH(AX$4),AJ7*(1+Macroindicadores!G$7),AW7))))))))) -> 38.40032 | AY7: =IF(ISBLANK(W7),"",IF(ISBLANK($O7),AK7,IF($J7="ANUAL",AK7*(1+Macroindicadores!H$7),IF(AND($I7="NOVO",MONTH($O7)=MONTH(AY$4)),AK7*(1+Macroindicadores!H$7),IF(AND($J7="PONTUAL",MONTH($O7)=MONTH(AY$4)),AK7*(1+Macroindicadores!H$7),IF(AND($J7="PONTUAL",MONTH($O7)<MONTH(AY$4)),MIN($AS7:AX7),IF(AND($I7="NOVO",MONTH($O7)>MONTH(AY$4)),AK7,IF(MONTH($O7)>MONTH(AY$4),AK7,IF(MONTH($O7)=MONTH(AY$4),AK7*(1+Macroindicadores!H$7),AX7))))))))) -> 38.40032 | AZ7: =IF(ISBLANK(X7),"",IF(ISBLANK($O7),AL7,IF($J7="ANUAL",AL7*(1+Macroindicadores!I$7),IF(AND($I7="NOVO",MONTH($O7)=MONTH(AZ$4)),AL7*(1+Macroindicadores!I$7),IF(AND($J7="PONTUAL",MONTH($O7)=MONTH(AZ$4)),AL7*(1+Macroindicadores!I$7),IF(AND($J7="PONTUAL",MONTH($O7)<MONTH(AZ$4)),MIN($AS7:AY7),IF(AND($I7="NOVO",MONTH($O7)>MONTH(AZ$4)),AL7,IF(MONTH($O7)>MONTH(AZ$4),AL7,IF(MONTH($O7)=MONTH(AZ$4),AL7*(1+Macroindicadores!I$7),AY7))))))))) -> 38.40032 | BA7: =IF(ISBLANK(Y7),"",IF(ISBLANK($O7),AM7,IF($J7="ANUAL",AM7*(1+Macroindicadores!J$7),IF(AND($I7="NOVO",MONTH($O7)=MONTH(BA$4)),AM7*(1+Macroindicadores!J$7),IF(AND($J7="PONTUAL",MONTH($O7)=MONTH(BA$4)),AM7*(1+Macroindicadores!J$7),IF(AND($J7="PONTUAL",MONTH($O7)<MONTH(BA$4)),MIN($AS7:AZ7),IF(AND($I7="NOVO",MONTH($O7)>MONTH(BA$4)),AM7,IF(MONTH($O7)>MONTH(BA$4),AM7,IF(MONTH($O7)=MONTH(BA$4),AM7*(1+Macroindicadores!J$7),AZ7))))))))) -> 38.40032 | ... BD7: =IF(ISBLANK(AB7),"",IF(ISBLANK($O7),AP7,IF($J7="ANUAL",AP7*(1+Macroindicadores!M$7),IF(AND($I7="NOVO",MONTH($O7)=MONTH(BD$4)),AP7*(1+Macroindicadores!M$7),IF(AND($J7="PONTUAL",MONTH($O7)=MONTH(BD$4)),AP7*(1+Macroindicadores!M$7),IF(AND($J7="PONTUAL",MONTH($O7)<MONTH(BD$4)),MIN($AS7:BC7),IF(AND($I7="NOVO",MONTH($O7)>MONTH(BD$4)),AP7,IF(MONTH($O7)>MONTH(BD$4),AP7,IF(MONTH($O7)=MONTH(BD$4),AP7*(1+Macroindicadores!M$7),BC7))))))))) -> 38.40032 | BE7: =IF(AND(ISBLANK($Q7),ISBLANK($R7),ISBLANK($S7),ISBLANK($T7),ISBLANK($U7),ISBLANK($V7),ISBLANK($W7),ISBLANK($X7),ISBLANK($Y7),ISBLANK($Z7),ISBLANK($AA7),ISBLANK($AB7)),"",SUM(AS7:BD7)) -> 460.80384 | BG7: =IF(ISBLANK(Q7),"",AS7/Macroindicadores!B$2) -> 6.5306667 | BH7: =IF(ISBLANK(R7),"",AT7/Macroindicadores!C$2) -> 6.5306667 | BI7: =IF(ISBLANK(S7),"",AU7/Macroindicadores!D$2) -> 6.5306667 | BJ7: =IF(ISBLANK(T7),"",AV7/Macroindicadores!E$2) -> 6.5306667 | BK7: =IF(ISBLANK(U7),"",AW7/Macroindicadores!F$2) -> 6.5306667 | BL7: =IF(ISBLANK(V7),"",AX7/Macroindicadores!G$2) -> 6.5306667 | BM7: =IF(ISBLANK(W7),"",AY7/Macroindicadores!H$2) -> 6.5306667 | BN7: =IF(ISBLANK(X7),"",AZ7/Macroindicadores!I$2) -> 6.5306667 | ... BR7: =IF(ISBLANK(AB7),"",BD7/Macroindicadores!M$2) -> 6.5306667 | BS7: =IF(AND(ISBLANK($Q7),ISBLANK($R7),ISBLANK($S7),ISBLANK($T7),ISBLANK($U7),ISBLANK($V7),ISBLANK($W7),ISBLANK($X7),ISBLANK($Y7),ISBLANK($Z7),ISBLANK($AA7),ISBLANK($AB7)),"",SUM(BG7:BR7)) -> 78.368 | BT7: =IF(ISBLANK($L7),"",_xlfn.XLOOKUP($L7,'CENTRO CUSTO'!$A:$A,'CENTRO CUSTO'!$E:$E,FALSE,0)) -> G&A BU
A8: =IF(ISBLANK($F8),"","Budget") -> Budget | B8: =IF(ISBLANK($F8),"",$F$1) -> 2026 | C8: =IF(ISBLANK($L8),"",_xlfn.XLOOKUP($L8,'CENTRO CUSTO'!$A:$A,'CENTRO CUSTO'!F:F,FALSE,0)) -> Transporte | D8: =IF(ISBLANK($L8),"",_xlfn.XLOOKUP($L8,'CENTRO CUSTO'!$A:$A,'CENTRO CUSTO'!G:G,FALSE,0)) -> BU-TR | E8: =IF(ISBLANK($L8),"",_xlfn.XLOOKUP($L8,'CENTRO CUSTO'!$A:$A,'CENTRO CUSTO'!H:H,FALSE,0)) -> G&A | F8: RAVANEDA | G8: Applications support and maintenance | H8: SAP R3 - AMS | I8: Existente | J8: Mensal | K8: Contrato em Curso | L8: BU-MMTR | TI | M8: =IF(ISBLANK($L8),"",_xlfn.XLOOKUP($L8,'CENTRO CUSTO'!$A:$A,'CENTRO CUSTO'!D:D,FALSE,0)) -> Alexandre Ayabe | N8: Manutenção de Informática | P8: BRL | Q8: =35000*Rateio!$E$3 -> 0 | R8: =35000*Rateio!$E$3 -> 0 | S8: =35000*Rateio!$E$3 -> 0 | AC8: =IF(AND(ISBLANK($Q8),ISBLANK($R8),ISBLANK($S8),ISBLANK($T8),ISBLANK($U8),ISBLANK($V8),ISBLANK($W8),ISBLANK($X8),ISBLANK($Y8),ISBLANK($Z8),ISBLANK($AA8),ISBLANK($AB8)),"",SUM(Q8:AB8)) -> 0 | AE8: =IF(ISBLANK(Q8),"",IF($P8="BRL",Q8,Q8*Macroindicadores!B$2)/1000) -> 0 | AF8: =IF(ISBLANK(R8),"",IF($P8="BRL",R8,R8*Macroindicadores!C$2)/1000) -> 0 | AG8: =IF(ISBLANK(S8),"",IF($P8="BRL",S8,S8*Macroindicadores!D$2)/1000) -> 0 | AH8: =IF(ISBLANK(T8),"",IF($P8="BRL",T8,T8*Macroindicadores!E$2)/1000) | AI8: =IF(ISBLANK(U8),"",IF($P8="BRL",U8,U8*Macroindicadores!F$2)/1000) | AJ8: =IF(ISBLANK(V8),"",IF($P8="BRL",V8,V8*Macroindicadores!G$2)/1000) | AK8: =IF(ISBLANK(W8),"",IF($P8="BRL",W8,W8*Macroindicadores!H$2)/1000) | AL8: =IF(ISBLANK(X8),"",IF($P8="BRL",X8,X8*Macroindicadores!I$2)/1000) | ... AP8: =IF(ISBLANK(AB8),"",IF($P8="BRL",AB8,AB8*Macroindicadores!M$2)/1000) | AQ8: =IF(AND(ISBLANK($Q8),ISBLANK($R8),ISBLANK($S8),ISBLANK($T8),ISBLANK($U8),ISBLANK($V8),ISBLANK($W8),ISBLANK($X8),ISBLANK($Y8),ISBLANK($Z8),ISBLANK($AA8),ISBLANK($AB8)),"",SUM(AE8:AP8)) -> 0 | AS8: =IF(ISBLANK(Q8),"",IF(ISBLANK($O8),AE8,IF($J8="ANUAL",AE8*(1+Macroindicadores!B$7),IF(AND($I8="NOVO",MONTH($O8)=MONTH(AS$4)),AE8*(1+Macroindicadores!B$7),IF(AND($J8="PONTUAL",MONTH($O8)=MONTH(AS$4)),AE8*(1+Macroindicadores!B$7),IF(AND($J8="PONTUAL",MONTH($O8)<MONTH(AS$4)),MIN(AR8:$AS8),IF(AND($I8="NOVO",MONTH($O8)>MONTH(AS$4)),AE8,IF(MONTH($O8)>MONTH(AS$4),AE8,IF(MONTH($O8)=MONTH(AS$4),AE8*(1+Macroindicadores!B$7),AR8))))))))) -> 0 | AT8: =IF(ISBLANK(R8),"",IF(ISBLANK($O8),AF8,IF($J8="ANUAL",AF8*(1+Macroindicadores!C$7),IF(AND($I8="NOVO",MONTH($O8)=MONTH(AT$4)),AF8*(1+Macroindicadores!C$7),IF(AND($J8="PONTUAL",MONTH($O8)=MONTH(AT$4)),AF8*(1+Macroindicadores!C$7),IF(AND($J8="PONTUAL",MONTH($O8)<MONTH(AT$4)),MIN($AS8:AS8),IF(AND($I8="NOVO",MONTH($O8)>MONTH(AT$4)),AF8,IF(MONTH($O8)>MONTH(AT$4),AF8,IF(MONTH($O8)=MONTH(AT$4),AF8*(1+Macroindicadores!C$7),AS8))))))))) -> 0 | AU8: =IF(ISBLANK(S8),"",IF(ISBLANK($O8),AG8,IF($J8="ANUAL",AG8*(1+Macroindicadores!D$7),IF(AND($I8="NOVO",MONTH($O8)=MONTH(AU$4)),AG8*(1+Macroindicadores!D$7),IF(AND($J8="PONTUAL",MONTH($O8)=MONTH(AU$4)),AG8*(1+Macroindicadores!D$7),IF(AND($J8="PONTUAL",MONTH($O8)<MONTH(AU$4)),MIN($AS8:AT8),IF(AND($I8="NOVO",MONTH($O8)>MONTH(AU$4)),AG8,IF(MONTH($O8)>MONTH(AU$4),AG8,IF(MONTH($O8)=MONTH(AU$4),AG8*(1+Macroindicadores!D$7),AT8))))))))) -> 0 | AV8: =IF(ISBLANK(T8),"",IF(ISBLANK($O8),AH8,IF($J8="ANUAL",AH8*(1+Macroindicadores!E$7),IF(AND($I8="NOVO",MONTH($O8)=MONTH(AV$4)),AH8*(1+Macroindicadores!E$7),IF(AND($J8="PONTUAL",MONTH($O8)=MONTH(AV$4)),AH8*(1+Macroindicadores!E$7),IF(AND($J8="PONTUAL",MONTH($O8)<MONTH(AV$4)),MIN($AS8:AU8),IF(AND($I8="NOVO",MONTH($O8)>MONTH(AV$4)),AH8,IF(MONTH($O8)>MONTH(AV$4),AH8,IF(MONTH($O8)=MONTH(AV$4),AH8*(1+Macroindicadores!E$7),AU8))))))))) | AW8: =IF(ISBLANK(U8),"",IF(ISBLANK($O8),AI8,IF($J8="ANUAL",AI8*(1+Macroindicadores!F$7),IF(AND($I8="NOVO",MONTH($O8)=MONTH(AW$4)),AI8*(1+Macroindicadores!F$7),IF(AND($J8="PONTUAL",MONTH($O8)=MONTH(AW$4)),AI8*(1+Macroindicadores!F$7),IF(AND($J8="PONTUAL",MONTH($O8)<MONTH(AW$4)),MIN($AS8:AV8),IF(AND($I8="NOVO",MONTH($O8)>MONTH(AW$4)),AI8,IF(MONTH($O8)>MONTH(AW$4),AI8,IF(MONTH($O8)=MONTH(AW$4),AI8*(1+Macroindicadores!F$7),AV8))))))))) | AX8: =IF(ISBLANK(V8),"",IF(ISBLANK($O8),AJ8,IF($J8="ANUAL",AJ8*(1+Macroindicadores!G$7),IF(AND($I8="NOVO",MONTH($O8)=MONTH(AX$4)),AJ8*(1+Macroindicadores!G$7),IF(AND($J8="PONTUAL",MONTH($O8)=MONTH(AX$4)),AJ8*(1+Macroindicadores!G$7),IF(AND($J8="PONTUAL",MONTH($O8)<MONTH(AX$4)),MIN($AS8:AW8),IF(AND($I8="NOVO",MONTH($O8)>MONTH(AX$4)),AJ8,IF(MONTH($O8)>MONTH(AX$4),AJ8,IF(MONTH($O8)=MONTH(AX$4),AJ8*(1+Macroindicadores!G$7),AW8))))))))) | AY8: =IF(ISBLANK(W8),"",IF(ISBLANK($O8),AK8,IF($J8="ANUAL",AK8*(1+Macroindicadores!H$7),IF(AND($I8="NOVO",MONTH($O8)=MONTH(AY$4)),AK8*(1+Macroindicadores!H$7),IF(AND($J8="PONTUAL",MONTH($O8)=MONTH(AY$4)),AK8*(1+Macroindicadores!H$7),IF(AND($J8="PONTUAL",MONTH($O8)<MONTH(AY$4)),MIN($AS8:AX8),IF(AND($I8="NOVO",MONTH($O8)>MONTH(AY$4)),AK8,IF(MONTH($O8)>MONTH(AY$4),AK8,IF(MONTH($O8)=MONTH(AY$4),AK8*(1+Macroindicadores!H$7),AX8))))))))) | AZ8: =IF(ISBLANK(X8),"",IF(ISBLANK($O8),AL8,IF($J8="ANUAL",AL8*(1+Macroindicadores!I$7),IF(AND($I8="NOVO",MONTH($O8)=MONTH(AZ$4)),AL8*(1+Macroindicadores!I$7),IF(AND($J8="PONTUAL",MONTH($O8)=MONTH(AZ$4)),AL8*(1+Macroindicadores!I$7),IF(AND($J8="PONTUAL",MONTH($O8)<MONTH(AZ$4)),MIN($AS8:AY8),IF(AND($I8="NOVO",MONTH($O8)>MONTH(AZ$4)),AL8,IF(MONTH($O8)>MONTH(AZ$4),AL8,IF(MONTH($O8)=MONTH(AZ$4),AL8*(1+Macroindicadores!I$7),AY8))))))))) | BA8: =IF(ISBLANK(Y8),"",IF(ISBLANK($O8),AM8,IF($J8="ANUAL",AM8*(1+Macroindicadores!J$7),IF(AND($I8="NOVO",MONTH($O8)=MONTH(BA$4)),AM8*(1+Macroindicadores!J$7),IF(AND($J8="PONTUAL",MONTH($O8)=MONTH(BA$4)),AM8*(1+Macroindicadores!J$7),IF(AND($J8="PONTUAL",MONTH($O8)<MONTH(BA$4)),MIN($AS8:AZ8),IF(AND($I8="NOVO",MONTH($O8)>MONTH(BA$4)),AM8,IF(MONTH($O8)>MONTH(BA$4),AM8,IF(MONTH($O8)=MONTH(BA$4),AM8*(1+Macroindicadores!J$7),AZ8))))))))) | ... BD8: =IF(ISBLANK(AB8),"",IF(ISBLANK($O8),AP8,IF($J8="ANUAL",AP8*(1+Macroindicadores!M$7),IF(AND($I8="NOVO",MONTH($O8)=MONTH(BD$4)),AP8*(1+Macroindicadores!M$7),IF(AND($J8="PONTUAL",MONTH($O8)=MONTH(BD$4)),AP8*(1+Macroindicadores!M$7),IF(AND($J8="PONTUAL",MONTH($O8)<MONTH(BD$4)),MIN($AS8:BC8),IF(AND($I8="NOVO",MONTH($O8)>MONTH(BD$4)),AP8,IF(MONTH($O8)>MONTH(BD$4),AP8,IF(MONTH($O8)=MONTH(BD$4),AP8*(1+Macroindicadores!M$7),BC8))))))))) | BE8: =IF(AND(ISBLANK($Q8),ISBLANK($R8),ISBLANK($S8),ISBLANK($T8),ISBLANK($U8),ISBLANK($V8),ISBLANK($W8),ISBLANK($X8),ISBLANK($Y8),ISBLANK($Z8),ISBLANK($AA8),ISBLANK($AB8)),"",SUM(AS8:BD8)) -> 0 | BG8: =IF(ISBLANK(Q8),"",AS8/Macroindicadores!B$2) -> 0 | BH8: =IF(ISBLANK(R8),"",AT8/Macroindicadores!C$2) -> 0 | BI8: =IF(ISBLANK(S8),"",AU8/Macroindicadores!D$2) -> 0 | BJ8: =IF(ISBLANK(T8),"",AV8/Macroindicadores!E$2) | BK8: =IF(ISBLANK(U8),"",AW8/Macroindicadores!F$2) | BL8: =IF(ISBLANK(V8),"",AX8/Macroindicadores!G$2) | BM8: =IF(ISBLANK(W8),"",AY8/Macroindicadores!H$2) | BN8: =IF(ISBLANK(X8),"",AZ8/Macroindicadores!I$2) | ... BR8: =IF(ISBLANK(AB8),"",BD8/Macroindicadores!M$2) | BS8: =IF(AND(ISBLANK($Q8),ISBLANK($R8),ISBLANK($S8),ISBLANK($T8),ISBLANK($U8),ISBLANK($V8),ISBLANK($W8),ISBLANK($X8),ISBLANK($Y8),ISBLANK($Z8),ISBLANK($AA8),ISBLANK($AB8)),"",SUM(BG8:BR8)) -> 0 | BT8: =IF(ISBLANK($L8),"",_xlfn.XLOOKUP($L8,'CENTRO CUSTO'!$A:$A,'CENTRO CUSTO'!$E:$E,FALSE,0)) -> G&A BU
A9: =IF(ISBLANK($F9),"","Budget") -> Budget | B9: =IF(ISBLANK($F9),"",$F$1) -> 2026 | C9: =IF(ISBLANK($L9),"",_xlfn.XLOOKUP($L9,'CENTRO CUSTO'!$A:$A,'CENTRO CUSTO'!F:F,FALSE,0)) -> Martini Meat | D9: =IF(ISBLANK($L9),"",_xlfn.XLOOKUP($L9,'CENTRO CUSTO'!$A:$A,'CENTRO CUSTO'!G:G,FALSE,0)) -> BU-MMAZ | E9: =IF(ISBLANK($L9),"",_xlfn.XLOOKUP($L9,'CENTRO CUSTO'!$A:$A,'CENTRO CUSTO'!H:H,FALSE,0)) -> G&A | F9: RAVANEDA | G9: Applications support and maintenance | H9: SAP R3 - AMS | I9: Existente | J9: Mensal | K9: Contrato em Curso | L9: BU-MMAZ | TI | M9: =IF(ISBLANK($L9),"",_xlfn.XLOOKUP($L9,'CENTRO CUSTO'!$A:$A,'CENTRO CUSTO'!D:D,FALSE,0)) -> Alexandre Ayabe | N9: Manutenção de Informática | P9: BRL | Q9: =35000*Rateio!$E$4 -> 35000 | R9: =35000*Rateio!$E$4 -> 35000 | S9: =35000*Rateio!$E$4 -> 35000 | AC9: =IF(AND(ISBLANK($Q9),ISBLANK($R9),ISBLANK($S9),ISBLANK($T9),ISBLANK($U9),ISBLANK($V9),ISBLANK($W9),ISBLANK($X9),ISBLANK($Y9),ISBLANK($Z9),ISBLANK($AA9),ISBLANK($AB9)),"",SUM(Q9:AB9)) -> 105000 | AE9: =IF(ISBLANK(Q9),"",IF($P9="BRL",Q9,Q9*Macroindicadores!B$2)/1000) -> 35 | AF9: =IF(ISBLANK(R9),"",IF($P9="BRL",R9,R9*Macroindicadores!C$2)/1000) -> 35 | AG9: =IF(ISBLANK(S9),"",IF($P9="BRL",S9,S9*Macroindicadores!D$2)/1000) -> 35 | AH9: =IF(ISBLANK(T9),"",IF($P9="BRL",T9,T9*Macroindicadores!E$2)/1000) | AI9: =IF(ISBLANK(U9),"",IF($P9="BRL",U9,U9*Macroindicadores!F$2)/1000) | AJ9: =IF(ISBLANK(V9),"",IF($P9="BRL",V9,V9*Macroindicadores!G$2)/1000) | AK9: =IF(ISBLANK(W9),"",IF($P9="BRL",W9,W9*Macroindicadores!H$2)/1000) | AL9: =IF(ISBLANK(X9),"",IF($P9="BRL",X9,X9*Macroindicadores!I$2)/1000) | ... AP9: =IF(ISBLANK(AB9),"",IF($P9="BRL",AB9,AB9*Macroindicadores!M$2)/1000) | AQ9: =IF(AND(ISBLANK($Q9),ISBLANK($R9),ISBLANK($S9),ISBLANK($T9),ISBLANK($U9),ISBLANK($V9),ISBLANK($W9),ISBLANK($X9),ISBLANK($Y9),ISBLANK($Z9),ISBLANK($AA9),ISBLANK($AB9)),"",SUM(AE9:AP9)) -> 105 | AS9: =IF(ISBLANK(Q9),"",IF(ISBLANK($O9),AE9,IF($J9="ANUAL",AE9*(1+Macroindicadores!B$7),IF(AND($I9="NOVO",MONTH($O9)=MONTH(AS$4)),AE9*(1+Macroindicadores!B$7),IF(AND($J9="PONTUAL",MONTH($O9)=MONTH(AS$4)),AE9*(1+Macroindicadores!B$7),IF(AND($J9="PONTUAL",MONTH($O9)<MONTH(AS$4)),MIN(AR9:$AS9),IF(AND($I9="NOVO",MONTH($O9)>MONTH(AS$4)),AE9,IF(MONTH($O9)>MONTH(AS$4),AE9,IF(MONTH($O9)=MONTH(AS$4),AE9*(1+Macroindicadores!B$7),AR9))))))))) -> 35 | AT9: =IF(ISBLANK(R9),"",IF(ISBLANK($O9),AF9,IF($J9="ANUAL",AF9*(1+Macroindicadores!C$7),IF(AND($I9="NOVO",MONTH($O9)=MONTH(AT$4)),AF9*(1+Macroindicadores!C$7),IF(AND($J9="PONTUAL",MONTH($O9)=MONTH(AT$4)),AF9*(1+Macroindicadores!C$7),IF(AND($J9="PONTUAL",MONTH($O9)<MONTH(AT$4)),MIN($AS9:AS9),IF(AND($I9="NOVO",MONTH($O9)>MONTH(AT$4)),AF9,IF(MONTH($O9)>MONTH(AT$4),AF9,IF(MONTH($O9)=MONTH(AT$4),AF9*(1+Macroindicadores!C$7),AS9))))))))) -> 35 | AU9: =IF(ISBLANK(S9),"",IF(ISBLANK($O9),AG9,IF($J9="ANUAL",AG9*(1+Macroindicadores!D$7),IF(AND($I9="NOVO",MONTH($O9)=MONTH(AU$4)),AG9*(1+Macroindicadores!D$7),IF(AND($J9="PONTUAL",MONTH($O9)=MONTH(AU$4)),AG9*(1+Macroindicadores!D$7),IF(AND($J9="PONTUAL",MONTH($O9)<MONTH(AU$4)),MIN($AS9:AT9),IF(AND($I9="NOVO",MONTH($O9)>MONTH(AU$4)),AG9,IF(MONTH($O9)>MONTH(AU$4),AG9,IF(MONTH($O9)=MONTH(AU$4),AG9*(1+Macroindicadores!D$7),AT9))))))))) -> 35 | AV9: =IF(ISBLANK(T9),"",IF(ISBLANK($O9),AH9,IF($J9="ANUAL",AH9*(1+Macroindicadores!E$7),IF(AND($I9="NOVO",MONTH($O9)=MONTH(AV$4)),AH9*(1+Macroindicadores!E$7),IF(AND($J9="PONTUAL",MONTH($O9)=MONTH(AV$4)),AH9*(1+Macroindicadores!E$7),IF(AND($J9="PONTUAL",MONTH($O9)<MONTH(AV$4)),MIN($AS9:AU9),IF(AND($I9="NOVO",MONTH($O9)>MONTH(AV$4)),AH9,IF(MONTH($O9)>MONTH(AV$4),AH9,IF(MONTH($O9)=MONTH(AV$4),AH9*(1+Macroindicadores!E$7),AU9))))))))) | AW9: =IF(ISBLANK(U9),"",IF(ISBLANK($O9),AI9,IF($J9="ANUAL",AI9*(1+Macroindicadores!F$7),IF(AND($I9="NOVO",MONTH($O9)=MONTH(AW$4)),AI9*(1+Macroindicadores!F$7),IF(AND($J9="PONTUAL",MONTH($O9)=MONTH(AW$4)),AI9*(1+Macroindicadores!F$7),IF(AND($J9="PONTUAL",MONTH($O9)<MONTH(AW$4)),MIN($AS9:AV9),IF(AND($I9="NOVO",MONTH($O9)>MONTH(AW$4)),AI9,IF(MONTH($O9)>MONTH(AW$4),AI9,IF(MONTH($O9)=MONTH(AW$4),AI9*(1+Macroindicadores!F$7),AV9))))))))) | AX9: =IF(ISBLANK(V9),"",IF(ISBLANK($O9),AJ9,IF($J9="ANUAL",AJ9*(1+Macroindicadores!G$7),IF(AND($I9="NOVO",MONTH($O9)=MONTH(AX$4)),AJ9*(1+Macroindicadores!G$7),IF(AND($J9="PONTUAL",MONTH($O9)=MONTH(AX$4)),AJ9*(1+Macroindicadores!G$7),IF(AND($J9="PONTUAL",MONTH($O9)<MONTH(AX$4)),MIN($AS9:AW9),IF(AND($I9="NOVO",MONTH($O9)>MONTH(AX$4)),AJ9,IF(MONTH($O9)>MONTH(AX$4),AJ9,IF(MONTH($O9)=MONTH(AX$4),AJ9*(1+Macroindicadores!G$7),AW9))))))))) | AY9: =IF(ISBLANK(W9),"",IF(ISBLANK($O9),AK9,IF($J9="ANUAL",AK9*(1+Macroindicadores!H$7),IF(AND($I9="NOVO",MONTH($O9)=MONTH(AY$4)),AK9*(1+Macroindicadores!H$7),IF(AND($J9="PONTUAL",MONTH($O9)=MONTH(AY$4)),AK9*(1+Macroindicadores!H$7),IF(AND($J9="PONTUAL",MONTH($O9)<MONTH(AY$4)),MIN($AS9:AX9),IF(AND($I9="NOVO",MONTH($O9)>MONTH(AY$4)),AK9,IF(MONTH($O9)>MONTH(AY$4),AK9,IF(MONTH($O9)=MONTH(AY$4),AK9*(1+Macroindicadores!H$7),AX9))))))))) | AZ9: =IF(ISBLANK(X9),"",IF(ISBLANK($O9),AL9,IF($J9="ANUAL",AL9*(1+Macroindicadores!I$7),IF(AND($I9="NOVO",MONTH($O9)=MONTH(AZ$4)),AL9*(1+Macroindicadores!I$7),IF(AND($J9="PONTUAL",MONTH($O9)=MONTH(AZ$4)),AL9*(1+Macroindicadores!I$7),IF(AND($J9="PONTUAL",MONTH($O9)<MONTH(AZ$4)),MIN($AS9:AY9),IF(AND($I9="NOVO",MONTH($O9)>MONTH(AZ$4)),AL9,IF(MONTH($O9)>MONTH(AZ$4),AL9,IF(MONTH($O9)=MONTH(AZ$4),AL9*(1+Macroindicadores!I$7),AY9))))))))) | BA9: =IF(ISBLANK(Y9),"",IF(ISBLANK($O9),AM9,IF($J9="ANUAL",AM9*(1+Macroindicadores!J$7),IF(AND($I9="NOVO",MONTH($O9)=MONTH(BA$4)),AM9*(1+Macroindicadores!J$7),IF(AND($J9="PONTUAL",MONTH($O9)=MONTH(BA$4)),AM9*(1+Macroindicadores!J$7),IF(AND($J9="PONTUAL",MONTH($O9)<MONTH(BA$4)),MIN($AS9:AZ9),IF(AND($I9="NOVO",MONTH($O9)>MONTH(BA$4)),AM9,IF(MONTH($O9)>MONTH(BA$4),AM9,IF(MONTH($O9)=MONTH(BA$4),AM9*(1+Macroindicadores!J$7),AZ9))))))))) | ... BD9: =IF(ISBLANK(AB9),"",IF(ISBLANK($O9),AP9,IF($J9="ANUAL",AP9*(1+Macroindicadores!M$7),IF(AND($I9="NOVO",MONTH($O9)=MONTH(BD$4)),AP9*(1+Macroindicadores!M$7),IF(AND($J9="PONTUAL",MONTH($O9)=MONTH(BD$4)),AP9*(1+Macroindicadores!M$7),IF(AND($J9="PONTUAL",MONTH($O9)<MONTH(BD$4)),MIN($AS9:BC9),IF(AND($I9="NOVO",MONTH($O9)>MONTH(BD$4)),AP9,IF(MONTH($O9)>MONTH(BD$4),AP9,IF(MONTH($O9)=MONTH(BD$4),AP9*(1+Macroindicadores!M$7),BC9))))))))) | BE9: =IF(AND(ISBLANK($Q9),ISBLANK($R9),ISBLANK($S9),ISBLANK($T9),ISBLANK($U9),ISBLANK($V9),ISBLANK($W9),ISBLANK($X9),ISBLANK($Y9),ISBLANK($Z9),ISBLANK($AA9),ISBLANK($AB9)),"",SUM(AS9:BD9)) -> 105 | BG9: =IF(ISBLANK(Q9),"",AS9/Macroindicadores!B$2) -> 5.952381 | BH9: =IF(ISBLANK(R9),"",AT9/Macroindicadores!C$2) -> 5.952381 | BI9: =IF(ISBLANK(S9),"",AU9/Macroindicadores!D$2) -> 5.952381 | BJ9: =IF(ISBLANK(T9),"",AV9/Macroindicadores!E$2) | BK9: =IF(ISBLANK(U9),"",AW9/Macroindicadores!F$2) | BL9: =IF(ISBLANK(V9),"",AX9/Macroindicadores!G$2) | BM9: =IF(ISBLANK(W9),"",AY9/Macroindicadores!H$2) | BN9: =IF(ISBLANK(X9),"",AZ9/Macroindicadores!I$2) | ... BR9: =IF(ISBLANK(AB9),"",BD9/Macroindicadores!M$2) | BS9: =IF(AND(ISBLANK($Q9),ISBLANK($R9),ISBLANK($S9),ISBLANK($T9),ISBLANK($U9),ISBLANK($V9),ISBLANK($W9),ISBLANK($X9),ISBLANK($Y9),ISBLANK($Z9),ISBLANK($AA9),ISBLANK($AB9)),"",SUM(BG9:BR9)) -> 17.857143 | BT9: =IF(ISBLANK($L9),"",_xlfn.XLOOKUP($L9,'CENTRO CUSTO'!$A:$A,'CENTRO CUSTO'!$E:$E,FALSE,0)) -> G&A BU
A10: =IF(ISBLANK($F10),"","Budget") -> Budget | B10: =IF(ISBLANK($F10),"",$F$1) -> 2026 | C10: =IF(ISBLANK($L10),"",_xlfn.XLOOKUP($L10,'CENTRO CUSTO'!$A:$A,'CENTRO CUSTO'!F:F,FALSE,0)) -> Transporte | D10: =IF(ISBLANK($L10),"",_xlfn.XLOOKUP($L10,'CENTRO CUSTO'!$A:$A,'CENTRO CUSTO'!G:G,FALSE,0)) -> BU-TR | E10: =IF(ISBLANK($L10),"",_xlfn.XLOOKUP($L10,'CENTRO CUSTO'!$A:$A,'CENTRO CUSTO'!H:H,FALSE,0)) -> G&A | F10: SEIDOR | G10: Applications support and maintenance | H10: SAP S4 - Licença | I10: Novo | J10: Mensal | K10: Baixa - Eficiência | L10: BU-MMTR | TI | M10: =IF(ISBLANK($L10),"",_xlfn.XLOOKUP($L10,'CENTRO CUSTO'!$A:$A,'CENTRO CUSTO'!D:D,FALSE,0)) -> Alexandre Ayabe | N10: Licença SAP | P10: USD | Q10: =140276*Rateio!$E$33/12 -> 2104.14 | R10: =140276*Rateio!$E$33/12 -> 2104.14 | S10: =140276*Rateio!$E$33/12 -> 2104.14 | T10: =140276*Rateio!$E$33/12 -> 2104.14 | U10: =140276*Rateio!$E$33/12 -> 2104.14 | V10: =140276*Rateio!$E$33/12 -> 2104.14 | W10: =140276*Rateio!$E$33/12 -> 2104.14 | X10: =140276*Rateio!$E$33/12 -> 2104.14 | ... AB10: =140276*Rateio!$E$33/12 -> 2104.14 | AC10: =IF(AND(ISBLANK($Q10),ISBLANK($R10),ISBLANK($S10),ISBLANK($T10),ISBLANK($U10),ISBLANK($V10),ISBLANK($W10),ISBLANK($X10),ISBLANK($Y10),ISBLANK($Z10),ISBLANK($AA10),ISBLANK($AB10)),"",SUM(Q10:AB10)) -> 25249.68 | AE10: =IF(ISBLANK(Q10),"",IF($P10="BRL",Q10,Q10*Macroindicadores!B$2)/1000) -> 12.372343 | AF10: =IF(ISBLANK(R10),"",IF($P10="BRL",R10,R10*Macroindicadores!C$2)/1000) -> 12.372343 | AG10: =IF(ISBLANK(S10),"",IF($P10="BRL",S10,S10*Macroindicadores!D$2)/1000) -> 12.372343 | AH10: =IF(ISBLANK(T10),"",IF($P10="BRL",T10,T10*Macroindicadores!E$2)/1000) -> 12.372343 | AI10: =IF(ISBLANK(U10),"",IF($P10="BRL",U10,U10*Macroindicadores!F$2)/1000) -> 12.372343 | AJ10: =IF(ISBLANK(V10),"",IF($P10="BRL",V10,V10*Macroindicadores!G$2)/1000) -> 12.372343 | AK10: =IF(ISBLANK(W10),"",IF($P10="BRL",W10,W10*Macroindicadores!H$2)/1000) -> 12.372343 | AL10: =IF(ISBLANK(X10),"",IF($P10="BRL",X10,X10*Macroindicadores!I$2)/1000) -> 12.372343 | ... AP10: =IF(ISBLANK(AB10),"",IF($P10="BRL",AB10,AB10*Macroindicadores!M$2)/1000) -> 12.372343 | AQ10: =IF(AND(ISBLANK($Q10),ISBLANK($R10),ISBLANK($S10),ISBLANK($T10),ISBLANK($U10),ISBLANK($V10),ISBLANK($W10),ISBLANK($X10),ISBLANK($Y10),ISBLANK($Z10),ISBLANK($AA10),ISBLANK($AB10)),"",SUM(AE10:AP10)) -> 148.46812 | AS10: =IF(ISBLANK(Q10),"",IF(ISBLANK($O10),AE10,IF($J10="ANUAL",AE10*(1+Macroindicadores!B$7),IF(AND($I10="NOVO",MONTH($O10)=MONTH(AS$4)),AE10*(1+Macroindicadores!B$7),IF(AND($J10="PONTUAL",MONTH($O10)=MONTH(AS$4)),AE10*(1+Macroindicadores!B$7),IF(AND($J10="PONTUAL",MONTH($O10)<MONTH(AS$4)),MIN(AR10:$AS10),IF(AND($I10="NOVO",MONTH($O10)>MONTH(AS$4)),AE10,IF(MONTH($O10)>MONTH(AS$4),AE10,IF(MONTH($O10)=MONTH(AS$4),AE10*(1+Macroindicadores!B$7),AR10))))))))) -> 12.372343 | AT10: =IF(ISBLANK(R10),"",IF(ISBLANK($O10),AF10,IF($J10="ANUAL",AF10*(1+Macroindicadores!C$7),IF(AND($I10="NOVO",MONTH($O10)=MONTH(AT$4)),AF10*(1+Macroindicadores!C$7),IF(AND($J10="PONTUAL",MONTH($O10)=MONTH(AT$4)),AF10*(1+Macroindicadores!C$7),IF(AND($J10="PONTUAL",MONTH($O10)<MONTH(AT$4)),MIN($AS10:AS10),IF(AND($I10="NOVO",MONTH($O10)>MONTH(AT$4)),AF10,IF(MONTH($O10)>MONTH(AT$4),AF10,IF(MONTH($O10)=MONTH(AT$4),AF10*(1+Macroindicadores!C$7),AS10))))))))) -> 12.372343 | AU10: =IF(ISBLANK(S10),"",IF(ISBLANK($O10),AG10,IF($J10="ANUAL",AG10*(1+Macroindicadores!D$7),IF(AND($I10="NOVO",MONTH($O10)=MONTH(AU$4)),AG10*(1+Macroindicadores!D$7),IF(AND($J10="PONTUAL",MONTH($O10)=MONTH(AU$4)),AG10*(1+Macroindicadores!D$7),IF(AND($J10="PONTUAL",MONTH($O10)<MONTH(AU$4)),MIN($AS10:AT10),IF(AND($I10="NOVO",MONTH($O10)>MONTH(AU$4)),AG10,IF(MONTH($O10)>MONTH(AU$4),AG10,IF(MONTH($O10)=MONTH(AU$4),AG10*(1+Macroindicadores!D$7),AT10))))))))) -> 12.372343 | AV10: =IF(ISBLANK(T10),"",IF(ISBLANK($O10),AH10,IF($J10="ANUAL",AH10*(1+Macroindicadores!E$7),IF(AND($I10="NOVO",MONTH($O10)=MONTH(AV$4)),AH10*(1+Macroindicadores!E$7),IF(AND($J10="PONTUAL",MONTH($O10)=MONTH(AV$4)),AH10*(1+Macroindicadores!E$7),IF(AND($J10="PONTUAL",MONTH($O10)<MONTH(AV$4)),MIN($AS10:AU10),IF(AND($I10="NOVO",MONTH($O10)>MONTH(AV$4)),AH10,IF(MONTH($O10)>MONTH(AV$4),AH10,IF(MONTH($O10)=MONTH(AV$4),AH10*(1+Macroindicadores!E$7),AU10))))))))) -> 12.372343 | AW10: =IF(ISBLANK(U10),"",IF(ISBLANK($O10),AI10,IF($J10="ANUAL",AI10*(1+Macroindicadores!F$7),IF(AND($I10="NOVO",MONTH($O10)=MONTH(AW$4)),AI10*(1+Macroindicadores!F$7),IF(AND($J10="PONTUAL",MONTH($O10)=MONTH(AW$4)),AI10*(1+Macroindicadores!F$7),IF(AND($J10="PONTUAL",MONTH($O10)<MONTH(AW$4)),MIN($AS10:AV10),IF(AND($I10="NOVO",MONTH($O10)>MONTH(AW$4)),AI10,IF(MONTH($O10)>MONTH(AW$4),AI10,IF(MONTH($O10)=MONTH(AW$4),AI10*(1+Macroindicadores!F$7),AV10))))))))) -> 12.372343 | AX10: =IF(ISBLANK(V10),"",IF(ISBLANK($O10),AJ10,IF($J10="ANUAL",AJ10*(1+Macroindicadores!G$7),IF(AND($I10="NOVO",MONTH($O10)=MONTH(AX$4)),AJ10*(1+Macroindicadores!G$7),IF(AND($J10="PONTUAL",MONTH($O10)=MONTH(AX$4)),AJ10*(1+Macroindicadores!G$7),IF(AND($J10="PONTUAL",MONTH($O10)<MONTH(AX$4)),MIN($AS10:AW10),IF(AND($I10="NOVO",MONTH($O10)>MONTH(AX$4)),AJ10,IF(MONTH($O10)>MONTH(AX$4),AJ10,IF(MONTH($O10)=MONTH(AX$4),AJ10*(1+Macroindicadores!G$7),AW10))))))))) -> 12.372343 | AY10: =IF(ISBLANK(W10),"",IF(ISBLANK($O10),AK10,IF($J10="ANUAL",AK10*(1+Macroindicadores!H$7),IF(AND($I10="NOVO",MONTH($O10)=MONTH(AY$4)),AK10*(1+Macroindicadores!H$7),IF(AND($J10="PONTUAL",MONTH($O10)=MONTH(AY$4)),AK10*(1+Macroindicadores!H$7),IF(AND($J10="PONTUAL",MONTH($O10)<MONTH(AY$4)),MIN($AS10:AX10),IF(AND($I10="NOVO",MONTH($O10)>MONTH(AY$4)),AK10,IF(MONTH($O10)>MONTH(AY$4),AK10,IF(MONTH($O10)=MONTH(AY$4),AK10*(1+Macroindicadores!H$7),AX10))))))))) -> 12.372343 | AZ10: =IF(ISBLANK(X10),"",IF(ISBLANK($O10),AL10,IF($J10="ANUAL",AL10*(1+Macroindicadores!I$7),IF(AND($I10="NOVO",MONTH($O10)=MONTH(AZ$4)),AL10*(1+Macroindicadores!I$7),IF(AND($J10="PONTUAL",MONTH($O10)=MONTH(AZ$4)),AL10*(1+Macroindicadores!I$7),IF(AND($J10="PONTUAL",MONTH($O10)<MONTH(AZ$4)),MIN($AS10:AY10),IF(AND($I10="NOVO",MONTH($O10)>MONTH(AZ$4)),AL10,IF(MONTH($O10)>MONTH(AZ$4),AL10,IF(MONTH($O10)=MONTH(AZ$4),AL10*(1+Macroindicadores!I$7),AY10))))))))) -> 12.372343 | BA10: =IF(ISBLANK(Y10),"",IF(ISBLANK($O10),AM10,IF($J10="ANUAL",AM10*(1+Macroindicadores!J$7),IF(AND($I10="NOVO",MONTH($O10)=MONTH(BA$4)),AM10*(1+Macroindicadores!J$7),IF(AND($J10="PONTUAL",MONTH($O10)=MONTH(BA$4)),AM10*(1+Macroindicadores!J$7),IF(AND($J10="PONTUAL",MONTH($O10)<MONTH(BA$4)),MIN($AS10:AZ10),IF(AND($I10="NOVO",MONTH($O10)>MONTH(BA$4)),AM10,IF(MONTH($O10)>MONTH(BA$4),AM10,IF(MONTH($O10)=MONTH(BA$4),AM10*(1+Macroindicadores!J$7),AZ10))))))))) -> 12.372343 | ... BD10: =IF(ISBLANK(AB10),"",IF(ISBLANK($O10),AP10,IF($J10="ANUAL",AP10*(1+Macroindicadores!M$7),IF(AND($I10="NOVO",MONTH($O10)=MONTH(BD$4)),AP10*(1+Macroindicadores!M$7),IF(AND($J10="PONTUAL",MONTH($O10)=MONTH(BD$4)),AP10*(1+Macroindicadores!M$7),IF(AND($J10="PONTUAL",MONTH($O10)<MONTH(BD$4)),MIN($AS10:BC10),IF(AND($I10="NOVO",MONTH($O10)>MONTH(BD$4)),AP10,IF(MONTH($O10)>MONTH(BD$4),AP10,IF(MONTH($O10)=MONTH(BD$4),AP10*(1+Macroindicadores!M$7),BC10))))))))) -> 12.372343 | BE10: =IF(AND(ISBLANK($Q10),ISBLANK($R10),ISBLANK($S10),ISBLANK($T10),ISBLANK($U10),ISBLANK($V10),ISBLANK($W10),ISBLANK($X10),ISBLANK($Y10),ISBLANK($Z10),ISBLANK($AA10),ISBLANK($AB10)),"",SUM(AS10:BD10)) -> 148.46812 | BG10: =IF(ISBLANK(Q10),"",AS10/Macroindicadores!B$2) -> 2.10414 | BH10: =IF(ISBLANK(R10),"",AT10/Macroindicadores!C$2) -> 2.10414 | BI10: =IF(ISBLANK(S10),"",AU10/Macroindicadores!D$2) -> 2.10414 | BJ10: =IF(ISBLANK(T10),"",AV10/Macroindicadores!E$2) -> 2.10414 | BK10: =IF(ISBLANK(U10),"",AW10/Macroindicadores!F$2) -> 2.10414 | BL10: =IF(ISBLANK(V10),"",AX10/Macroindicadores!G$2) -> 2.10414 | BM10: =IF(ISBLANK(W10),"",AY10/Macroindicadores!H$2) -> 2.10414 | BN10: =IF(ISBLANK(X10),"",AZ10/Macroindicadores!I$2) -> 2.10414 | ... BR10: =IF(ISBLANK(AB10),"",BD10/Macroindicadores!M$2) -> 2.10414 | BS10: =IF(AND(ISBLANK($Q10),ISBLANK($R10),ISBLANK($S10),ISBLANK($T10),ISBLANK($U10),ISBLANK($V10),ISBLANK($W10),ISBLANK($X10),ISBLANK($Y10),ISBLANK($Z10),ISBLANK($AA10),ISBLANK($AB10)),"",SUM(BG10:BR10)) -> 25.24968 | BT10: =IF(ISBLANK($L10),"",_xlfn.XLOOKUP($L10,'CENTRO CUSTO'!$A:$A,'CENTRO CUSTO'!$E:$E,FALSE,0)) -> G&A BU
A11: =IF(ISBLANK($F11),"","Budget") -> Budget | B11: =IF(ISBLANK($F11),"",$F$1) -> 2026 | C11: =IF(ISBLANK($L11),"",_xlfn.XLOOKUP($L11,'CENTRO CUSTO'!$A:$A,'CENTRO CUSTO'!F:F,FALSE,0)) -> Martini Meat | D11: =IF(ISBLANK($L11),"",_xlfn.XLOOKUP($L11,'CENTRO CUSTO'!$A:$A,'CENTRO CUSTO'!G:G,FALSE,0)) -> BU-MMAZ | E11: =IF(ISBLANK($L11),"",_xlfn.XLOOKUP($L11,'CENTRO CUSTO'!$A:$A,'CENTRO CUSTO'!H:H,FALSE,0)) -> G&A | F11: SEIDOR | G11: Applications support and maintenance | H11: SAP S4 - Licença | I11: Novo | J11: Mensal | K11: Contrato em Curso | L11: BU-MMAZ | TI | M11: =IF(ISBLANK($L11),"",_xlfn.XLOOKUP($L11,'CENTRO CUSTO'!$A:$A,'CENTRO CUSTO'!D:D,FALSE,0)) -> Alexandre Ayabe | N11: Licença SAP | P11: USD | Q11: =140276*Rateio!$E$34/12 -> 5611.04 | R11: =140276*Rateio!$E$34/12 -> 5611.04 | S11: =140276*Rateio!$E$34/12 -> 5611.04 | T11: =140276*Rateio!$E$34/12 -> 5611.04 | U11: =140276*Rateio!$E$34/12 -> 5611.04 | V11: =140276*Rateio!$E$34/12 -> 5611.04 | W11: =140276*Rateio!$E$34/12 -> 5611.04 | X11: =140276*Rateio!$E$34/12 -> 5611.04 | ... AB11: =140276*Rateio!$E$34/12 -> 5611.04 | AC11: =IF(AND(ISBLANK($Q11),ISBLANK($R11),ISBLANK($S11),ISBLANK($T11),ISBLANK($U11),ISBLANK($V11),ISBLANK($W11),ISBLANK($X11),ISBLANK($Y11),ISBLANK($Z11),ISBLANK($AA11),ISBLANK($AB11)),"",SUM(Q11:AB11)) -> 67332.48 | AE11: =IF(ISBLANK(Q11),"",IF($P11="BRL",Q11,Q11*Macroindicadores!B$2)/1000) -> 32.992915 | AF11: =IF(ISBLANK(R11),"",IF($P11="BRL",R11,R11*Macroindicadores!C$2)/1000) -> 32.992915 | AG11: =IF(ISBLANK(S11),"",IF($P11="BRL",S11,S11*Macroindicadores!D$2)/1000) -> 32.992915 | AH11: =IF(ISBLANK(T11),"",IF($P11="BRL",T11,T11*Macroindicadores!E$2)/1000) -> 32.992915 | AI11: =IF(ISBLANK(U11),"",IF($P11="BRL",U11,U11*Macroindicadores!F$2)/1000) -> 32.992915 | AJ11: =IF(ISBLANK(V11),"",IF($P11="BRL",V11,V11*Macroindicadores!G$2)/1000) -> 32.992915 | AK11: =IF(ISBLANK(W11),"",IF($P11="BRL",W11,W11*Macroindicadores!H$2)/1000) -> 32.992915 | AL11: =IF(ISBLANK(X11),"",IF($P11="BRL",X11,X11*Macroindicadores!I$2)/1000) -> 32.992915 | ... AP11: =IF(ISBLANK(AB11),"",IF($P11="BRL",AB11,AB11*Macroindicadores!M$2)/1000) -> 32.992915 | AQ11: =IF(AND(ISBLANK($Q11),ISBLANK($R11),ISBLANK($S11),ISBLANK($T11),ISBLANK($U11),ISBLANK($V11),ISBLANK($W11),ISBLANK($X11),ISBLANK($Y11),ISBLANK($Z11),ISBLANK($AA11),ISBLANK($AB11)),"",SUM(AE11:AP11)) -> 395.91498 | AS11: =IF(ISBLANK(Q11),"",IF(ISBLANK($O11),AE11,IF($J11="ANUAL",AE11*(1+Macroindicadores!B$7),IF(AND($I11="NOVO",MONTH($O11)=MONTH(AS$4)),AE11*(1+Macroindicadores!B$7),IF(AND($J11="PONTUAL",MONTH($O11)=MONTH(AS$4)),AE11*(1+Macroindicadores!B$7),IF(AND($J11="PONTUAL",MONTH($O11)<MONTH(AS$4)),MIN(AR11:$AS11),IF(AND($I11="NOVO",MONTH($O11)>MONTH(AS$4)),AE11,IF(MONTH($O11)>MONTH(AS$4),AE11,IF(MONTH($O11)=MONTH(AS$4),AE11*(1+Macroindicadores!B$7),AR11))))))))) -> 32.992915 | AT11: =IF(ISBLANK(R11),"",IF(ISBLANK($O11),AF11,IF($J11="ANUAL",AF11*(1+Macroindicadores!C$7),IF(AND($I11="NOVO",MONTH($O11)=MONTH(AT$4)),AF11*(1+Macroindicadores!C$7),IF(AND($J11="PONTUAL",MONTH($O11)=MONTH(AT$4)),AF11*(1+Macroindicadores!C$7),IF(AND($J11="PONTUAL",MONTH($O11)<MONTH(AT$4)),MIN($AS11:AS11),IF(AND($I11="NOVO",MONTH($O11)>MONTH(AT$4)),AF11,IF(MONTH($O11)>MONTH(AT$4),AF11,IF(MONTH($O11)=MONTH(AT$4),AF11*(1+Macroindicadores!C$7),AS11))))))))) -> 32.992915 | AU11: =IF(ISBLANK(S11),"",IF(ISBLANK($O11),AG11,IF($J11="ANUAL",AG11*(1+Macroindicadores!D$7),IF(AND($I11="NOVO",MONTH($O11)=MONTH(AU$4)),AG11*(1+Macroindicadores!D$7),IF(AND($J11="PONTUAL",MONTH($O11)=MONTH(AU$4)),AG11*(1+Macroindicadores!D$7),IF(AND($J11="PONTUAL",MONTH($O11)<MONTH(AU$4)),MIN($AS11:AT11),IF(AND($I11="NOVO",MONTH($O11)>MONTH(AU$4)),AG11,IF(MONTH($O11)>MONTH(AU$4),AG11,IF(MONTH($O11)=MONTH(AU$4),AG11*(1+Macroindicadores!D$7),AT11))))))))) -> 32.992915 | AV11: =IF(ISBLANK(T11),"",IF(ISBLANK($O11),AH11,IF($J11="ANUAL",AH11*(1+Macroindicadores!E$7),IF(AND($I11="NOVO",MONTH($O11)=MONTH(AV$4)),AH11*(1+Macroindicadores!E$7),IF(AND($J11="PONTUAL",MONTH($O11)=MONTH(AV$4)),AH11*(1+Macroindicadores!E$7),IF(AND($J11="PONTUAL",MONTH($O11)<MONTH(AV$4)),MIN($AS11:AU11),IF(AND($I11="NOVO",MONTH($O11)>MONTH(AV$4)),AH11,IF(MONTH($O11)>MONTH(AV$4),AH11,IF(MONTH($O11)=MONTH(AV$4),AH11*(1+Macroindicadores!E$7),AU11))))))))) -> 32.992915 | AW11: =IF(ISBLANK(U11),"",IF(ISBLANK($O11),AI11,IF($J11="ANUAL",AI11*(1+Macroindicadores!F$7),IF(AND($I11="NOVO",MONTH($O11)=MONTH(AW$4)),AI11*(1+Macroindicadores!F$7),IF(AND($J11="PONTUAL",MONTH($O11)=MONTH(AW$4)),AI11*(1+Macroindicadores!F$7),IF(AND($J11="PONTUAL",MONTH($O11)<MONTH(AW$4)),MIN($AS11:AV11),IF(AND($I11="NOVO",MONTH($O11)>MONTH(AW$4)),AI11,IF(MONTH($O11)>MONTH(AW$4),AI11,IF(MONTH($O11)=MONTH(AW$4),AI11*(1+Macroindicadores!F$7),AV11))))))))) -> 32.992915 | AX11: =IF(ISBLANK(V11),"",IF(ISBLANK($O11),AJ11,IF($J11="ANUAL",AJ11*(1+Macroindicadores!G$7),IF(AND($I11="NOVO",MONTH($O11)=MONTH(AX$4)),AJ11*(1+Macroindicadores!G$7),IF(AND($J11="PONTUAL",MONTH($O11)=MONTH(AX$4)),AJ11*(1+Macroindicadores!G$7),IF(AND($J11="PONTUAL",MONTH($O11)<MONTH(AX$4)),MIN($AS11:AW11),IF(AND($I11="NOVO",MONTH($O11)>MONTH(AX$4)),AJ11,IF(MONTH($O11)>MONTH(AX$4),AJ11,IF(MONTH($O11)=MONTH(AX$4),AJ11*(1+Macroindicadores!G$7),AW11))))))))) -> 32.992915 | AY11: =IF(ISBLANK(W11),"",IF(ISBLANK($O11),AK11,IF($J11="ANUAL",AK11*(1+Macroindicadores!H$7),IF(AND($I11="NOVO",MONTH($O11)=MONTH(AY$4)),AK11*(1+Macroindicadores!H$7),IF(AND($J11="PONTUAL",MONTH($O11)=MONTH(AY$4)),AK11*(1+Macroindicadores!H$7),IF(AND($J11="PONTUAL",MONTH($O11)<MONTH(AY$4)),MIN($AS11:AX11),IF(AND($I11="NOVO",MONTH($O11)>MONTH(AY$4)),AK11,IF(MONTH($O11)>MONTH(AY$4),AK11,IF(MONTH($O11)=MONTH(AY$4),AK11*(1+Macroindicadores!H$7),AX11))))))))) -> 32.992915 | AZ11: =IF(ISBLANK(X11),"",IF(ISBLANK($O11),AL11,IF($J11="ANUAL",AL11*(1+Macroindicadores!I$7),IF(AND($I11="NOVO",MONTH($O11)=MONTH(AZ$4)),AL11*(1+Macroindicadores!I$7),IF(AND($J11="PONTUAL",MONTH($O11)=MONTH(AZ$4)),AL11*(1+Macroindicadores!I$7),IF(AND($J11="PONTUAL",MONTH($O11)<MONTH(AZ$4)),MIN($AS11:AY11),IF(AND($I11="NOVO",MONTH($O11)>MONTH(AZ$4)),AL11,IF(MONTH($O11)>MONTH(AZ$4),AL11,IF(MONTH($O11)=MONTH(AZ$4),AL11*(1+Macroindicadores!I$7),AY11))))))))) -> 32.992915 | BA11: =IF(ISBLANK(Y11),"",IF(ISBLANK($O11),AM11,IF($J11="ANUAL",AM11*(1+Macroindicadores!J$7),IF(AND($I11="NOVO",MONTH($O11)=MONTH(BA$4)),AM11*(1+Macroindicadores!J$7),IF(AND($J11="PONTUAL",MONTH($O11)=MONTH(BA$4)),AM11*(1+Macroindicadores!J$7),IF(AND($J11="PONTUAL",MONTH($O11)<MONTH(BA$4)),MIN($AS11:AZ11),IF(AND($I11="NOVO",MONTH($O11)>MONTH(BA$4)),AM11,IF(MONTH($O11)>MONTH(BA$4),AM11,IF(MONTH($O11)=MONTH(BA$4),AM11*(1+Macroindicadores!J$7),AZ11))))))))) -> 32.992915 | ... BD11: =IF(ISBLANK(AB11),"",IF(ISBLANK($O11),AP11,IF($J11="ANUAL",AP11*(1+Macroindicadores!M$7),IF(AND($I11="NOVO",MONTH($O11)=MONTH(BD$4)),AP11*(1+Macroindicadores!M$7),IF(AND($J11="PONTUAL",MONTH($O11)=MONTH(BD$4)),AP11*(1+Macroindicadores!M$7),IF(AND($J11="PONTUAL",MONTH($O11)<MONTH(BD$4)),MIN($AS11:BC11),IF(AND($I11="NOVO",MONTH($O11)>MONTH(BD$4)),AP11,IF(MONTH($O11)>MONTH(BD$4),AP11,IF(MONTH($O11)=MONTH(BD$4),AP11*(1+Macroindicadores!M$7),BC11))))))))) -> 32.992915 | BE11: =IF(AND(ISBLANK($Q11),ISBLANK($R11),ISBLANK($S11),ISBLANK($T11),ISBLANK($U11),ISBLANK($V11),ISBLANK($W11),ISBLANK($X11),ISBLANK($Y11),ISBLANK($Z11),ISBLANK($AA11),ISBLANK($AB11)),"",SUM(AS11:BD11)) -> 395.91498 | BG11: =IF(ISBLANK(Q11),"",AS11/Macroindicadores!B$2) -> 5.61104 | BH11: =IF(ISBLANK(R11),"",AT11/Macroindicadores!C$2) -> 5.61104 | BI11: =IF(ISBLANK(S11),"",AU11/Macroindicadores!D$2) -> 5.61104 | BJ11: =IF(ISBLANK(T11),"",AV11/Macroindicadores!E$2) -> 5.61104 | BK11: =IF(ISBLANK(U11),"",AW11/Macroindicadores!F$2) -> 5.61104 | BL11: =IF(ISBLANK(V11),"",AX11/Macroindicadores!G$2) -> 5.61104 | BM11: =IF(ISBLANK(W11),"",AY11/Macroindicadores!H$2) -> 5.61104 | BN11: =IF(ISBLANK(X11),"",AZ11/Macroindicadores!I$2) -> 5.61104 | ... BR11: =IF(ISBLANK(AB11),"",BD11/Macroindicadores!M$2) -> 5.61104 | BS11: =IF(AND(ISBLANK($Q11),ISBLANK($R11),ISBLANK($S11),ISBLANK($T11),ISBLANK($U11),ISBLANK($V11),ISBLANK($W11),ISBLANK($X11),ISBLANK($Y11),ISBLANK($Z11),ISBLANK($AA11),ISBLANK($AB11)),"",SUM(BG11:BR11)) -> 67.33248 | BT11: =IF(ISBLANK($L11),"",_xlfn.XLOOKUP($L11,'CENTRO CUSTO'!$A:$A,'CENTRO CUSTO'!$E:$E,FALSE,0)) -> G&A BU
A12: =IF(ISBLANK($F12),"","Budget") -> Budget | B12: =IF(ISBLANK($F12),"",$F$1) -> 2026 | C12: =IF(ISBLANK($L12),"",_xlfn.XLOOKUP($L12,'CENTRO CUSTO'!$A:$A,'CENTRO CUSTO'!F:F,FALSE,0)) -> MRV | D12: =IF(ISBLANK($L12),"",_xlfn.XLOOKUP($L12,'CENTRO CUSTO'!$A:$A,'CENTRO CUSTO'!G:G,FALSE,0)) -> BU-MRV | E12: =IF(ISBLANK($L12),"",_xlfn.XLOOKUP($L12,'CENTRO CUSTO'!$A:$A,'CENTRO CUSTO'!H:H,FALSE,0)) -> G&A | F12: SEIDOR | G12: Applications support and maintenance | H12: SAP S4 - Licença | I12: Novo | J12: Mensal | K12: Contrato em Curso | L12: BU-MRV | TI | M12: =IF(ISBLANK($L12),"",_xlfn.XLOOKUP($L12,'CENTRO CUSTO'!$A:$A,'CENTRO CUSTO'!D:D,FALSE,0)) -> Alexandre Ayabe | N12: Licença SAP | P12: USD | Q12: =140276*Rateio!$E$50/12 -> 584.48333 | R12: =140276*Rateio!$E$50/12 -> 584.48333 | S12: =140276*Rateio!$E$50/12 -> 584.48333 | T12: =140276*Rateio!$E$50/12 -> 584.48333 | U12: =140276*Rateio!$E$50/12 -> 584.48333 | V12: =140276*Rateio!$E$50/12 -> 584.48333 | W12: =140276*Rateio!$E$50/12 -> 584.48333 | X12: =140276*Rateio!$E$50/12 -> 584.48333 | ... AB12: =140276*Rateio!$E$50/12 -> 584.48333 | AC12: =IF(AND(ISBLANK($Q12),ISBLANK($R12),ISBLANK($S12),ISBLANK($T12),ISBLANK($U12),ISBLANK($V12),ISBLANK($W12),ISBLANK($X12),ISBLANK($Y12),ISBLANK($Z12),ISBLANK($AA12),ISBLANK($AB12)),"",SUM(Q12:AB12)) -> 7013.8 | AE12: =IF(ISBLANK(Q12),"",IF($P12="BRL",Q12,Q12*Macroindicadores!B$2)/1000) -> 3.436762 | AF12: =IF(ISBLANK(R12),"",IF($P12="BRL",R12,R12*Macroindicadores!C$2)/1000) -> 3.436762 | AG12: =IF(ISBLANK(S12),"",IF($P12="BRL",S12,S12*Macroindicadores!D$2)/1000) -> 3.436762 | AH12: =IF(ISBLANK(T12),"",IF($P12="BRL",T12,T12*Macroindicadores!E$2)/1000) -> 3.436762 | AI12: =IF(ISBLANK(U12),"",IF($P12="BRL",U12,U12*Macroindicadores!F$2)/1000) -> 3.436762 | AJ12: =IF(ISBLANK(V12),"",IF($P12="BRL",V12,V12*Macroindicadores!G$2)/1000) -> 3.436762 | AK12: =IF(ISBLANK(W12),"",IF($P12="BRL",W12,W12*Macroindicadores!H$2)/1000) -> 3.436762 | AL12: =IF(ISBLANK(X12),"",IF($P12="BRL",X12,X12*Macroindicadores!I$2)/1000) -> 3.436762 | ... AP12: =IF(ISBLANK(AB12),"",IF($P12="BRL",AB12,AB12*Macroindicadores!M$2)/1000) -> 3.436762 | AQ12: =IF(AND(ISBLANK($Q12),ISBLANK($R12),ISBLANK($S12),ISBLANK($T12),ISBLANK($U12),ISBLANK($V12),ISBLANK($W12),ISBLANK($X12),ISBLANK($Y12),ISBLANK($Z12),ISBLANK($AA12),ISBLANK($AB12)),"",SUM(AE12:AP12)) -> 41.241144 | AS12: =IF(ISBLANK(Q12),"",IF(ISBLANK($O12),AE12,IF($J12="ANUAL",AE12*(1+Macroindicadores!B$7),IF(AND($I12="NOVO",MONTH($O12)=MONTH(AS$4)),AE12*(1+Macroindicadores!B$7),IF(AND($J12="PONTUAL",MONTH($O12)=MONTH(AS$4)),AE12*(1+Macroindicadores!B$7),IF(AND($J12="PONTUAL",MONTH($O12)<MONTH(AS$4)),MIN(AR12:$AS12),IF(AND($I12="NOVO",MONTH($O12)>MONTH(AS$4)),AE12,IF(MONTH($O12)>MONTH(AS$4),AE12,IF(MONTH($O12)=MONTH(AS$4),AE12*(1+Macroindicadores!B$7),AR12))))))))) -> 3.436762 | AT12: =IF(ISBLANK(R12),"",IF(ISBLANK($O12),AF12,IF($J12="ANUAL",AF12*(1+Macroindicadores!C$7),IF(AND($I12="NOVO",MONTH($O12)=MONTH(AT$4)),AF12*(1+Macroindicadores!C$7),IF(AND($J12="PONTUAL",MONTH($O12)=MONTH(AT$4)),AF12*(1+Macroindicadores!C$7),IF(AND($J12="PONTUAL",MONTH($O12)<MONTH(AT$4)),MIN($AS12:AS12),IF(AND($I12="NOVO",MONTH($O12)>MONTH(AT$4)),AF12,IF(MONTH($O12)>MONTH(AT$4),AF12,IF(MONTH($O12)=MONTH(AT$4),AF12*(1+Macroindicadores!C$7),AS12))))))))) -> 3.436762 | AU12: =IF(ISBLANK(S12),"",IF(ISBLANK($O12),AG12,IF($J12="ANUAL",AG12*(1+Macroindicadores!D$7),IF(AND($I12="NOVO",MONTH($O12)=MONTH(AU$4)),AG12*(1+Macroindicadores!D$7),IF(AND($J12="PONTUAL",MONTH($O12)=MONTH(AU$4)),AG12*(1+Macroindicadores!D$7),IF(AND($J12="PONTUAL",MONTH($O12)<MONTH(AU$4)),MIN($AS12:AT12),IF(AND($I12="NOVO",MONTH($O12)>MONTH(AU$4)),AG12,IF(MONTH($O12)>MONTH(AU$4),AG12,IF(MONTH($O12)=MONTH(AU$4),AG12*(1+Macroindicadores!D$7),AT12))))))))) -> 3.436762 | AV12: =IF(ISBLANK(T12),"",IF(ISBLANK($O12),AH12,IF($J12="ANUAL",AH12*(1+Macroindicadores!E$7),IF(AND($I12="NOVO",MONTH($O12)=MONTH(AV$4)),AH12*(1+Macroindicadores!E$7),IF(AND($J12="PONTUAL",MONTH($O12)=MONTH(AV$4)),AH12*(1+Macroindicadores!E$7),IF(AND($J12="PONTUAL",MONTH($O12)<MONTH(AV$4)),MIN($AS12:AU12),IF(AND($I12="NOVO",MONTH($O12)>MONTH(AV$4)),AH12,IF(MONTH($O12)>MONTH(AV$4),AH12,IF(MONTH($O12)=MONTH(AV$4),AH12*(1+Macroindicadores!E$7),AU12))))))))) -> 3.436762 | AW12: =IF(ISBLANK(U12),"",IF(ISBLANK($O12),AI12,IF($J12="ANUAL",AI12*(1+Macroindicadores!F$7),IF(AND($I12="NOVO",MONTH($O12)=MONTH(AW$4)),AI12*(1+Macroindicadores!F$7),IF(AND($J12="PONTUAL",MONTH($O12)=MONTH(AW$4)),AI12*(1+Macroindicadores!F$7),IF(AND($J12="PONTUAL",MONTH($O12)<MONTH(AW$4)),MIN($AS12:AV12),IF(AND($I12="NOVO",MONTH($O12)>MONTH(AW$4)),AI12,IF(MONTH($O12)>MONTH(AW$4),AI12,IF(MONTH($O12)=MONTH(AW$4),AI12*(1+Macroindicadores!F$7),AV12))))))))) -> 3.436762 | AX12: =IF(ISBLANK(V12),"",IF(ISBLANK($O12),AJ12,IF($J12="ANUAL",AJ12*(1+Macroindicadores!G$7),IF(AND($I12="NOVO",MONTH($O12)=MONTH(AX$4)),AJ12*(1+Macroindicadores!G$7),IF(AND($J12="PONTUAL",MONTH($O12)=MONTH(AX$4)),AJ12*(1+Macroindicadores!G$7),IF(AND($J12="PONTUAL",MONTH($O12)<MONTH(AX$4)),MIN($AS12:AW12),IF(AND($I12="NOVO",MONTH($O12)>MONTH(AX$4)),AJ12,IF(MONTH($O12)>MONTH(AX$4),AJ12,IF(MONTH($O12)=MONTH(AX$4),AJ12*(1+Macroindicadores!G$7),AW12))))))))) -> 3.436762 | AY12: =IF(ISBLANK(W12),"",IF(ISBLANK($O12),AK12,IF($J12="ANUAL",AK12*(1+Macroindicadores!H$7),IF(AND($I12="NOVO",MONTH($O12)=MONTH(AY$4)),AK12*(1+Macroindicadores!H$7),IF(AND($J12="PONTUAL",MONTH($O12)=MONTH(AY$4)),AK12*(1+Macroindicadores!H$7),IF(AND($J12="PONTUAL",MONTH($O12)<MONTH(AY$4)),MIN($AS12:AX12),IF(AND($I12="NOVO",MONTH($O12)>MONTH(AY$4)),AK12,IF(MONTH($O12)>MONTH(AY$4),AK12,IF(MONTH($O12)=MONTH(AY$4),AK12*(1+Macroindicadores!H$7),AX12))))))))) -> 3.436762 | AZ12: =IF(ISBLANK(X12),"",IF(ISBLANK($O12),AL12,IF($J12="ANUAL",AL12*(1+Macroindicadores!I$7),IF(AND($I12="NOVO",MONTH($O12)=MONTH(AZ$4)),AL12*(1+Macroindicadores!I$7),IF(AND($J12="PONTUAL",MONTH($O12)=MONTH(AZ$4)),AL12*(1+Macroindicadores!I$7),IF(AND($J12="PONTUAL",MONTH($O12)<MONTH(AZ$4)),MIN($AS12:AY12),IF(AND($I12="NOVO",MONTH($O12)>MONTH(AZ$4)),AL12,IF(MONTH($O12)>MONTH(AZ$4),AL12,IF(MONTH($O12)=MONTH(AZ$4),AL12*(1+Macroindicadores!I$7),AY12))))))))) -> 3.436762 | BA12: =IF(ISBLANK(Y12),"",IF(ISBLANK($O12),AM12,IF($J12="ANUAL",AM12*(1+Macroindicadores!J$7),IF(AND($I12="NOVO",MONTH($O12)=MONTH(BA$4)),AM12*(1+Macroindicadores!J$7),IF(AND($J12="PONTUAL",MONTH($O12)=MONTH(BA$4)),AM12*(1+Macroindicadores!J$7),IF(AND($J12="PONTUAL",MONTH($O12)<MONTH(BA$4)),MIN($AS12:AZ12),IF(AND($I12="NOVO",MONTH($O12)>MONTH(BA$4)),AM12,IF(MONTH($O12)>MONTH(BA$4),AM12,IF(MONTH($O12)=MONTH(BA$4),AM12*(1+Macroindicadores!J$7),AZ12))))))))) -> 3.436762 | ... BD12: =IF(ISBLANK(AB12),"",IF(ISBLANK($O12),AP12,IF($J12="ANUAL",AP12*(1+Macroindicadores!M$7),IF(AND($I12="NOVO",MONTH($O12)=MONTH(BD$4)),AP12*(1+Macroindicadores!M$7),IF(AND($J12="PONTUAL",MONTH($O12)=MONTH(BD$4)),AP12*(1+Macroindicadores!M$7),IF(AND($J12="PONTUAL",MONTH($O12)<MONTH(BD$4)),MIN($AS12:BC12),IF(AND($I12="NOVO",MONTH($O12)>MONTH(BD$4)),AP12,IF(MONTH($O12)>MONTH(BD$4),AP12,IF(MONTH($O12)=MONTH(BD$4),AP12*(1+Macroindicadores!M$7),BC12))))))))) -> 3.436762 | BE12: =IF(AND(ISBLANK($Q12),ISBLANK($R12),ISBLANK($S12),ISBLANK($T12),ISBLANK($U12),ISBLANK($V12),ISBLANK($W12),ISBLANK($X12),ISBLANK($Y12),ISBLANK($Z12),ISBLANK($AA12),ISBLANK($AB12)),"",SUM(AS12:BD12)) -> 41.241144 | BG12: =IF(ISBLANK(Q12),"",AS12/Macroindicadores!B$2) -> 0.58448333 | BH12: =IF(ISBLANK(R12),"",AT12/Macroindicadores!C$2) -> 0.58448333 | BI12: =IF(ISBLANK(S12),"",AU12/Macroindicadores!D$2) -> 0.58448333 | BJ12: =IF(ISBLANK(T12),"",AV12/Macroindicadores!E$2) -> 0.58448333 | BK12: =IF(ISBLANK(U12),"",AW12/Macroindicadores!F$2) -> 0.58448333 | BL12: =IF(ISBLANK(V12),"",AX12/Macroindicadores!G$2) -> 0.58448333 | BM12: =IF(ISBLANK(W12),"",AY12/Macroindicadores!H$2) -> 0.58448333 | BN12: =IF(ISBLANK(X12),"",AZ12/Macroindicadores!I$2) -> 0.58448333 | ... BR12: =IF(ISBLANK(AB12),"",BD12/Macroindicadores!M$2) -> 0.58448333 | BS12: =IF(AND(ISBLANK($Q12),ISBLANK($R12),ISBLANK($S12),ISBLANK($T12),ISBLANK($U12),ISBLANK($V12),ISBLANK($W12),ISBLANK($X12),ISBLANK($Y12),ISBLANK($Z12),ISBLANK($AA12),ISBLANK($AB12)),"",SUM(BG12:BR12)) -> 7.0138 | BT12: =IF(ISBLANK($L12),"",_xlfn.XLOOKUP($L12,'CENTRO CUSTO'!$A:$A,'CENTRO CUSTO'!$E:$E,FALSE,0)) -> G&A BU
A13: =IF(ISBLANK($F13),"","Budget") -> Budget | B13: =IF(ISBLANK($F13),"",$F$1) -> 2026 | C13: =IF(ISBLANK($L13),"",_xlfn.XLOOKUP($L13,'CENTRO CUSTO'!$A:$A,'CENTRO CUSTO'!F:F,FALSE,0)) -> SKM | D13: =IF(ISBLANK($L13),"",_xlfn.XLOOKUP($L13,'CENTRO CUSTO'!$A:$A,'CENTRO CUSTO'!G:G,FALSE,0)) -> BU-SKM | E13: =IF(ISBLANK($L13),"",_xlfn.XLOOKUP($L13,'CENTRO CUSTO'!$A:$A,'CENTRO CUSTO'!H:H,FALSE,0)) -> G&A | F13: SEIDOR | G13: Applications support and maintenance | H13: SAP S4 - Licença | I13: Existente | J13: Mensal | K13: Contrato em Curso | L13: BU-GRU | TI | M13: =IF(ISBLANK($L13),"",_xlfn.XLOOKUP($L13,'CENTRO CUSTO'!$A:$A,'CENTRO CUSTO'!D:D,FALSE,0)) -> Alexandre Ayabe | N13: Licença SAP | P13: USD | Q13: =140276*Rateio!$E$53/12 -> 701.38 | R13: =140276*Rateio!$E$53/12 -> 701.38 | S13: =140276*Rateio!$E$53/12 -> 701.38 | T13: =140276*Rateio!$E$53/12 -> 701.38 | U13: =140276*Rateio!$E$53/12 -> 701.38 | V13: =140276*Rateio!$E$53/12 -> 701.38 | W13: =140276*Rateio!$E$53/12 -> 701.38 | X13: =140276*Rateio!$E$53/12 -> 701.38 | ... AB13: =140276*Rateio!$E$53/12 -> 701.38 | AC13: =IF(AND(ISBLANK($Q13),ISBLANK($R13),ISBLANK($S13),ISBLANK($T13),ISBLANK($U13),ISBLANK($V13),ISBLANK($W13),ISBLANK($X13),ISBLANK($Y13),ISBLANK($Z13),ISBLANK($AA13),ISBLANK($AB13)),"",SUM(Q13:AB13)) -> 8416.56 | AE13: =IF(ISBLANK(Q13),"",IF($P13="BRL",Q13,Q13*Macroindicadores!B$2)/1000) -> 4.1241144 | AF13: =IF(ISBLANK(R13),"",IF($P13="BRL",R13,R13*Macroindicadores!C$2)/1000) -> 4.1241144 | AG13: =IF(ISBLANK(S13),"",IF($P13="BRL",S13,S13*Macroindicadores!D$2)/1000) -> 4.1241144 | AH13: =IF(ISBLANK(T13),"",IF($P13="BRL",T13,T13*Macroindicadores!E$2)/1000) -> 4.1241144 | AI13: =IF(ISBLANK(U13),"",IF($P13="BRL",U13,U13*Macroindicadores!F$2)/1000) -> 4.1241144 | AJ13: =IF(ISBLANK(V13),"",IF($P13="BRL",V13,V13*Macroindicadores!G$2)/1000) -> 4.1241144 | AK13: =IF(ISBLANK(W13),"",IF($P13="BRL",W13,W13*Macroindicadores!H$2)/1000) -> 4.1241144 | AL13: =IF(ISBLANK(X13),"",IF($P13="BRL",X13,X13*Macroindicadores!I$2)/1000) -> 4.1241144 | ... AP13: =IF(ISBLANK(AB13),"",IF($P13="BRL",AB13,AB13*Macroindicadores!M$2)/1000) -> 4.1241144 | AQ13: =IF(AND(ISBLANK($Q13),ISBLANK($R13),ISBLANK($S13),ISBLANK($T13),ISBLANK($U13),ISBLANK($V13),ISBLANK($W13),ISBLANK($X13),ISBLANK($Y13),ISBLANK($Z13),ISBLANK($AA13),ISBLANK($AB13)),"",SUM(AE13:AP13)) -> 49.489373 | AS13: =IF(ISBLANK(Q13),"",IF(ISBLANK($O13),AE13,IF($J13="ANUAL",AE13*(1+Macroindicadores!B$7),IF(AND($I13="NOVO",MONTH($O13)=MONTH(AS$4)),AE13*(1+Macroindicadores!B$7),IF(AND($J13="PONTUAL",MONTH($O13)=MONTH(AS$4)),AE13*(1+Macroindicadores!B$7),IF(AND($J13="PONTUAL",MONTH($O13)<MONTH(AS$4)),MIN(AR13:$AS13),IF(AND($I13="NOVO",MONTH($O13)>MONTH(AS$4)),AE13,IF(MONTH($O13)>MONTH(AS$4),AE13,IF(MONTH($O13)=MONTH(AS$4),AE13*(1+Macroindicadores!B$7),AR13))))))))) -> 4.1241144 | AT13: =IF(ISBLANK(R13),"",IF(ISBLANK($O13),AF13,IF($J13="ANUAL",AF13*(1+Macroindicadores!C$7),IF(AND($I13="NOVO",MONTH($O13)=MONTH(AT$4)),AF13*(1+Macroindicadores!C$7),IF(AND($J13="PONTUAL",MONTH($O13)=MONTH(AT$4)),AF13*(1+Macroindicadores!C$7),IF(AND($J13="PONTUAL",MONTH($O13)<MONTH(AT$4)),MIN($AS13:AS13),IF(AND($I13="NOVO",MONTH($O13)>MONTH(AT$4)),AF13,IF(MONTH($O13)>MONTH(AT$4),AF13,IF(MONTH($O13)=MONTH(AT$4),AF13*(1+Macroindicadores!C$7),AS13))))))))) -> 4.1241144 | AU13: =IF(ISBLANK(S13),"",IF(ISBLANK($O13),AG13,IF($J13="ANUAL",AG13*(1+Macroindicadores!D$7),IF(AND($I13="NOVO",MONTH($O13)=MONTH(AU$4)),AG13*(1+Macroindicadores!D$7),IF(AND($J13="PONTUAL",MONTH($O13)=MONTH(AU$4)),AG13*(1+Macroindicadores!D$7),IF(AND($J13="PONTUAL",MONTH($O13)<MONTH(AU$4)),MIN($AS13:AT13),IF(AND($I13="NOVO",MONTH($O13)>MONTH(AU$4)),AG13,IF(MONTH($O13)>MONTH(AU$4),AG13,IF(MONTH($O13)=MONTH(AU$4),AG13*(1+Macroindicadores!D$7),AT13))))))))) -> 4.1241144 | AV13: =IF(ISBLANK(T13),"",IF(ISBLANK($O13),AH13,IF($J13="ANUAL",AH13*(1+Macroindicadores!E$7),IF(AND($I13="NOVO",MONTH($O13)=MONTH(AV$4)),AH13*(1+Macroindicadores!E$7),IF(AND($J13="PONTUAL",MONTH($O13)=MONTH(AV$4)),AH13*(1+Macroindicadores!E$7),IF(AND($J13="PONTUAL",MONTH($O13)<MONTH(AV$4)),MIN($AS13:AU13),IF(AND($I13="NOVO",MONTH($O13)>MONTH(AV$4)),AH13,IF(MONTH($O13)>MONTH(AV$4),AH13,IF(MONTH($O13)=MONTH(AV$4),AH13*(1+Macroindicadores!E$7),AU13))))))))) -> 4.1241144 | AW13: =IF(ISBLANK(U13),"",IF(ISBLANK($O13),AI13,IF($J13="ANUAL",AI13*(1+Macroindicadores!F$7),IF(AND($I13="NOVO",MONTH($O13)=MONTH(AW$4)),AI13*(1+Macroindicadores!F$7),IF(AND($J13="PONTUAL",MONTH($O13)=MONTH(AW$4)),AI13*(1+Macroindicadores!F$7),IF(AND($J13="PONTUAL",MONTH($O13)<MONTH(AW$4)),MIN($AS13:AV13),IF(AND($I13="NOVO",MONTH($O13)>MONTH(AW$4)),AI13,IF(MONTH($O13)>MONTH(AW$4),AI13,IF(MONTH($O13)=MONTH(AW$4),AI13*(1+Macroindicadores!F$7),AV13))))))))) -> 4.1241144 | AX13: =IF(ISBLANK(V13),"",IF(ISBLANK($O13),AJ13,IF($J13="ANUAL",AJ13*(1+Macroindicadores!G$7),IF(AND($I13="NOVO",MONTH($O13)=MONTH(AX$4)),AJ13*(1+Macroindicadores!G$7),IF(AND($J13="PONTUAL",MONTH($O13)=MONTH(AX$4)),AJ13*(1+Macroindicadores!G$7),IF(AND($J13="PONTUAL",MONTH($O13)<MONTH(AX$4)),MIN($AS13:AW13),IF(AND($I13="NOVO",MONTH($O13)>MONTH(AX$4)),AJ13,IF(MONTH($O13)>MONTH(AX$4),AJ13,IF(MONTH($O13)=MONTH(AX$4),AJ13*(1+Macroindicadores!G$7),AW13))))))))) -> 4.1241144 | AY13: =IF(ISBLANK(W13),"",IF(ISBLANK($O13),AK13,IF($J13="ANUAL",AK13*(1+Macroindicadores!H$7),IF(AND($I13="NOVO",MONTH($O13)=MONTH(AY$4)),AK13*(1+Macroindicadores!H$7),IF(AND($J13="PONTUAL",MONTH($O13)=MONTH(AY$4)),AK13*(1+Macroindicadores!H$7),IF(AND($J13="PONTUAL",MONTH($O13)<MONTH(AY$4)),MIN($AS13:AX13),IF(AND($I13="NOVO",MONTH($O13)>MONTH(AY$4)),AK13,IF(MONTH($O13)>MONTH(AY$4),AK13,IF(MONTH($O13)=MONTH(AY$4),AK13*(1+Macroindicadores!H$7),AX13))))))))) -> 4.1241144 | AZ13: =IF(ISBLANK(X13),"",IF(ISBLANK($O13),AL13,IF($J13="ANUAL",AL13*(1+Macroindicadores!I$7),IF(AND($I13="NOVO",MONTH($O13)=MONTH(AZ$4)),AL13*(1+Macroindicadores!I$7),IF(AND($J13="PONTUAL",MONTH($O13)=MONTH(AZ$4)),AL13*(1+Macroindicadores!I$7),IF(AND($J13="PONTUAL",MONTH($O13)<MONTH(AZ$4)),MIN($AS13:AY13),IF(AND($I13="NOVO",MONTH($O13)>MONTH(AZ$4)),AL13,IF(MONTH($O13)>MONTH(AZ$4),AL13,IF(MONTH($O13)=MONTH(AZ$4),AL13*(1+Macroindicadores!I$7),AY13))))))))) -> 4.1241144 | BA13: =IF(ISBLANK(Y13),"",IF(ISBLANK($O13),AM13,IF($J13="ANUAL",AM13*(1+Macroindicadores!J$7),IF(AND($I13="NOVO",MONTH($O13)=MONTH(BA$4)),AM13*(1+Macroindicadores!J$7),IF(AND($J13="PONTUAL",MONTH($O13)=MONTH(BA$4)),AM13*(1+Macroindicadores!J$7),IF(AND($J13="PONTUAL",MONTH($O13)<MONTH(BA$4)),MIN($AS13:AZ13),IF(AND($I13="NOVO",MONTH($O13)>MONTH(BA$4)),AM13,IF(MONTH($O13)>MONTH(BA$4),AM13,IF(MONTH($O13)=MONTH(BA$4),AM13*(1+Macroindicadores!J$7),AZ13))))))))) -> 4.1241144 | ... BD13: =IF(ISBLANK(AB13),"",IF(ISBLANK($O13),AP13,IF($J13="ANUAL",AP13*(1+Macroindicadores!M$7),IF(AND($I13="NOVO",MONTH($O13)=MONTH(BD$4)),AP13*(1+Macroindicadores!M$7),IF(AND($J13="PONTUAL",MONTH($O13)=MONTH(BD$4)),AP13*(1+Macroindicadores!M$7),IF(AND($J13="PONTUAL",MONTH($O13)<MONTH(BD$4)),MIN($AS13:BC13),IF(AND($I13="NOVO",MONTH($O13)>MONTH(BD$4)),AP13,IF(MONTH($O13)>MONTH(BD$4),AP13,IF(MONTH($O13)=MONTH(BD$4),AP13*(1+Macroindicadores!M$7),BC13))))))))) -> 4.1241144 | BE13: =IF(AND(ISBLANK($Q13),ISBLANK($R13),ISBLANK($S13),ISBLANK($T13),ISBLANK($U13),ISBLANK($V13),ISBLANK($W13),ISBLANK($X13),ISBLANK($Y13),ISBLANK($Z13),ISBLANK($AA13),ISBLANK($AB13)),"",SUM(AS13:BD13)) -> 49.489373 | BG13: =IF(ISBLANK(Q13),"",AS13/Macroindicadores!B$2) -> 0.70138 | BH13: =IF(ISBLANK(R13),"",AT13/Macroindicadores!C$2) -> 0.70138 | BI13: =IF(ISBLANK(S13),"",AU13/Macroindicadores!D$2) -> 0.70138 | BJ13: =IF(ISBLANK(T13),"",AV13/Macroindicadores!E$2) -> 0.70138 | BK13: =IF(ISBLANK(U13),"",AW13/Macroindicadores!F$2) -> 0.70138 | BL13: =IF(ISBLANK(V13),"",AX13/Macroindicadores!G$2) -> 0.70138 | BM13: =IF(ISBLANK(W13),"",AY13/Macroindicadores!H$2) -> 0.70138 | BN13: =IF(ISBLANK(X13),"",AZ13/Macroindicadores!I$2) -> 0.70138 | ... BR13: =IF(ISBLANK(AB13),"",BD13/Macroindicadores!M$2) -> 0.70138 | BS13: =IF(AND(ISBLANK($Q13),ISBLANK($R13),ISBLANK($S13),ISBLANK($T13),ISBLANK($U13),ISBLANK($V13),ISBLANK($W13),ISBLANK($X13),ISBLANK($Y13),ISBLANK($Z13),ISBLANK($AA13),ISBLANK($AB13)),"",SUM(BG13:BR13)) -> 8.41656 | BT13: =IF(ISBLANK($L13),"",_xlfn.XLOOKUP($L13,'CENTRO CUSTO'!$A:$A,'CENTRO CUSTO'!$E:$E,FALSE,0)) -> G&A BU
A14: =IF(ISBLANK($F14),"","Budget") -> Budget | B14: =IF(ISBLANK($F14),"",$F$1) -> 2026 | C14: =IF(ISBLANK($L14),"",_xlfn.XLOOKUP($L14,'CENTRO CUSTO'!$A:$A,'CENTRO CUSTO'!F:F,FALSE,0)) -> Rio de Janeiro | D14: =IF(ISBLANK($L14),"",_xlfn.XLOOKUP($L14,'CENTRO CUSTO'!$A:$A,'CENTRO CUSTO'!G:G,FALSE,0)) -> BU-RJ | E14: =IF(ISBLANK($L14),"",_xlfn.XLOOKUP($L14,'CENTRO CUSTO'!$A:$A,'CENTRO CUSTO'!H:H,FALSE,0)) -> G&A | F14: SEIDOR | G14: Applications support and maintenance | H14: SAP S4 - Licença | I14: Novo | J14: Mensal | K14: Contrato em Curso | L14: BU-RJ | TI | M14: =IF(ISBLANK($L14),"",_xlfn.XLOOKUP($L14,'CENTRO CUSTO'!$A:$A,'CENTRO CUSTO'!D:D,FALSE,0)) -> Alexandre Ayabe | N14: Licença SAP | P14: USD | Q14: =140276*Rateio!$E$56/12 -> 233.79333 | R14: =140276*Rateio!$E$56/12 -> 233.79333 | S14: =140276*Rateio!$E$56/12 -> 233.79333 | T14: =140276*Rateio!$E$56/12 -> 233.79333 | U14: =140276*Rateio!$E$56/12 -> 233.79333 | V14: =140276*Rateio!$E$56/12 -> 233.79333 | W14: =140276*Rateio!$E$56/12 -> 233.79333 | X14: =140276*Rateio!$E$56/12 -> 233.79333 | ... AB14: =140276*Rateio!$E$56/12 -> 233.79333 | AC14: =IF(AND(ISBLANK($Q14),ISBLANK($R14),ISBLANK($S14),ISBLANK($T14),ISBLANK($U14),ISBLANK($V14),ISBLANK($W14),ISBLANK($X14),ISBLANK($Y14),ISBLANK($Z14),ISBLANK($AA14),ISBLANK($AB14)),"",SUM(Q14:AB14)) -> 2805.52 | AE14: =IF(ISBLANK(Q14),"",IF($P14="BRL",Q14,Q14*Macroindicadores!B$2)/1000) -> 1.3747048 | AF14: =IF(ISBLANK(R14),"",IF($P14="BRL",R14,R14*Macroindicadores!C$2)/1000) -> 1.3747048 | AG14: =IF(ISBLANK(S14),"",IF($P14="BRL",S14,S14*Macroindicadores!D$2)/1000) -> 1.3747048 | AH14: =IF(ISBLANK(T14),"",IF($P14="BRL",T14,T14*Macroindicadores!E$2)/1000) -> 1.3747048 | AI14: =IF(ISBLANK(U14),"",IF($P14="BRL",U14,U14*Macroindicadores!F$2)/1000) -> 1.3747048 | AJ14: =IF(ISBLANK(V14),"",IF($P14="BRL",V14,V14*Macroindicadores!G$2)/1000) -> 1.3747048 | AK14: =IF(ISBLANK(W14),"",IF($P14="BRL",W14,W14*Macroindicadores!H$2)/1000) -> 1.3747048 | AL14: =IF(ISBLANK(X14),"",IF($P14="BRL",X14,X14*Macroindicadores!I$2)/1000) -> 1.3747048 | ... AP14: =IF(ISBLANK(AB14),"",IF($P14="BRL",AB14,AB14*Macroindicadores!M$2)/1000) -> 1.3747048 | AQ14: =IF(AND(ISBLANK($Q14),ISBLANK($R14),ISBLANK($S14),ISBLANK($T14),ISBLANK($U14),ISBLANK($V14),ISBLANK($W14),ISBLANK($X14),ISBLANK($Y14),ISBLANK($Z14),ISBLANK($AA14),ISBLANK($AB14)),"",SUM(AE14:AP14)) -> 16.496458 | AS14: =IF(ISBLANK(Q14),"",IF(ISBLANK($O14),AE14,IF($J14="ANUAL",AE14*(1+Macroindicadores!B$7),IF(AND($I14="NOVO",MONTH($O14)=MONTH(AS$4)),AE14*(1+Macroindicadores!B$7),IF(AND($J14="PONTUAL",MONTH($O14)=MONTH(AS$4)),AE14*(1+Macroindicadores!B$7),IF(AND($J14="PONTUAL",MONTH($O14)<MONTH(AS$4)),MIN(AR14:$AS14),IF(AND($I14="NOVO",MONTH($O14)>MONTH(AS$4)),AE14,IF(MONTH($O14)>MONTH(AS$4),AE14,IF(MONTH($O14)=MONTH(AS$4),AE14*(1+Macroindicadores!B$7),AR14))))))))) -> 1.3747048 | AT14: =IF(ISBLANK(R14),"",IF(ISBLANK($O14),AF14,IF($J14="ANUAL",AF14*(1+Macroindicadores!C$7),IF(AND($I14="NOVO",MONTH($O14)=MONTH(AT$4)),AF14*(1+Macroindicadores!C$7),IF(AND($J14="PONTUAL",MONTH($O14)=MONTH(AT$4)),AF14*(1+Macroindicadores!C$7),IF(AND($J14="PONTUAL",MONTH($O14)<MONTH(AT$4)),MIN($AS14:AS14),IF(AND($I14="NOVO",MONTH($O14)>MONTH(AT$4)),AF14,IF(MONTH($O14)>MONTH(AT$4),AF14,IF(MONTH($O14)=MONTH(AT$4),AF14*(1+Macroindicadores!C$7),AS14))))))))) -> 1.3747048 | AU14: =IF(ISBLANK(S14),"",IF(ISBLANK($O14),AG14,IF($J14="ANUAL",AG14*(1+Macroindicadores!D$7),IF(AND($I14="NOVO",MONTH($O14)=MONTH(AU$4)),AG14*(1+Macroindicadores!D$7),IF(AND($J14="PONTUAL",MONTH($O14)=MONTH(AU$4)),AG14*(1+Macroindicadores!D$7),IF(AND($J14="PONTUAL",MONTH($O14)<MONTH(AU$4)),MIN($AS14:AT14),IF(AND($I14="NOVO",MONTH($O14)>MONTH(AU$4)),AG14,IF(MONTH($O14)>MONTH(AU$4),AG14,IF(MONTH($O14)=MONTH(AU$4),AG14*(1+Macroindicadores!D$7),AT14))))))))) -> 1.3747048 | AV14: =IF(ISBLANK(T14),"",IF(ISBLANK($O14),AH14,IF($J14="ANUAL",AH14*(1+Macroindicadores!E$7),IF(AND($I14="NOVO",MONTH($O14)=MONTH(AV$4)),AH14*(1+Macroindicadores!E$7),IF(AND($J14="PONTUAL",MONTH($O14)=MONTH(AV$4)),AH14*(1+Macroindicadores!E$7),IF(AND($J14="PONTUAL",MONTH($O14)<MONTH(AV$4)),MIN($AS14:AU14),IF(AND($I14="NOVO",MONTH($O14)>MONTH(AV$4)),AH14,IF(MONTH($O14)>MONTH(AV$4),AH14,IF(MONTH($O14)=MONTH(AV$4),AH14*(1+Macroindicadores!E$7),AU14))))))))) -> 1.3747048 | AW14: =IF(ISBLANK(U14),"",IF(ISBLANK($O14),AI14,IF($J14="ANUAL",AI14*(1+Macroindicadores!F$7),IF(AND($I14="NOVO",MONTH($O14)=MONTH(AW$4)),AI14*(1+Macroindicadores!F$7),IF(AND($J14="PONTUAL",MONTH($O14)=MONTH(AW$4)),AI14*(1+Macroindicadores!F$7),IF(AND($J14="PONTUAL",MONTH($O14)<MONTH(AW$4)),MIN($AS14:AV14),IF(AND($I14="NOVO",MONTH($O14)>MONTH(AW$4)),AI14,IF(MONTH($O14)>MONTH(AW$4),AI14,IF(MONTH($O14)=MONTH(AW$4),AI14*(1+Macroindicadores!F$7),AV14))))))))) -> 1.3747048 | AX14: =IF(ISBLANK(V14),"",IF(ISBLANK($O14),AJ14,IF($J14="ANUAL",AJ14*(1+Macroindicadores!G$7),IF(AND($I14="NOVO",MONTH($O14)=MONTH(AX$4)),AJ14*(1+Macroindicadores!G$7),IF(AND($J14="PONTUAL",MONTH($O14)=MONTH(AX$4)),AJ14*(1+Macroindicadores!G$7),IF(AND($J14="PONTUAL",MONTH($O14)<MONTH(AX$4)),MIN($AS14:AW14),IF(AND($I14="NOVO",MONTH($O14)>MONTH(AX$4)),AJ14,IF(MONTH($O14)>MONTH(AX$4),AJ14,IF(MONTH($O14)=MONTH(AX$4),AJ14*(1+Macroindicadores!G$7),AW14))))))))) -> 1.3747048 | AY14: =IF(ISBLANK(W14),"",IF(ISBLANK($O14),AK14,IF($J14="ANUAL",AK14*(1+Macroindicadores!H$7),IF(AND($I14="NOVO",MONTH($O14)=MONTH(AY$4)),AK14*(1+Macroindicadores!H$7),IF(AND($J14="PONTUAL",MONTH($O14)=MONTH(AY$4)),AK14*(1+Macroindicadores!H$7),IF(AND($J14="PONTUAL",MONTH($O14)<MONTH(AY$4)),MIN($AS14:AX14),IF(AND($I14="NOVO",MONTH($O14)>MONTH(AY$4)),AK14,IF(MONTH($O14)>MONTH(AY$4),AK14,IF(MONTH($O14)=MONTH(AY$4),AK14*(1+Macroindicadores!H$7),AX14))))))))) -> 1.3747048 | AZ14: =IF(ISBLANK(X14),"",IF(ISBLANK($O14),AL14,IF($J14="ANUAL",AL14*(1+Macroindicadores!I$7),IF(AND($I14="NOVO",MONTH($O14)=MONTH(AZ$4)),AL14*(1+Macroindicadores!I$7),IF(AND($J14="PONTUAL",MONTH($O14)=MONTH(AZ$4)),AL14*(1+Macroindicadores!I$7),IF(AND($J14="PONTUAL",MONTH($O14)<MONTH(AZ$4)),MIN($AS14:AY14),IF(AND($I14="NOVO",MONTH($O14)>MONTH(AZ$4)),AL14,IF(MONTH($O14)>MONTH(AZ$4),AL14,IF(MONTH($O14)=MONTH(AZ$4),AL14*(1+Macroindicadores!I$7),AY14))))))))) -> 1.3747048 | BA14: =IF(ISBLANK(Y14),"",IF(ISBLANK($O14),AM14,IF($J14="ANUAL",AM14*(1+Macroindicadores!J$7),IF(AND($I14="NOVO",MONTH($O14)=MONTH(BA$4)),AM14*(1+Macroindicadores!J$7),IF(AND($J14="PONTUAL",MONTH($O14)=MONTH(BA$4)),AM14*(1+Macroindicadores!J$7),IF(AND($J14="PONTUAL",MONTH($O14)<MONTH(BA$4)),MIN($AS14:AZ14),IF(AND($I14="NOVO",MONTH($O14)>MONTH(BA$4)),AM14,IF(MONTH($O14)>MONTH(BA$4),AM14,IF(MONTH($O14)=MONTH(BA$4),AM14*(1+Macroindicadores!J$7),AZ14))))))))) -> 1.3747048 | ... BD14: =IF(ISBLANK(AB14),"",IF(ISBLANK($O14),AP14,IF($J14="ANUAL",AP14*(1+Macroindicadores!M$7),IF(AND($I14="NOVO",MONTH($O14)=MONTH(BD$4)),AP14*(1+Macroindicadores!M$7),IF(AND($J14="PONTUAL",MONTH($O14)=MONTH(BD$4)),AP14*(1+Macroindicadores!M$7),IF(AND($J14="PONTUAL",MONTH($O14)<MONTH(BD$4)),MIN($AS14:BC14),IF(AND($I14="NOVO",MONTH($O14)>MONTH(BD$4)),AP14,IF(MONTH($O14)>MONTH(BD$4),AP14,IF(MONTH($O14)=MONTH(BD$4),AP14*(1+Macroindicadores!M$7),BC14))))))))) -> 1.3747048 | BE14: =IF(AND(ISBLANK($Q14),ISBLANK($R14),ISBLANK($S14),ISBLANK($T14),ISBLANK($U14),ISBLANK($V14),ISBLANK($W14),ISBLANK($X14),ISBLANK($Y14),ISBLANK($Z14),ISBLANK($AA14),ISBLANK($AB14)),"",SUM(AS14:BD14)) -> 16.496458 | BG14: =IF(ISBLANK(Q14),"",AS14/Macroindicadores!B$2) -> 0.23379333 | BH14: =IF(ISBLANK(R14),"",AT14/Macroindicadores!C$2) -> 0.23379333 | BI14: =IF(ISBLANK(S14),"",AU14/Macroindicadores!D$2) -> 0.23379333 | BJ14: =IF(ISBLANK(T14),"",AV14/Macroindicadores!E$2) -> 0.23379333 | BK14: =IF(ISBLANK(U14),"",AW14/Macroindicadores!F$2) -> 0.23379333 | BL14: =IF(ISBLANK(V14),"",AX14/Macroindicadores!G$2) -> 0.23379333 | BM14: =IF(ISBLANK(W14),"",AY14/Macroindicadores!H$2) -> 0.23379333 | BN14: =IF(ISBLANK(X14),"",AZ14/Macroindicadores!I$2) -> 0.23379333 | ... BR14: =IF(ISBLANK(AB14),"",BD14/Macroindicadores!M$2) -> 0.23379333 | BS14: =IF(AND(ISBLANK($Q14),ISBLANK($R14),ISBLANK($S14),ISBLANK($T14),ISBLANK($U14),ISBLANK($V14),ISBLANK($W14),ISBLANK($X14),ISBLANK($Y14),ISBLANK($Z14),ISBLANK($AA14),ISBLANK($AB14)),"",SUM(BG14:BR14)) -> 2.80552 | BT14: =IF(ISBLANK($L14),"",_xlfn.XLOOKUP($L14,'CENTRO CUSTO'!$A:$A,'CENTRO CUSTO'!$E:$E,FALSE,0)) -> G&A BU
A15: =IF(ISBLANK($F15),"","Budget") -> Budget | B15: =IF(ISBLANK($F15),"",$F$1) -> 2026 | C15: =IF(ISBLANK($L15),"",_xlfn.XLOOKUP($L15,'CENTRO CUSTO'!$A:$A,'CENTRO CUSTO'!F:F,FALSE,0)) -> Cone Sul | D15: =IF(ISBLANK($L15),"",_xlfn.XLOOKUP($L15,'CENTRO CUSTO'!$A:$A,'CENTRO CUSTO'!G:G,FALSE,0)) -> Plataforma | E15: =IF(ISBLANK($L15),"",_xlfn.XLOOKUP($L15,'CENTRO CUSTO'!$A:$A,'CENTRO CUSTO'!H:H,FALSE,0)) -> G&A | F15: SEIDOR | G15: Applications support and maintenance | H15: SAP S4 - Licença | I15: Novo | J15: Mensal | K15: Contrato em Curso | L15: PL | TI | M15: =IF(ISBLANK($L15),"",_xlfn.XLOOKUP($L15,'CENTRO CUSTO'!$A:$A,'CENTRO CUSTO'!D:D,FALSE,0)) -> Alexandre Ayabe | N15: Licença SAP | P15: USD | Q15: =140276*Rateio!$E$58/12 -> 1870.3467 | R15: =140276*Rateio!$E$58/12 -> 1870.3467 | S15: =140276*Rateio!$E$58/12 -> 1870.3467 | T15: =140276*Rateio!$E$58/12 -> 1870.3467 | U15: =140276*Rateio!$E$58/12 -> 1870.3467 | V15: =140276*Rateio!$E$58/12 -> 1870.3467 | W15: =140276*Rateio!$E$58/12 -> 1870.3467 | X15: =140276*Rateio!$E$58/12 -> 1870.3467 | ... AB15: =140276*Rateio!$E$58/12 -> 1870.3467 | AC15: =IF(AND(ISBLANK($Q15),ISBLANK($R15),ISBLANK($S15),ISBLANK($T15),ISBLANK($U15),ISBLANK($V15),ISBLANK($W15),ISBLANK($X15),ISBLANK($Y15),ISBLANK($Z15),ISBLANK($AA15),ISBLANK($AB15)),"",SUM(Q15:AB15)) -> 22444.16 | AE15: =IF(ISBLANK(Q15),"",IF($P15="BRL",Q15,Q15*Macroindicadores!B$2)/1000) -> 10.997638 | AF15: =IF(ISBLANK(R15),"",IF($P15="BRL",R15,R15*Macroindicadores!C$2)/1000) -> 10.997638 | AG15: =IF(ISBLANK(S15),"",IF($P15="BRL",S15,S15*Macroindicadores!D$2)/1000) -> 10.997638 | AH15: =IF(ISBLANK(T15),"",IF($P15="BRL",T15,T15*Macroindicadores!E$2)/1000) -> 10.997638 | AI15: =IF(ISBLANK(U15),"",IF($P15="BRL",U15,U15*Macroindicadores!F$2)/1000) -> 10.997638 | AJ15: =IF(ISBLANK(V15),"",IF($P15="BRL",V15,V15*Macroindicadores!G$2)/1000) -> 10.997638 | AK15: =IF(ISBLANK(W15),"",IF($P15="BRL",W15,W15*Macroindicadores!H$2)/1000) -> 10.997638 | AL15: =IF(ISBLANK(X15),"",IF($P15="BRL",X15,X15*Macroindicadores!I$2)/1000) -> 10.997638 | ... AP15: =IF(ISBLANK(AB15),"",IF($P15="BRL",AB15,AB15*Macroindicadores!M$2)/1000) -> 10.997638 | AQ15: =IF(AND(ISBLANK($Q15),ISBLANK($R15),ISBLANK($S15),ISBLANK($T15),ISBLANK($U15),ISBLANK($V15),ISBLANK($W15),ISBLANK($X15),ISBLANK($Y15),ISBLANK($Z15),ISBLANK($AA15),ISBLANK($AB15)),"",SUM(AE15:AP15)) -> 131.97166 | AS15: =IF(ISBLANK(Q15),"",IF(ISBLANK($O15),AE15,IF($J15="ANUAL",AE15*(1+Macroindicadores!B$7),IF(AND($I15="NOVO",MONTH($O15)=MONTH(AS$4)),AE15*(1+Macroindicadores!B$7),IF(AND($J15="PONTUAL",MONTH($O15)=MONTH(AS$4)),AE15*(1+Macroindicadores!B$7),IF(AND($J15="PONTUAL",MONTH($O15)<MONTH(AS$4)),MIN(AR15:$AS15),IF(AND($I15="NOVO",MONTH($O15)>MONTH(AS$4)),AE15,IF(MONTH($O15)>MONTH(AS$4),AE15,IF(MONTH($O15)=MONTH(AS$4),AE15*(1+Macroindicadores!B$7),AR15))))))))) -> 10.997638 | AT15: =IF(ISBLANK(R15),"",IF(ISBLANK($O15),AF15,IF($J15="ANUAL",AF15*(1+Macroindicadores!C$7),IF(AND($I15="NOVO",MONTH($O15)=MONTH(AT$4)),AF15*(1+Macroindicadores!C$7),IF(AND($J15="PONTUAL",MONTH($O15)=MONTH(AT$4)),AF15*(1+Macroindicadores!C$7),IF(AND($J15="PONTUAL",MONTH($O15)<MONTH(AT$4)),MIN($AS15:AS15),IF(AND($I15="NOVO",MONTH($O15)>MONTH(AT$4)),AF15,IF(MONTH($O15)>MONTH(AT$4),AF15,IF(MONTH($O15)=MONTH(AT$4),AF15*(1+Macroindicadores!C$7),AS15))))))))) -> 10.997638 | AU15: =IF(ISBLANK(S15),"",IF(ISBLANK($O15),AG15,IF($J15="ANUAL",AG15*(1+Macroindicadores!D$7),IF(AND($I15="NOVO",MONTH($O15)=MONTH(AU$4)),AG15*(1+Macroindicadores!D$7),IF(AND($J15="PONTUAL",MONTH($O15)=MONTH(AU$4)),AG15*(1+Macroindicadores!D$7),IF(AND($J15="PONTUAL",MONTH($O15)<MONTH(AU$4)),MIN($AS15:AT15),IF(AND($I15="NOVO",MONTH($O15)>MONTH(AU$4)),AG15,IF(MONTH($O15)>MONTH(AU$4),AG15,IF(MONTH($O15)=MONTH(AU$4),AG15*(1+Macroindicadores!D$7),AT15))))))))) -> 10.997638 | AV15: =IF(ISBLANK(T15),"",IF(ISBLANK($O15),AH15,IF($J15="ANUAL",AH15*(1+Macroindicadores!E$7),IF(AND($I15="NOVO",MONTH($O15)=MONTH(AV$4)),AH15*(1+Macroindicadores!E$7),IF(AND($J15="PONTUAL",MONTH($O15)=MONTH(AV$4)),AH15*(1+Macroindicadores!E$7),IF(AND($J15="PONTUAL",MONTH($O15)<MONTH(AV$4)),MIN($AS15:AU15),IF(AND($I15="NOVO",MONTH($O15)>MONTH(AV$4)),AH15,IF(MONTH($O15)>MONTH(AV$4),AH15,IF(MONTH($O15)=MONTH(AV$4),AH15*(1+Macroindicadores!E$7),AU15))))))))) -> 10.997638 | AW15: =IF(ISBLANK(U15),"",IF(ISBLANK($O15),AI15,IF($J15="ANUAL",AI15*(1+Macroindicadores!F$7),IF(AND($I15="NOVO",MONTH($O15)=MONTH(AW$4)),AI15*(1+Macroindicadores!F$7),IF(AND($J15="PONTUAL",MONTH($O15)=MONTH(AW$4)),AI15*(1+Macroindicadores!F$7),IF(AND($J15="PONTUAL",MONTH($O15)<MONTH(AW$4)),MIN($AS15:AV15),IF(AND($I15="NOVO",MONTH($O15)>MONTH(AW$4)),AI15,IF(MONTH($O15)>MONTH(AW$4),AI15,IF(MONTH($O15)=MONTH(AW$4),AI15*(1+Macroindicadores!F$7),AV15))))))))) -> 10.997638 | AX15: =IF(ISBLANK(V15),"",IF(ISBLANK($O15),AJ15,IF($J15="ANUAL",AJ15*(1+Macroindicadores!G$7),IF(AND($I15="NOVO",MONTH($O15)=MONTH(AX$4)),AJ15*(1+Macroindicadores!G$7),IF(AND($J15="PONTUAL",MONTH($O15)=MONTH(AX$4)),AJ15*(1+Macroindicadores!G$7),IF(AND($J15="PONTUAL",MONTH($O15)<MONTH(AX$4)),MIN($AS15:AW15),IF(AND($I15="NOVO",MONTH($O15)>MONTH(AX$4)),AJ15,IF(MONTH($O15)>MONTH(AX$4),AJ15,IF(MONTH($O15)=MONTH(AX$4),AJ15*(1+Macroindicadores!G$7),AW15))))))))) -> 10.997638 | AY15: =IF(ISBLANK(W15),"",IF(ISBLANK($O15),AK15,IF($J15="ANUAL",AK15*(1+Macroindicadores!H$7),IF(AND($I15="NOVO",MONTH($O15)=MONTH(AY$4)),AK15*(1+Macroindicadores!H$7),IF(AND($J15="PONTUAL",MONTH($O15)=MONTH(AY$4)),AK15*(1+Macroindicadores!H$7),IF(AND($J15="PONTUAL",MONTH($O15)<MONTH(AY$4)),MIN($AS15:AX15),IF(AND($I15="NOVO",MONTH($O15)>MONTH(AY$4)),AK15,IF(MONTH($O15)>MONTH(AY$4),AK15,IF(MONTH($O15)=MONTH(AY$4),AK15*(1+Macroindicadores!H$7),AX15))))))))) -> 10.997638 | AZ15: =IF(ISBLANK(X15),"",IF(ISBLANK($O15),AL15,IF($J15="ANUAL",AL15*(1+Macroindicadores!I$7),IF(AND($I15="NOVO",MONTH($O15)=MONTH(AZ$4)),AL15*(1+Macroindicadores!I$7),IF(AND($J15="PONTUAL",MONTH($O15)=MONTH(AZ$4)),AL15*(1+Macroindicadores!I$7),IF(AND($J15="PONTUAL",MONTH($O15)<MONTH(AZ$4)),MIN($AS15:AY15),IF(AND($I15="NOVO",MONTH($O15)>MONTH(AZ$4)),AL15,IF(MONTH($O15)>MONTH(AZ$4),AL15,IF(MONTH($O15)=MONTH(AZ$4),AL15*(1+Macroindicadores!I$7),AY15))))))))) -> 10.997638 | BA15: =IF(ISBLANK(Y15),"",IF(ISBLANK($O15),AM15,IF($J15="ANUAL",AM15*(1+Macroindicadores!J$7),IF(AND($I15="NOVO",MONTH($O15)=MONTH(BA$4)),AM15*(1+Macroindicadores!J$7),IF(AND($J15="PONTUAL",MONTH($O15)=MONTH(BA$4)),AM15*(1+Macroindicadores!J$7),IF(AND($J15="PONTUAL",MONTH($O15)<MONTH(BA$4)),MIN($AS15:AZ15),IF(AND($I15="NOVO",MONTH($O15)>MONTH(BA$4)),AM15,IF(MONTH($O15)>MONTH(BA$4),AM15,IF(MONTH($O15)=MONTH(BA$4),AM15*(1+Macroindicadores!J$7),AZ15))))))))) -> 10.997638 | ... BD15: =IF(ISBLANK(AB15),"",IF(ISBLANK($O15),AP15,IF($J15="ANUAL",AP15*(1+Macroindicadores!M$7),IF(AND($I15="NOVO",MONTH($O15)=MONTH(BD$4)),AP15*(1+Macroindicadores!M$7),IF(AND($J15="PONTUAL",MONTH($O15)=MONTH(BD$4)),AP15*(1+Macroindicadores!M$7),IF(AND($J15="PONTUAL",MONTH($O15)<MONTH(BD$4)),MIN($AS15:BC15),IF(AND($I15="NOVO",MONTH($O15)>MONTH(BD$4)),AP15,IF(MONTH($O15)>MONTH(BD$4),AP15,IF(MONTH($O15)=MONTH(BD$4),AP15*(1+Macroindicadores!M$7),BC15))))))))) -> 10.997638 | BE15: =IF(AND(ISBLANK($Q15),ISBLANK($R15),ISBLANK($S15),ISBLANK($T15),ISBLANK($U15),ISBLANK($V15),ISBLANK($W15),ISBLANK($X15),ISBLANK($Y15),ISBLANK($Z15),ISBLANK($AA15),ISBLANK($AB15)),"",SUM(AS15:BD15)) -> 131.97166 | BG15: =IF(ISBLANK(Q15),"",AS15/Macroindicadores!B$2) -> 1.8703467 | BH15: =IF(ISBLANK(R15),"",AT15/Macroindicadores!C$2) -> 1.8703467 | BI15: =IF(ISBLANK(S15),"",AU15/Macroindicadores!D$2) -> 1.8703467 | BJ15: =IF(ISBLANK(T15),"",AV15/Macroindicadores!E$2) -> 1.8703467 | BK15: =IF(ISBLANK(U15),"",AW15/Macroindicadores!F$2) -> 1.8703467 | BL15: =IF(ISBLANK(V15),"",AX15/Macroindicadores!G$2) -> 1.8703467 | BM15: =IF(ISBLANK(W15),"",AY15/Macroindicadores!H$2) -> 1.8703467 | BN15: =IF(ISBLANK(X15),"",AZ15/Macroindicadores!I$2) -> 1.8703467 | ... BR15: =IF(ISBLANK(AB15),"",BD15/Macroindicadores!M$2) -> 1.8703467 | BS15: =IF(AND(ISBLANK($Q15),ISBLANK($R15),ISBLANK($S15),ISBLANK($T15),ISBLANK($U15),ISBLANK($V15),ISBLANK($W15),ISBLANK($X15),ISBLANK($Y15),ISBLANK($Z15),ISBLANK($AA15),ISBLANK($AB15)),"",SUM(BG15:BR15)) -> 22.44416 | BT15: =IF(ISBLANK($L15),"",_xlfn.XLOOKUP($L15,'CENTRO CUSTO'!$A:$A,'CENTRO CUSTO'!$E:$E,FALSE,0)) -> G&A PL
A16: =IF(ISBLANK($F16),"","Budget") -> Budget | B16: =IF(ISBLANK($F16),"",$F$1) -> 2026 | C16: =IF(ISBLANK($L16),"",_xlfn.XLOOKUP($L16,'CENTRO CUSTO'!$A:$A,'CENTRO CUSTO'!F:F,FALSE,0)) -> LATAM | D16: =IF(ISBLANK($L16),"",_xlfn.XLOOKUP($L16,'CENTRO CUSTO'!$A:$A,'CENTRO CUSTO'!G:G,FALSE,0)) -> Corporativo | E16: =IF(ISBLANK($L16),"",_xlfn.XLOOKUP($L16,'CENTRO CUSTO'!$A:$A,'CENTRO CUSTO'!H:H,FALSE,0)) -> G&A | F16: SEIDOR | G16: Applications support and maintenance | H16: SAP S4 - Licença | I16: Novo | J16: Mensal | K16: Contrato em Curso | L16: CP | TI | M16: =IF(ISBLANK($L16),"",_xlfn.XLOOKUP($L16,'CENTRO CUSTO'!$A:$A,'CENTRO CUSTO'!D:D,FALSE,0)) -> Jimmy Espinosa | N16: Licença SAP | P16: USD | Q16: =140276*Rateio!$E$59/12 -> 584.48333 | R16: =140276*Rateio!$E$59/12 -> 584.48333 | S16: =140276*Rateio!$E$59/12 -> 584.48333 | T16: =140276*Rateio!$E$59/12 -> 584.48333 | U16: =140276*Rateio!$E$59/12 -> 584.48333 | V16: =140276*Rateio!$E$59/12 -> 584.48333 | W16: =140276*Rateio!$E$59/12 -> 584.48333 | X16: =140276*Rateio!$E$59/12 -> 584.48333 | ... AB16: =140276*Rateio!$E$59/12 -> 584.48333 | AC16: =IF(AND(ISBLANK($Q16),ISBLANK($R16),ISBLANK($S16),ISBLANK($T16),ISBLANK($U16),ISBLANK($V16),ISBLANK($W16),ISBLANK($X16),ISBLANK($Y16),ISBLANK($Z16),ISBLANK($AA16),ISBLANK($AB16)),"",SUM(Q16:AB16)) -> 7013.8 | AE16: =IF(ISBLANK(Q16),"",IF($P16="BRL",Q16,Q16*Macroindicadores!B$2)/1000) -> 3.436762 | AF16: =IF(ISBLANK(R16),"",IF($P16="BRL",R16,R16*Macroindicadores!C$2)/1000) -> 3.436762 | AG16: =IF(ISBLANK(S16),"",IF($P16="BRL",S16,S16*Macroindicadores!D$2)/1000) -> 3.436762 | AH16: =IF(ISBLANK(T16),"",IF($P16="BRL",T16,T16*Macroindicadores!E$2)/1000) -> 3.436762 | AI16: =IF(ISBLANK(U16),"",IF($P16="BRL",U16,U16*Macroindicadores!F$2)/1000) -> 3.436762 | AJ16: =IF(ISBLANK(V16),"",IF($P16="BRL",V16,V16*Macroindicadores!G$2)/1000) -> 3.436762 | AK16: =IF(ISBLANK(W16),"",IF($P16="BRL",W16,W16*Macroindicadores!H$2)/1000) -> 3.436762 | AL16: =IF(ISBLANK(X16),"",IF($P16="BRL",X16,X16*Macroindicadores!I$2)/1000) -> 3.436762 | ... AP16: =IF(ISBLANK(AB16),"",IF($P16="BRL",AB16,AB16*Macroindicadores!M$2)/1000) -> 3.436762 | AQ16: =IF(AND(ISBLANK($Q16),ISBLANK($R16),ISBLANK($S16),ISBLANK($T16),ISBLANK($U16),ISBLANK($V16),ISBLANK($W16),ISBLANK($X16),ISBLANK($Y16),ISBLANK($Z16),ISBLANK($AA16),ISBLANK($AB16)),"",SUM(AE16:AP16)) -> 41.241144 | AS16: =IF(ISBLANK(Q16),"",IF(ISBLANK($O16),AE16,IF($J16="ANUAL",AE16*(1+Macroindicadores!B$7),IF(AND($I16="NOVO",MONTH($O16)=MONTH(AS$4)),AE16*(1+Macroindicadores!B$7),IF(AND($J16="PONTUAL",MONTH($O16)=MONTH(AS$4)),AE16*(1+Macroindicadores!B$7),IF(AND($J16="PONTUAL",MONTH($O16)<MONTH(AS$4)),MIN(AR16:$AS16),IF(AND($I16="NOVO",MONTH($O16)>MONTH(AS$4)),AE16,IF(MONTH($O16)>MONTH(AS$4),AE16,IF(MONTH($O16)=MONTH(AS$4),AE16*(1+Macroindicadores!B$7),AR16))))))))) -> 3.436762 | AT16: =IF(ISBLANK(R16),"",IF(ISBLANK($O16),AF16,IF($J16="ANUAL",AF16*(1+Macroindicadores!C$7),IF(AND($I16="NOVO",MONTH($O16)=MONTH(AT$4)),AF16*(1+Macroindicadores!C$7),IF(AND($J16="PONTUAL",MONTH($O16)=MONTH(AT$4)),AF16*(1+Macroindicadores!C$7),IF(AND($J16="PONTUAL",MONTH($O16)<MONTH(AT$4)),MIN($AS16:AS16),IF(AND($I16="NOVO",MONTH($O16)>MONTH(AT$4)),AF16,IF(MONTH($O16)>MONTH(AT$4),AF16,IF(MONTH($O16)=MONTH(AT$4),AF16*(1+Macroindicadores!C$7),AS16))))))))) -> 3.436762 | AU16: =IF(ISBLANK(S16),"",IF(ISBLANK($O16),AG16,IF($J16="ANUAL",AG16*(1+Macroindicadores!D$7),IF(AND($I16="NOVO",MONTH($O16)=MONTH(AU$4)),AG16*(1+Macroindicadores!D$7),IF(AND($J16="PONTUAL",MONTH($O16)=MONTH(AU$4)),AG16*(1+Macroindicadores!D$7),IF(AND($J16="PONTUAL",MONTH($O16)<MONTH(AU$4)),MIN($AS16:AT16),IF(AND($I16="NOVO",MONTH($O16)>MONTH(AU$4)),AG16,IF(MONTH($O16)>MONTH(AU$4),AG16,IF(MONTH($O16)=MONTH(AU$4),AG16*(1+Macroindicadores!D$7),AT16))))))))) -> 3.436762 | AV16: =IF(ISBLANK(T16),"",IF(ISBLANK($O16),AH16,IF($J16="ANUAL",AH16*(1+Macroindicadores!E$7),IF(AND($I16="NOVO",MONTH($O16)=MONTH(AV$4)),AH16*(1+Macroindicadores!E$7),IF(AND($J16="PONTUAL",MONTH($O16)=MONTH(AV$4)),AH16*(1+Macroindicadores!E$7),IF(AND($J16="PONTUAL",MONTH($O16)<MONTH(AV$4)),MIN($AS16:AU16),IF(AND($I16="NOVO",MONTH($O16)>MONTH(AV$4)),AH16,IF(MONTH($O16)>MONTH(AV$4),AH16,IF(MONTH($O16)=MONTH(AV$4),AH16*(1+Macroindicadores!E$7),AU16))))))))) -> 3.436762 | AW16: =IF(ISBLANK(U16),"",IF(ISBLANK($O16),AI16,IF($J16="ANUAL",AI16*(1+Macroindicadores!F$7),IF(AND($I16="NOVO",MONTH($O16)=MONTH(AW$4)),AI16*(1+Macroindicadores!F$7),IF(AND($J16="PONTUAL",MONTH($O16)=MONTH(AW$4)),AI16*(1+Macroindicadores!F$7),IF(AND($J16="PONTUAL",MONTH($O16)<MONTH(AW$4)),MIN($AS16:AV16),IF(AND($I16="NOVO",MONTH($O16)>MONTH(AW$4)),AI16,IF(MONTH($O16)>MONTH(AW$4),AI16,IF(MONTH($O16)=MONTH(AW$4),AI16*(1+Macroindicadores!F$7),AV16))))))))) -> 3.436762 | AX16: =IF(ISBLANK(V16),"",IF(ISBLANK($O16),AJ16,IF($J16="ANUAL",AJ16*(1+Macroindicadores!G$7),IF(AND($I16="NOVO",MONTH($O16)=MONTH(AX$4)),AJ16*(1+Macroindicadores!G$7),IF(AND($J16="PONTUAL",MONTH($O16)=MONTH(AX$4)),AJ16*(1+Macroindicadores!G$7),IF(AND($J16="PONTUAL",MONTH($O16)<MONTH(AX$4)),MIN($AS16:AW16),IF(AND($I16="NOVO",MONTH($O16)>MONTH(AX$4)),AJ16,IF(MONTH($O16)>MONTH(AX$4),AJ16,IF(MONTH($O16)=MONTH(AX$4),AJ16*(1+Macroindicadores!G$7),AW16))))))))) -> 3.436762 | AY16: =IF(ISBLANK(W16),"",IF(ISBLANK($O16),AK16,IF($J16="ANUAL",AK16*(1+Macroindicadores!H$7),IF(AND($I16="NOVO",MONTH($O16)=MONTH(AY$4)),AK16*(1+Macroindicadores!H$7),IF(AND($J16="PONTUAL",MONTH($O16)=MONTH(AY$4)),AK16*(1+Macroindicadores!H$7),IF(AND($J16="PONTUAL",MONTH($O16)<MONTH(AY$4)),MIN($AS16:AX16),IF(AND($I16="NOVO",MONTH($O16)>MONTH(AY$4)),AK16,IF(MONTH($O16)>MONTH(AY$4),AK16,IF(MONTH($O16)=MONTH(AY$4),AK16*(1+Macroindicadores!H$7),AX16))))))))) -> 3.436762 | AZ16: =IF(ISBLANK(X16),"",IF(ISBLANK($O16),AL16,IF($J16="ANUAL",AL16*(1+Macroindicadores!I$7),IF(AND($I16="NOVO",MONTH($O16)=MONTH(AZ$4)),AL16*(1+Macroindicadores!I$7),IF(AND($J16="PONTUAL",MONTH($O16)=MONTH(AZ$4)),AL16*(1+Macroindicadores!I$7),IF(AND($J16="PONTUAL",MONTH($O16)<MONTH(AZ$4)),MIN($AS16:AY16),IF(AND($I16="NOVO",MONTH($O16)>MONTH(AZ$4)),AL16,IF(MONTH($O16)>MONTH(AZ$4),AL16,IF(MONTH($O16)=MONTH(AZ$4),AL16*(1+Macroindicadores!I$7),AY16))))))))) -> 3.436762 | BA16: =IF(ISBLANK(Y16),"",IF(ISBLANK($O16),AM16,IF($J16="ANUAL",AM16*(1+Macroindicadores!J$7),IF(AND($I16="NOVO",MONTH($O16)=MONTH(BA$4)),AM16*(1+Macroindicadores!J$7),IF(AND($J16="PONTUAL",MONTH($O16)=MONTH(BA$4)),AM16*(1+Macroindicadores!J$7),IF(AND($J16="PONTUAL",MONTH($O16)<MONTH(BA$4)),MIN($AS16:AZ16),IF(AND($I16="NOVO",MONTH($O16)>MONTH(BA$4)),AM16,IF(MONTH($O16)>MONTH(BA$4),AM16,IF(MONTH($O16)=MONTH(BA$4),AM16*(1+Macroindicadores!J$7),AZ16))))))))) -> 3.436762 | ... BD16: =IF(ISBLANK(AB16),"",IF(ISBLANK($O16),AP16,IF($J16="ANUAL",AP16*(1+Macroindicadores!M$7),IF(AND($I16="NOVO",MONTH($O16)=MONTH(BD$4)),AP16*(1+Macroindicadores!M$7),IF(AND($J16="PONTUAL",MONTH($O16)=MONTH(BD$4)),AP16*(1+Macroindicadores!M$7),IF(AND($J16="PONTUAL",MONTH($O16)<MONTH(BD$4)),MIN($AS16:BC16),IF(AND($I16="NOVO",MONTH($O16)>MONTH(BD$4)),AP16,IF(MONTH($O16)>MONTH(BD$4),AP16,IF(MONTH($O16)=MONTH(BD$4),AP16*(1+Macroindicadores!M$7),BC16))))))))) -> 3.436762 | BE16: =IF(AND(ISBLANK($Q16),ISBLANK($R16),ISBLANK($S16),ISBLANK($T16),ISBLANK($U16),ISBLANK($V16),ISBLANK($W16),ISBLANK($X16),ISBLANK($Y16),ISBLANK($Z16),ISBLANK($AA16),ISBLANK($AB16)),"",SUM(AS16:BD16)) -> 41.241144 | BG16: =IF(ISBLANK(Q16),"",AS16/Macroindicadores!B$2) -> 0.58448333 | BH16: =IF(ISBLANK(R16),"",AT16/Macroindicadores!C$2) -> 0.58448333 | BI16: =IF(ISBLANK(S16),"",AU16/Macroindicadores!D$2) -> 0.58448333 | BJ16: =IF(ISBLANK(T16),"",AV16/Macroindicadores!E$2) -> 0.58448333 | BK16: =IF(ISBLANK(U16),"",AW16/Macroindicadores!F$2) -> 0.58448333 | BL16: =IF(ISBLANK(V16),"",AX16/Macroindicadores!G$2) -> 0.58448333 | BM16: =IF(ISBLANK(W16),"",AY16/Macroindicadores!H$2) -> 0.58448333 | BN16: =IF(ISBLANK(X16),"",AZ16/Macroindicadores!I$2) -> 0.58448333 | ... BR16: =IF(ISBLANK(AB16),"",BD16/Macroindicadores!M$2) -> 0.58448333 | BS16: =IF(AND(ISBLANK($Q16),ISBLANK($R16),ISBLANK($S16),ISBLANK($T16),ISBLANK($U16),ISBLANK($V16),ISBLANK($W16),ISBLANK($X16),ISBLANK($Y16),ISBLANK($Z16),ISBLANK($AA16),ISBLANK($AB16)),"",SUM(BG16:BR16)) -> 7.0138 | BT16: =IF(ISBLANK($L16),"",_xlfn.XLOOKUP($L16,'CENTRO CUSTO'!$A:$A,'CENTRO CUSTO'!$E:$E,FALSE,0)) -> G&A CP
A17: =IF(ISBLANK($F17),"","Budget") -> Budget | B17: =IF(ISBLANK($F17),"",$F$1) -> 2026 | C17: =IF(ISBLANK($L17),"",_xlfn.XLOOKUP($L17,'CENTRO CUSTO'!$A:$A,'CENTRO CUSTO'!F:F,FALSE,0)) -> Transporte | D17: =IF(ISBLANK($L17),"",_xlfn.XLOOKUP($L17,'CENTRO CUSTO'!$A:$A,'CENTRO CUSTO'!G:G,FALSE,0)) -> BU-TR | E17: =IF(ISBLANK($L17),"",_xlfn.XLOOKUP($L17,'CENTRO CUSTO'!$A:$A,'CENTRO CUSTO'!H:H,FALSE,0)) -> G&A | F17: SEIDOR | G17: Applications support and maintenance | H17: SAP S4 - AMS | I17: Novo | J17: Mensal | K17: Contrato em Curso | L17: BU-MMTR | TI | M17: =IF(ISBLANK($L17),"",_xlfn.XLOOKUP($L17,'CENTRO CUSTO'!$A:$A,'CENTRO CUSTO'!D:D,FALSE,0)) -> Alexandre Ayabe | N17: Manutenção de Informática | P17: USD | Q17: =187158*Rateio!$E$33/12 -> 2807.37 | R17: =187158*Rateio!$E$33/12 -> 2807.37 | S17: =187158*Rateio!$E$33/12 -> 2807.37 | T17: =187158*Rateio!$E$33/12 -> 2807.37 | U17: =187158*Rateio!$E$33/12 -> 2807.37 | V17: =187158*Rateio!$E$33/12 -> 2807.37 | W17: =187158*Rateio!$E$33/12 -> 2807.37 | X17: =187158*Rateio!$E$33/12 -> 2807.37 | ... AB17: =187158*Rateio!$E$33/12 -> 2807.37 | AC17: =IF(AND(ISBLANK($Q17),ISBLANK($R17),ISBLANK($S17),ISBLANK($T17),ISBLANK($U17),ISBLANK($V17),ISBLANK($W17),ISBLANK($X17),ISBLANK($Y17),ISBLANK($Z17),ISBLANK($AA17),ISBLANK($AB17)),"",SUM(Q17:AB17)) -> 33688.44 | AE17: =IF(ISBLANK(Q17),"",IF($P17="BRL",Q17,Q17*Macroindicadores!B$2)/1000) -> 16.507336 | AF17: =IF(ISBLANK(R17),"",IF($P17="BRL",R17,R17*Macroindicadores!C$2)/1000) -> 16.507336 | AG17: =IF(ISBLANK(S17),"",IF($P17="BRL",S17,S17*Macroindicadores!D$2)/1000) -> 16.507336 | AH17: =IF(ISBLANK(T17),"",IF($P17="BRL",T17,T17*Macroindicadores!E$2)/1000) -> 16.507336 | AI17: =IF(ISBLANK(U17),"",IF($P17="BRL",U17,U17*Macroindicadores!F$2)/1000) -> 16.507336 | AJ17: =IF(ISBLANK(V17),"",IF($P17="BRL",V17,V17*Macroindicadores!G$2)/1000) -> 16.507336 | AK17: =IF(ISBLANK(W17),"",IF($P17="BRL",W17,W17*Macroindicadores!H$2)/1000) -> 16.507336 | AL17: =IF(ISBLANK(X17),"",IF($P17="BRL",X17,X17*Macroindicadores!I$2)/1000) -> 16.507336 | ... AP17: =IF(ISBLANK(AB17),"",IF($P17="BRL",AB17,AB17*Macroindicadores!M$2)/1000) -> 16.507336 | AQ17: =IF(AND(ISBLANK($Q17),ISBLANK($R17),ISBLANK($S17),ISBLANK($T17),ISBLANK($U17),ISBLANK($V17),ISBLANK($W17),ISBLANK($X17),ISBLANK($Y17),ISBLANK($Z17),ISBLANK($AA17),ISBLANK($AB17)),"",SUM(AE17:AP17)) -> 198.08803 | AS17: =IF(ISBLANK(Q17),"",IF(ISBLANK($O17),AE17,IF($J17="ANUAL",AE17*(1+Macroindicadores!B$7),IF(AND($I17="NOVO",MONTH($O17)=MONTH(AS$4)),AE17*(1+Macroindicadores!B$7),IF(AND($J17="PONTUAL",MONTH($O17)=MONTH(AS$4)),AE17*(1+Macroindicadores!B$7),IF(AND($J17="PONTUAL",MONTH($O17)<MONTH(AS$4)),MIN(AR17:$AS17),IF(AND($I17="NOVO",MONTH($O17)>MONTH(AS$4)),AE17,IF(MONTH($O17)>MONTH(AS$4),AE17,IF(MONTH($O17)=MONTH(AS$4),AE17*(1+Macroindicadores!B$7),AR17))))))))) -> 16.507336 | AT17: =IF(ISBLANK(R17),"",IF(ISBLANK($O17),AF17,IF($J17="ANUAL",AF17*(1+Macroindicadores!C$7),IF(AND($I17="NOVO",MONTH($O17)=MONTH(AT$4)),AF17*(1+Macroindicadores!C$7),IF(AND($J17="PONTUAL",MONTH($O17)=MONTH(AT$4)),AF17*(1+Macroindicadores!C$7),IF(AND($J17="PONTUAL",MONTH($O17)<MONTH(AT$4)),MIN($AS17:AS17),IF(AND($I17="NOVO",MONTH($O17)>MONTH(AT$4)),AF17,IF(MONTH($O17)>MONTH(AT$4),AF17,IF(MONTH($O17)=MONTH(AT$4),AF17*(1+Macroindicadores!C$7),AS17))))))))) -> 16.507336 | AU17: =IF(ISBLANK(S17),"",IF(ISBLANK($O17),AG17,IF($J17="ANUAL",AG17*(1+Macroindicadores!D$7),IF(AND($I17="NOVO",MONTH($O17)=MONTH(AU$4)),AG17*(1+Macroindicadores!D$7),IF(AND($J17="PONTUAL",MONTH($O17)=MONTH(AU$4)),AG17*(1+Macroindicadores!D$7),IF(AND($J17="PONTUAL",MONTH($O17)<MONTH(AU$4)),MIN($AS17:AT17),IF(AND($I17="NOVO",MONTH($O17)>MONTH(AU$4)),AG17,IF(MONTH($O17)>MONTH(AU$4),AG17,IF(MONTH($O17)=MONTH(AU$4),AG17*(1+Macroindicadores!D$7),AT17))))))))) -> 16.507336 | AV17: =IF(ISBLANK(T17),"",IF(ISBLANK($O17),AH17,IF($J17="ANUAL",AH17*(1+Macroindicadores!E$7),IF(AND($I17="NOVO",MONTH($O17)=MONTH(AV$4)),AH17*(1+Macroindicadores!E$7),IF(AND($J17="PONTUAL",MONTH($O17)=MONTH(AV$4)),AH17*(1+Macroindicadores!E$7),IF(AND($J17="PONTUAL",MONTH($O17)<MONTH(AV$4)),MIN($AS17:AU17),IF(AND($I17="NOVO",MONTH($O17)>MONTH(AV$4)),AH17,IF(MONTH($O17)>MONTH(AV$4),AH17,IF(MONTH($O17)=MONTH(AV$4),AH17*(1+Macroindicadores!E$7),AU17))))))))) -> 16.507336 | AW17: =IF(ISBLANK(U17),"",IF(ISBLANK($O17),AI17,IF($J17="ANUAL",AI17*(1+Macroindicadores!F$7),IF(AND($I17="NOVO",MONTH($O17)=MONTH(AW$4)),AI17*(1+Macroindicadores!F$7),IF(AND($J17="PONTUAL",MONTH($O17)=MONTH(AW$4)),AI17*(1+Macroindicadores!F$7),IF(AND($J17="PONTUAL",MONTH($O17)<MONTH(AW$4)),MIN($AS17:AV17),IF(AND($I17="NOVO",MONTH($O17)>MONTH(AW$4)),AI17,IF(MONTH($O17)>MONTH(AW$4),AI17,IF(MONTH($O17)=MONTH(AW$4),AI17*(1+Macroindicadores!F$7),AV17))))))))) -> 16.507336 | AX17: =IF(ISBLANK(V17),"",IF(ISBLANK($O17),AJ17,IF($J17="ANUAL",AJ17*(1+Macroindicadores!G$7),IF(AND($I17="NOVO",MONTH($O17)=MONTH(AX$4)),AJ17*(1+Macroindicadores!G$7),IF(AND($J17="PONTUAL",MONTH($O17)=MONTH(AX$4)),AJ17*(1+Macroindicadores!G$7),IF(AND($J17="PONTUAL",MONTH($O17)<MONTH(AX$4)),MIN($AS17:AW17),IF(AND($I17="NOVO",MONTH($O17)>MONTH(AX$4)),AJ17,IF(MONTH($O17)>MONTH(AX$4),AJ17,IF(MONTH($O17)=MONTH(AX$4),AJ17*(1+Macroindicadores!G$7),AW17))))))))) -> 16.507336 | AY17: =IF(ISBLANK(W17),"",IF(ISBLANK($O17),AK17,IF($J17="ANUAL",AK17*(1+Macroindicadores!H$7),IF(AND($I17="NOVO",MONTH($O17)=MONTH(AY$4)),AK17*(1+Macroindicadores!H$7),IF(AND($J17="PONTUAL",MONTH($O17)=MONTH(AY$4)),AK17*(1+Macroindicadores!H$7),IF(AND($J17="PONTUAL",MONTH($O17)<MONTH(AY$4)),MIN($AS17:AX17),IF(AND($I17="NOVO",MONTH($O17)>MONTH(AY$4)),AK17,IF(MONTH($O17)>MONTH(AY$4),AK17,IF(MONTH($O17)=MONTH(AY$4),AK17*(1+Macroindicadores!H$7),AX17))))))))) -> 16.507336 | AZ17: =IF(ISBLANK(X17),"",IF(ISBLANK($O17),AL17,IF($J17="ANUAL",AL17*(1+Macroindicadores!I$7),IF(AND($I17="NOVO",MONTH($O17)=MONTH(AZ$4)),AL17*(1+Macroindicadores!I$7),IF(AND($J17="PONTUAL",MONTH($O17)=MONTH(AZ$4)),AL17*(1+Macroindicadores!I$7),IF(AND($J17="PONTUAL",MONTH($O17)<MONTH(AZ$4)),MIN($AS17:AY17),IF(AND($I17="NOVO",MONTH($O17)>MONTH(AZ$4)),AL17,IF(MONTH($O17)>MONTH(AZ$4),AL17,IF(MONTH($O17)=MONTH(AZ$4),AL17*(1+Macroindicadores!I$7),AY17))))))))) -> 16.507336 | BA17: =IF(ISBLANK(Y17),"",IF(ISBLANK($O17),AM17,IF($J17="ANUAL",AM17*(1+Macroindicadores!J$7),IF(AND($I17="NOVO",MONTH($O17)=MONTH(BA$4)),AM17*(1+Macroindicadores!J$7),IF(AND($J17="PONTUAL",MONTH($O17)=MONTH(BA$4)),AM17*(1+Macroindicadores!J$7),IF(AND($J17="PONTUAL",MONTH($O17)<MONTH(BA$4)),MIN($AS17:AZ17),IF(AND($I17="NOVO",MONTH($O17)>MONTH(BA$4)),AM17,IF(MONTH($O17)>MONTH(BA$4),AM17,IF(MONTH($O17)=MONTH(BA$4),AM17*(1+Macroindicadores!J$7),AZ17))))))))) -> 16.507336 | ... BD17: =IF(ISBLANK(AB17),"",IF(ISBLANK($O17),AP17,IF($J17="ANUAL",AP17*(1+Macroindicadores!M$7),IF(AND($I17="NOVO",MONTH($O17)=MONTH(BD$4)),AP17*(1+Macroindicadores!M$7),IF(AND($J17="PONTUAL",MONTH($O17)=MONTH(BD$4)),AP17*(1+Macroindicadores!M$7),IF(AND($J17="PONTUAL",MONTH($O17)<MONTH(BD$4)),MIN($AS17:BC17),IF(AND($I17="NOVO",MONTH($O17)>MONTH(BD$4)),AP17,IF(MONTH($O17)>MONTH(BD$4),AP17,IF(MONTH($O17)=MONTH(BD$4),AP17*(1+Macroindicadores!M$7),BC17))))))))) -> 16.507336 | BE17: =IF(AND(ISBLANK($Q17),ISBLANK($R17),ISBLANK($S17),ISBLANK($T17),ISBLANK($U17),ISBLANK($V17),ISBLANK($W17),ISBLANK($X17),ISBLANK($Y17),ISBLANK($Z17),ISBLANK($AA17),ISBLANK($AB17)),"",SUM(AS17:BD17)) -> 198.08803 | BG17: =IF(ISBLANK(Q17),"",AS17/Macroindicadores!B$2) -> 2.80737 | BH17: =IF(ISBLANK(R17),"",AT17/Macroindicadores!C$2) -> 2.80737 | BI17: =IF(ISBLANK(S17),"",AU17/Macroindicadores!D$2) -> 2.80737 | BJ17: =IF(ISBLANK(T17),"",AV17/Macroindicadores!E$2) -> 2.80737 | BK17: =IF(ISBLANK(U17),"",AW17/Macroindicadores!F$2) -> 2.80737 | BL17: =IF(ISBLANK(V17),"",AX17/Macroindicadores!G$2) -> 2.80737 | BM17: =IF(ISBLANK(W17),"",AY17/Macroindicadores!H$2) -> 2.80737 | BN17: =IF(ISBLANK(X17),"",AZ17/Macroindicadores!I$2) -> 2.80737 | ... BR17: =IF(ISBLANK(AB17),"",BD17/Macroindicadores!M$2) -> 2.80737 | BS17: =IF(AND(ISBLANK($Q17),ISBLANK($R17),ISBLANK($S17),ISBLANK($T17),ISBLANK($U17),ISBLANK($V17),ISBLANK($W17),ISBLANK($X17),ISBLANK($Y17),ISBLANK($Z17),ISBLANK($AA17),ISBLANK($AB17)),"",SUM(BG17:BR17)) -> 33.68844 | BT17: =IF(ISBLANK($L17),"",_xlfn.XLOOKUP($L17,'CENTRO CUSTO'!$A:$A,'CENTRO CUSTO'!$E:$E,FALSE,0)) -> G&A BU
A18: =IF(ISBLANK($F18),"","Budget") -> Budget | B18: =IF(ISBLANK($F18),"",$F$1) -> 2026 | C18: =IF(ISBLANK($L18),"",_xlfn.XLOOKUP($L18,'CENTRO CUSTO'!$A:$A,'CENTRO CUSTO'!F:F,FALSE,0)) -> Martini Meat | D18: =IF(ISBLANK($L18),"",_xlfn.XLOOKUP($L18,'CENTRO CUSTO'!$A:$A,'CENTRO CUSTO'!G:G,FALSE,0)) -> BU-MMAZ | E18: =IF(ISBLANK($L18),"",_xlfn.XLOOKUP($L18,'CENTRO CUSTO'!$A:$A,'CENTRO CUSTO'!H:H,FALSE,0)) -> G&A | F18: SEIDOR | G18: Applications support and maintenance | H18: SAP S4 - AMS | I18: Novo | J18: Mensal | K18: Contrato em Curso | L18: BU-MMAZ | TI | M18: =IF(ISBLANK($L18),"",_xlfn.XLOOKUP($L18,'CENTRO CUSTO'!$A:$A,'CENTRO CUSTO'!D:D,FALSE,0)) -> Alexandre Ayabe | N18: Manutenção de Informática | P18: USD | Q18: =187158*Rateio!$E$34/12 -> 7486.32 | R18: =187158*Rateio!$E$34/12 -> 7486.32 | S18: =187158*Rateio!$E$34/12 -> 7486.32 | T18: =187158*Rateio!$E$34/12 -> 7486.32 | U18: =187158*Rateio!$E$34/12 -> 7486.32 | V18: =187158*Rateio!$E$34/12 -> 7486.32 | W18: =187158*Rateio!$E$34/12 -> 7486.32 | X18: =187158*Rateio!$E$34/12 -> 7486.32 | ... AB18: =187158*Rateio!$E$34/12 -> 7486.32 | AC18: =IF(AND(ISBLANK($Q18),ISBLANK($R18),ISBLANK($S18),ISBLANK($T18),ISBLANK($U18),ISBLANK($V18),ISBLANK($W18),ISBLANK($X18),ISBLANK($Y18),ISBLANK($Z18),ISBLANK($AA18),ISBLANK($AB18)),"",SUM(Q18:AB18)) -> 89835.84 | AE18: =IF(ISBLANK(Q18),"",IF($P18="BRL",Q18,Q18*Macroindicadores!B$2)/1000) -> 44.019562 | AF18: =IF(ISBLANK(R18),"",IF($P18="BRL",R18,R18*Macroindicadores!C$2)/1000) -> 44.019562 | AG18: =IF(ISBLANK(S18),"",IF($P18="BRL",S18,S18*Macroindicadores!D$2)/1000) -> 44.019562 | AH18: =IF(ISBLANK(T18),"",IF($P18="BRL",T18,T18*Macroindicadores!E$2)/1000) -> 44.019562 | AI18: =IF(ISBLANK(U18),"",IF($P18="BRL",U18,U18*Macroindicadores!F$2)/1000) -> 44.019562 | AJ18: =IF(ISBLANK(V18),"",IF($P18="BRL",V18,V18*Macroindicadores!G$2)/1000) -> 44.019562 | AK18: =IF(ISBLANK(W18),"",IF($P18="BRL",W18,W18*Macroindicadores!H$2)/1000) -> 44.019562 | AL18: =IF(ISBLANK(X18),"",IF($P18="BRL",X18,X18*Macroindicadores!I$2)/1000) -> 44.019562 | ... AP18: =IF(ISBLANK(AB18),"",IF($P18="BRL",AB18,AB18*Macroindicadores!M$2)/1000) -> 44.019562 | AQ18: =IF(AND(ISBLANK($Q18),ISBLANK($R18),ISBLANK($S18),ISBLANK($T18),ISBLANK($U18),ISBLANK($V18),ISBLANK($W18),ISBLANK($X18),ISBLANK($Y18),ISBLANK($Z18),ISBLANK($AA18),ISBLANK($AB18)),"",SUM(AE18:AP18)) -> 528.23474 | AS18: =IF(ISBLANK(Q18),"",IF(ISBLANK($O18),AE18,IF($J18="ANUAL",AE18*(1+Macroindicadores!B$7),IF(AND($I18="NOVO",MONTH($O18)=MONTH(AS$4)),AE18*(1+Macroindicadores!B$7),IF(AND($J18="PONTUAL",MONTH($O18)=MONTH(AS$4)),AE18*(1+Macroindicadores!B$7),IF(AND($J18="PONTUAL",MONTH($O18)<MONTH(AS$4)),MIN(AR18:$AS18),IF(AND($I18="NOVO",MONTH($O18)>MONTH(AS$4)),AE18,IF(MONTH($O18)>MONTH(AS$4),AE18,IF(MONTH($O18)=MONTH(AS$4),AE18*(1+Macroindicadores!B$7),AR18))))))))) -> 44.019562 | AT18: =IF(ISBLANK(R18),"",IF(ISBLANK($O18),AF18,IF($J18="ANUAL",AF18*(1+Macroindicadores!C$7),IF(AND($I18="NOVO",MONTH($O18)=MONTH(AT$4)),AF18*(1+Macroindicadores!C$7),IF(AND($J18="PONTUAL",MONTH($O18)=MONTH(AT$4)),AF18*(1+Macroindicadores!C$7),IF(AND($J18="PONTUAL",MONTH($O18)<MONTH(AT$4)),MIN($AS18:AS18),IF(AND($I18="NOVO",MONTH($O18)>MONTH(AT$4)),AF18,IF(MONTH($O18)>MONTH(AT$4),AF18,IF(MONTH($O18)=MONTH(AT$4),AF18*(1+Macroindicadores!C$7),AS18))))))))) -> 44.019562 | AU18: =IF(ISBLANK(S18),"",IF(ISBLANK($O18),AG18,IF($J18="ANUAL",AG18*(1+Macroindicadores!D$7),IF(AND($I18="NOVO",MONTH($O18)=MONTH(AU$4)),AG18*(1+Macroindicadores!D$7),IF(AND($J18="PONTUAL",MONTH($O18)=MONTH(AU$4)),AG18*(1+Macroindicadores!D$7),IF(AND($J18="PONTUAL",MONTH($O18)<MONTH(AU$4)),MIN($AS18:AT18),IF(AND($I18="NOVO",MONTH($O18)>MONTH(AU$4)),AG18,IF(MONTH($O18)>MONTH(AU$4),AG18,IF(MONTH($O18)=MONTH(AU$4),AG18*(1+Macroindicadores!D$7),AT18))))))))) -> 44.019562 | AV18: =IF(ISBLANK(T18),"",IF(ISBLANK($O18),AH18,IF($J18="ANUAL",AH18*(1+Macroindicadores!E$7),IF(AND($I18="NOVO",MONTH($O18)=MONTH(AV$4)),AH18*(1+Macroindicadores!E$7),IF(AND($J18="PONTUAL",MONTH($O18)=MONTH(AV$4)),AH18*(1+Macroindicadores!E$7),IF(AND($J18="PONTUAL",MONTH($O18)<MONTH(AV$4)),MIN($AS18:AU18),IF(AND($I18="NOVO",MONTH($O18)>MONTH(AV$4)),AH18,IF(MONTH($O18)>MONTH(AV$4),AH18,IF(MONTH($O18)=MONTH(AV$4),AH18*(1+Macroindicadores!E$7),AU18))))))))) -> 44.019562 | AW18: =IF(ISBLANK(U18),"",IF(ISBLANK($O18),AI18,IF($J18="ANUAL",AI18*(1+Macroindicadores!F$7),IF(AND($I18="NOVO",MONTH($O18)=MONTH(AW$4)),AI18*(1+Macroindicadores!F$7),IF(AND($J18="PONTUAL",MONTH($O18)=MONTH(AW$4)),AI18*(1+Macroindicadores!F$7),IF(AND($J18="PONTUAL",MONTH($O18)<MONTH(AW$4)),MIN($AS18:AV18),IF(AND($I18="NOVO",MONTH($O18)>MONTH(AW$4)),AI18,IF(MONTH($O18)>MONTH(AW$4),AI18,IF(MONTH($O18)=MONTH(AW$4),AI18*(1+Macroindicadores!F$7),AV18))))))))) -> 44.019562 | AX18: =IF(ISBLANK(V18),"",IF(ISBLANK($O18),AJ18,IF($J18="ANUAL",AJ18*(1+Macroindicadores!G$7),IF(AND($I18="NOVO",MONTH($O18)=MONTH(AX$4)),AJ18*(1+Macroindicadores!G$7),IF(AND($J18="PONTUAL",MONTH($O18)=MONTH(AX$4)),AJ18*(1+Macroindicadores!G$7),IF(AND($J18="PONTUAL",MONTH($O18)<MONTH(AX$4)),MIN($AS18:AW18),IF(AND($I18="NOVO",MONTH($O18)>MONTH(AX$4)),AJ18,IF(MONTH($O18)>MONTH(AX$4),AJ18,IF(MONTH($O18)=MONTH(AX$4),AJ18*(1+Macroindicadores!G$7),AW18))))))))) -> 44.019562 | AY18: =IF(ISBLANK(W18),"",IF(ISBLANK($O18),AK18,IF($J18="ANUAL",AK18*(1+Macroindicadores!H$7),IF(AND($I18="NOVO",MONTH($O18)=MONTH(AY$4)),AK18*(1+Macroindicadores!H$7),IF(AND($J18="PONTUAL",MONTH($O18)=MONTH(AY$4)),AK18*(1+Macroindicadores!H$7),IF(AND($J18="PONTUAL",MONTH($O18)<MONTH(AY$4)),MIN($AS18:AX18),IF(AND($I18="NOVO",MONTH($O18)>MONTH(AY$4)),AK18,IF(MONTH($O18)>MONTH(AY$4),AK18,IF(MONTH($O18)=MONTH(AY$4),AK18*(1+Macroindicadores!H$7),AX18))))))))) -> 44.019562 | AZ18: =IF(ISBLANK(X18),"",IF(ISBLANK($O18),AL18,IF($J18="ANUAL",AL18*(1+Macroindicadores!I$7),IF(AND($I18="NOVO",MONTH($O18)=MONTH(AZ$4)),AL18*(1+Macroindicadores!I$7),IF(AND($J18="PONTUAL",MONTH($O18)=MONTH(AZ$4)),AL18*(1+Macroindicadores!I$7),IF(AND($J18="PONTUAL",MONTH($O18)<MONTH(AZ$4)),MIN($AS18:AY18),IF(AND($I18="NOVO",MONTH($O18)>MONTH(AZ$4)),AL18,IF(MONTH($O18)>MONTH(AZ$4),AL18,IF(MONTH($O18)=MONTH(AZ$4),AL18*(1+Macroindicadores!I$7),AY18))))))))) -> 44.019562 | BA18: =IF(ISBLANK(Y18),"",IF(ISBLANK($O18),AM18,IF($J18="ANUAL",AM18*(1+Macroindicadores!J$7),IF(AND($I18="NOVO",MONTH($O18)=MONTH(BA$4)),AM18*(1+Macroindicadores!J$7),IF(AND($J18="PONTUAL",MONTH($O18)=MONTH(BA$4)),AM18*(1+Macroindicadores!J$7),IF(AND($J18="PONTUAL",MONTH($O18)<MONTH(BA$4)),MIN($AS18:AZ18),IF(AND($I18="NOVO",MONTH($O18)>MONTH(BA$4)),AM18,IF(MONTH($O18)>MONTH(BA$4),AM18,IF(MONTH($O18)=MONTH(BA$4),AM18*(1+Macroindicadores!J$7),AZ18))))))))) -> 44.019562 | ... BD18: =IF(ISBLANK(AB18),"",IF(ISBLANK($O18),AP18,IF($J18="ANUAL",AP18*(1+Macroindicadores!M$7),IF(AND($I18="NOVO",MONTH($O18)=MONTH(BD$4)),AP18*(1+Macroindicadores!M$7),IF(AND($J18="PONTUAL",MONTH($O18)=MONTH(BD$4)),AP18*(1+Macroindicadores!M$7),IF(AND($J18="PONTUAL",MONTH($O18)<MONTH(BD$4)),MIN($AS18:BC18),IF(AND($I18="NOVO",MONTH($O18)>MONTH(BD$4)),AP18,IF(MONTH($O18)>MONTH(BD$4),AP18,IF(MONTH($O18)=MONTH(BD$4),AP18*(1+Macroindicadores!M$7),BC18))))))))) -> 44.019562 | BE18: =IF(AND(ISBLANK($Q18),ISBLANK($R18),ISBLANK($S18),ISBLANK($T18),ISBLANK($U18),ISBLANK($V18),ISBLANK($W18),ISBLANK($X18),ISBLANK($Y18),ISBLANK($Z18),ISBLANK($AA18),ISBLANK($AB18)),"",SUM(AS18:BD18)) -> 528.23474 | BG18: =IF(ISBLANK(Q18),"",AS18/Macroindicadores!B$2) -> 7.48632 | BH18: =IF(ISBLANK(R18),"",AT18/Macroindicadores!C$2) -> 7.48632 | BI18: =IF(ISBLANK(S18),"",AU18/Macroindicadores!D$2) -> 7.48632 | BJ18: =IF(ISBLANK(T18),"",AV18/Macroindicadores!E$2) -> 7.48632 | BK18: =IF(ISBLANK(U18),"",AW18/Macroindicadores!F$2) -> 7.48632 | BL18: =IF(ISBLANK(V18),"",AX18/Macroindicadores!G$2) -> 7.48632 | BM18: =IF(ISBLANK(W18),"",AY18/Macroindicadores!H$2) -> 7.48632 | BN18: =IF(ISBLANK(X18),"",AZ18/Macroindicadores!I$2) -> 7.48632 | ... BR18: =IF(ISBLANK(AB18),"",BD18/Macroindicadores!M$2) -> 7.48632 | BS18: =IF(AND(ISBLANK($Q18),ISBLANK($R18),ISBLANK($S18),ISBLANK($T18),ISBLANK($U18),ISBLANK($V18),ISBLANK($W18),ISBLANK($X18),ISBLANK($Y18),ISBLANK($Z18),ISBLANK($AA18),ISBLANK($AB18)),"",SUM(BG18:BR18)) -> 89.83584 | BT18: =IF(ISBLANK($L18),"",_xlfn.XLOOKUP($L18,'CENTRO CUSTO'!$A:$A,'CENTRO CUSTO'!$E:$E,FALSE,0)) -> G&A BU
A19: =IF(ISBLANK($F19),"","Budget") -> Budget | B19: =IF(ISBLANK($F19),"",$F$1) -> 2026 | C19: =IF(ISBLANK($L19),"",_xlfn.XLOOKUP($L19,'CENTRO CUSTO'!$A:$A,'CENTRO CUSTO'!F:F,FALSE,0)) -> MRV | D19: =IF(ISBLANK($L19),"",_xlfn.XLOOKUP($L19,'CENTRO CUSTO'!$A:$A,'CENTRO CUSTO'!G:G,FALSE,0)) -> BU-MRV | E19: =IF(ISBLANK($L19),"",_xlfn.XLOOKUP($L19,'CENTRO CUSTO'!$A:$A,'CENTRO CUSTO'!H:H,FALSE,0)) -> G&A | F19: SEIDOR | G19: Applications support and maintenance | H19: SAP S4 - AMS | I19: Novo | J19: Mensal | K19: Contrato em Curso | L19: BU-MRV | TI | M19: =IF(ISBLANK($L19),"",_xlfn.XLOOKUP($L19,'CENTRO CUSTO'!$A:$A,'CENTRO CUSTO'!D:D,FALSE,0)) -> Alexandre Ayabe | N19: Manutenção de Informática | P19: USD | Q19: =187158*Rateio!$E$50/12 -> 779.825 | R19: =187158*Rateio!$E$50/12 -> 779.825 | S19: =187158*Rateio!$E$50/12 -> 779.825 | T19: =187158*Rateio!$E$50/12 -> 779.825 | U19: =187158*Rateio!$E$50/12 -> 779.825 | V19: =187158*Rateio!$E$50/12 -> 779.825 | W19: =187158*Rateio!$E$50/12 -> 779.825 | X19: =187158*Rateio!$E$50/12 -> 779.825 | ... AB19: =187158*Rateio!$E$50/12 -> 779.825 | AC19: =IF(AND(ISBLANK($Q19),ISBLANK($R19),ISBLANK($S19),ISBLANK($T19),ISBLANK($U19),ISBLANK($V19),ISBLANK($W19),ISBLANK($X19),ISBLANK($Y19),ISBLANK($Z19),ISBLANK($AA19),ISBLANK($AB19)),"",SUM(Q19:AB19)) -> 9357.9 | AE19: =IF(ISBLANK(Q19),"",IF($P19="BRL",Q19,Q19*Macroindicadores!B$2)/1000) -> 4.585371 | AF19: =IF(ISBLANK(R19),"",IF($P19="BRL",R19,R19*Macroindicadores!C$2)/1000) -> 4.585371 | AG19: =IF(ISBLANK(S19),"",IF($P19="BRL",S19,S19*Macroindicadores!D$2)/1000) -> 4.585371 | AH19: =IF(ISBLANK(T19),"",IF($P19="BRL",T19,T19*Macroindicadores!E$2)/1000) -> 4.585371 | AI19: =IF(ISBLANK(U19),"",IF($P19="BRL",U19,U19*Macroindicadores!F$2)/1000) -> 4.585371 | AJ19: =IF(ISBLANK(V19),"",IF($P19="BRL",V19,V19*Macroindicadores!G$2)/1000) -> 4.585371 | AK19: =IF(ISBLANK(W19),"",IF($P19="BRL",W19,W19*Macroindicadores!H$2)/1000) -> 4.585371 | AL19: =IF(ISBLANK(X19),"",IF($P19="BRL",X19,X19*Macroindicadores!I$2)/1000) -> 4.585371 | ... AP19: =IF(ISBLANK(AB19),"",IF($P19="BRL",AB19,AB19*Macroindicadores!M$2)/1000) -> 4.585371 | AQ19: =IF(AND(ISBLANK($Q19),ISBLANK($R19),ISBLANK($S19),ISBLANK($T19),ISBLANK($U19),ISBLANK($V19),ISBLANK($W19),ISBLANK($X19),ISBLANK($Y19),ISBLANK($Z19),ISBLANK($AA19),ISBLANK($AB19)),"",SUM(AE19:AP19)) -> 55.024452 | AS19: =IF(ISBLANK(Q19),"",IF(ISBLANK($O19),AE19,IF($J19="ANUAL",AE19*(1+Macroindicadores!B$7),IF(AND($I19="NOVO",MONTH($O19)=MONTH(AS$4)),AE19*(1+Macroindicadores!B$7),IF(AND($J19="PONTUAL",MONTH($O19)=MONTH(AS$4)),AE19*(1+Macroindicadores!B$7),IF(AND($J19="PONTUAL",MONTH($O19)<MONTH(AS$4)),MIN(AR19:$AS19),IF(AND($I19="NOVO",MONTH($O19)>MONTH(AS$4)),AE19,IF(MONTH($O19)>MONTH(AS$4),AE19,IF(MONTH($O19)=MONTH(AS$4),AE19*(1+Macroindicadores!B$7),AR19))))))))) -> 4.585371 | AT19: =IF(ISBLANK(R19),"",IF(ISBLANK($O19),AF19,IF($J19="ANUAL",AF19*(1+Macroindicadores!C$7),IF(AND($I19="NOVO",MONTH($O19)=MONTH(AT$4)),AF19*(1+Macroindicadores!C$7),IF(AND($J19="PONTUAL",MONTH($O19)=MONTH(AT$4)),AF19*(1+Macroindicadores!C$7),IF(AND($J19="PONTUAL",MONTH($O19)<MONTH(AT$4)),MIN($AS19:AS19),IF(AND($I19="NOVO",MONTH($O19)>MONTH(AT$4)),AF19,IF(MONTH($O19)>MONTH(AT$4),AF19,IF(MONTH($O19)=MONTH(AT$4),AF19*(1+Macroindicadores!C$7),AS19))))))))) -> 4.585371 | AU19: =IF(ISBLANK(S19),"",IF(ISBLANK($O19),AG19,IF($J19="ANUAL",AG19*(1+Macroindicadores!D$7),IF(AND($I19="NOVO",MONTH($O19)=MONTH(AU$4)),AG19*(1+Macroindicadores!D$7),IF(AND($J19="PONTUAL",MONTH($O19)=MONTH(AU$4)),AG19*(1+Macroindicadores!D$7),IF(AND($J19="PONTUAL",MONTH($O19)<MONTH(AU$4)),MIN($AS19:AT19),IF(AND($I19="NOVO",MONTH($O19)>MONTH(AU$4)),AG19,IF(MONTH($O19)>MONTH(AU$4),AG19,IF(MONTH($O19)=MONTH(AU$4),AG19*(1+Macroindicadores!D$7),AT19))))))))) -> 4.585371 | AV19: =IF(ISBLANK(T19),"",IF(ISBLANK($O19),AH19,IF($J19="ANUAL",AH19*(1+Macroindicadores!E$7),IF(AND($I19="NOVO",MONTH($O19)=MONTH(AV$4)),AH19*(1+Macroindicadores!E$7),IF(AND($J19="PONTUAL",MONTH($O19)=MONTH(AV$4)),AH19*(1+Macroindicadores!E$7),IF(AND($J19="PONTUAL",MONTH($O19)<MONTH(AV$4)),MIN($AS19:AU19),IF(AND($I19="NOVO",MONTH($O19)>MONTH(AV$4)),AH19,IF(MONTH($O19)>MONTH(AV$4),AH19,IF(MONTH($O19)=MONTH(AV$4),AH19*(1+Macroindicadores!E$7),AU19))))))))) -> 4.585371 | AW19: =IF(ISBLANK(U19),"",IF(ISBLANK($O19),AI19,IF($J19="ANUAL",AI19*(1+Macroindicadores!F$7),IF(AND($I19="NOVO",MONTH($O19)=MONTH(AW$4)),AI19*(1+Macroindicadores!F$7),IF(AND($J19="PONTUAL",MONTH($O19)=MONTH(AW$4)),AI19*(1+Macroindicadores!F$7),IF(AND($J19="PONTUAL",MONTH($O19)<MONTH(AW$4)),MIN($AS19:AV19),IF(AND($I19="NOVO",MONTH($O19)>MONTH(AW$4)),AI19,IF(MONTH($O19)>MONTH(AW$4),AI19,IF(MONTH($O19)=MONTH(AW$4),AI19*(1+Macroindicadores!F$7),AV19))))))))) -> 4.585371 | AX19: =IF(ISBLANK(V19),"",IF(ISBLANK($O19),AJ19,IF($J19="ANUAL",AJ19*(1+Macroindicadores!G$7),IF(AND($I19="NOVO",MONTH($O19)=MONTH(AX$4)),AJ19*(1+Macroindicadores!G$7),IF(AND($J19="PONTUAL",MONTH($O19)=MONTH(AX$4)),AJ19*(1+Macroindicadores!G$7),IF(AND($J19="PONTUAL",MONTH($O19)<MONTH(AX$4)),MIN($AS19:AW19),IF(AND($I19="NOVO",MONTH($O19)>MONTH(AX$4)),AJ19,IF(MONTH($O19)>MONTH(AX$4),AJ19,IF(MONTH($O19)=MONTH(AX$4),AJ19*(1+Macroindicadores!G$7),AW19))))))))) -> 4.585371 | AY19: =IF(ISBLANK(W19),"",IF(ISBLANK($O19),AK19,IF($J19="ANUAL",AK19*(1+Macroindicadores!H$7),IF(AND($I19="NOVO",MONTH($O19)=MONTH(AY$4)),AK19*(1+Macroindicadores!H$7),IF(AND($J19="PONTUAL",MONTH($O19)=MONTH(AY$4)),AK19*(1+Macroindicadores!H$7),IF(AND($J19="PONTUAL",MONTH($O19)<MONTH(AY$4)),MIN($AS19:AX19),IF(AND($I19="NOVO",MONTH($O19)>MONTH(AY$4)),AK19,IF(MONTH($O19)>MONTH(AY$4),AK19,IF(MONTH($O19)=MONTH(AY$4),AK19*(1+Macroindicadores!H$7),AX19))))))))) -> 4.585371 | AZ19: =IF(ISBLANK(X19),"",IF(ISBLANK($O19),AL19,IF($J19="ANUAL",AL19*(1+Macroindicadores!I$7),IF(AND($I19="NOVO",MONTH($O19)=MONTH(AZ$4)),AL19*(1+Macroindicadores!I$7),IF(AND($J19="PONTUAL",MONTH($O19)=MONTH(AZ$4)),AL19*(1+Macroindicadores!I$7),IF(AND($J19="PONTUAL",MONTH($O19)<MONTH(AZ$4)),MIN($AS19:AY19),IF(AND($I19="NOVO",MONTH($O19)>MONTH(AZ$4)),AL19,IF(MONTH($O19)>MONTH(AZ$4),AL19,IF(MONTH($O19)=MONTH(AZ$4),AL19*(1+Macroindicadores!I$7),AY19))))))))) -> 4.585371 | BA19: =IF(ISBLANK(Y19),"",IF(ISBLANK($O19),AM19,IF($J19="ANUAL",AM19*(1+Macroindicadores!J$7),IF(AND($I19="NOVO",MONTH($O19)=MONTH(BA$4)),AM19*(1+Macroindicadores!J$7),IF(AND($J19="PONTUAL",MONTH($O19)=MONTH(BA$4)),AM19*(1+Macroindicadores!J$7),IF(AND($J19="PONTUAL",MONTH($O19)<MONTH(BA$4)),MIN($AS19:AZ19),IF(AND($I19="NOVO",MONTH($O19)>MONTH(BA$4)),AM19,IF(MONTH($O19)>MONTH(BA$4),AM19,IF(MONTH($O19)=MONTH(BA$4),AM19*(1+Macroindicadores!J$7),AZ19))))))))) -> 4.585371 | ... BD19: =IF(ISBLANK(AB19),"",IF(ISBLANK($O19),AP19,IF($J19="ANUAL",AP19*(1+Macroindicadores!M$7),IF(AND($I19="NOVO",MONTH($O19)=MONTH(BD$4)),AP19*(1+Macroindicadores!M$7),IF(AND($J19="PONTUAL",MONTH($O19)=MONTH(BD$4)),AP19*(1+Macroindicadores!M$7),IF(AND($J19="PONTUAL",MONTH($O19)<MONTH(BD$4)),MIN($AS19:BC19),IF(AND($I19="NOVO",MONTH($O19)>MONTH(BD$4)),AP19,IF(MONTH($O19)>MONTH(BD$4),AP19,IF(MONTH($O19)=MONTH(BD$4),AP19*(1+Macroindicadores!M$7),BC19))))))))) -> 4.585371 | BE19: =IF(AND(ISBLANK($Q19),ISBLANK($R19),ISBLANK($S19),ISBLANK($T19),ISBLANK($U19),ISBLANK($V19),ISBLANK($W19),ISBLANK($X19),ISBLANK($Y19),ISBLANK($Z19),ISBLANK($AA19),ISBLANK($AB19)),"",SUM(AS19:BD19)) -> 55.024452 | BG19: =IF(ISBLANK(Q19),"",AS19/Macroindicadores!B$2) -> 0.779825 | BH19: =IF(ISBLANK(R19),"",AT19/Macroindicadores!C$2) -> 0.779825 | BI19: =IF(ISBLANK(S19),"",AU19/Macroindicadores!D$2) -> 0.779825 | BJ19: =IF(ISBLANK(T19),"",AV19/Macroindicadores!E$2) -> 0.779825 | BK19: =IF(ISBLANK(U19),"",AW19/Macroindicadores!F$2) -> 0.779825 | BL19: =IF(ISBLANK(V19),"",AX19/Macroindicadores!G$2) -> 0.779825 | BM19: =IF(ISBLANK(W19),"",AY19/Macroindicadores!H$2) -> 0.779825 | BN19: =IF(ISBLANK(X19),"",AZ19/Macroindicadores!I$2) -> 0.779825 | ... BR19: =IF(ISBLANK(AB19),"",BD19/Macroindicadores!M$2) -> 0.779825 | BS19: =IF(AND(ISBLANK($Q19),ISBLANK($R19),ISBLANK($S19),ISBLANK($T19),ISBLANK($U19),ISBLANK($V19),ISBLANK($W19),ISBLANK($X19),ISBLANK($Y19),ISBLANK($Z19),ISBLANK($AA19),ISBLANK($AB19)),"",SUM(BG19:BR19)) -> 9.3579 | BT19: =IF(ISBLANK($L19),"",_xlfn.XLOOKUP($L19,'CENTRO CUSTO'!$A:$A,'CENTRO CUSTO'!$E:$E,FALSE,0)) -> G&A BU
A20: =IF(ISBLANK($F20),"","Budget") -> Budget | B20: =IF(ISBLANK($F20),"",$F$1) -> 2026 | C20: =IF(ISBLANK($L20),"",_xlfn.XLOOKUP($L20,'CENTRO CUSTO'!$A:$A,'CENTRO CUSTO'!F:F,FALSE,0)) -> SKM | D20: =IF(ISBLANK($L20),"",_xlfn.XLOOKUP($L20,'CENTRO CUSTO'!$A:$A,'CENTRO CUSTO'!G:G,FALSE,0)) -> BU-SKM | E20: =IF(ISBLANK($L20),"",_xlfn.XLOOKUP($L20,'CENTRO CUSTO'!$A:$A,'CENTRO CUSTO'!H:H,FALSE,0)) -> G&A | F20: SEIDOR | G20: Applications support and maintenance | H20: SAP S4 - AMS | I20: Existente | J20: Mensal | K20: Contrato em Curso | L20: BU-GRU | TI | M20: =IF(ISBLANK($L20),"",_xlfn.XLOOKUP($L20,'CENTRO CUSTO'!$A:$A,'CENTRO CUSTO'!D:D,FALSE,0)) -> Alexandre Ayabe | N20: Manutenção de Informática | P20: USD | Q20: =187158*Rateio!$E$53/12 -> 935.79 | R20: =187158*Rateio!$E$53/12 -> 935.79 | S20: =187158*Rateio!$E$53/12 -> 935.79 | T20: =187158*Rateio!$E$53/12 -> 935.79 | U20: =187158*Rateio!$E$53/12 -> 935.79 | V20: =187158*Rateio!$E$53/12 -> 935.79 | W20: =187158*Rateio!$E$53/12 -> 935.79 | X20: =187158*Rateio!$E$53/12 -> 935.79 | ... AB20: =187158*Rateio!$E$53/12 -> 935.79 | AC20: =IF(AND(ISBLANK($Q20),ISBLANK($R20),ISBLANK($S20),ISBLANK($T20),ISBLANK($U20),ISBLANK($V20),ISBLANK($W20),ISBLANK($X20),ISBLANK($Y20),ISBLANK($Z20),ISBLANK($AA20),ISBLANK($AB20)),"",SUM(Q20:AB20)) -> 11229.48 | AE20: =IF(ISBLANK(Q20),"",IF($P20="BRL",Q20,Q20*Macroindicadores!B$2)/1000) -> 5.5024452 | AF20: =IF(ISBLANK(R20),"",IF($P20="BRL",R20,R20*Macroindicadores!C$2)/1000) -> 5.5024452 | AG20: =IF(ISBLANK(S20),"",IF($P20="BRL",S20,S20*Macroindicadores!D$2)/1000) -> 5.5024452 | AH20: =IF(ISBLANK(T20),"",IF($P20="BRL",T20,T20*Macroindicadores!E$2)/1000) -> 5.5024452 | AI20: =IF(ISBLANK(U20),"",IF($P20="BRL",U20,U20*Macroindicadores!F$2)/1000) -> 5.5024452 | AJ20: =IF(ISBLANK(V20),"",IF($P20="BRL",V20,V20*Macroindicadores!G$2)/1000) -> 5.5024452 | AK20: =IF(ISBLANK(W20),"",IF($P20="BRL",W20,W20*Macroindicadores!H$2)/1000) -> 5.5024452 | AL20: =IF(ISBLANK(X20),"",IF($P20="BRL",X20,X20*Macroindicadores!I$2)/1000) -> 5.5024452 | ... AP20: =IF(ISBLANK(AB20),"",IF($P20="BRL",AB20,AB20*Macroindicadores!M$2)/1000) -> 5.5024452 | AQ20: =IF(AND(ISBLANK($Q20),ISBLANK($R20),ISBLANK($S20),ISBLANK($T20),ISBLANK($U20),ISBLANK($V20),ISBLANK($W20),ISBLANK($X20),ISBLANK($Y20),ISBLANK($Z20),ISBLANK($AA20),ISBLANK($AB20)),"",SUM(AE20:AP20)) -> 66.029342 | AS20: =IF(ISBLANK(Q20),"",IF(ISBLANK($O20),AE20,IF($J20="ANUAL",AE20*(1+Macroindicadores!B$7),IF(AND($I20="NOVO",MONTH($O20)=MONTH(AS$4)),AE20*(1+Macroindicadores!B$7),IF(AND($J20="PONTUAL",MONTH($O20)=MONTH(AS$4)),AE20*(1+Macroindicadores!B$7),IF(AND($J20="PONTUAL",MONTH($O20)<MONTH(AS$4)),MIN(AR20:$AS20),IF(AND($I20="NOVO",MONTH($O20)>MONTH(AS$4)),AE20,IF(MONTH($O20)>MONTH(AS$4),AE20,IF(MONTH($O20)=MONTH(AS$4),AE20*(1+Macroindicadores!B$7),AR20))))))))) -> 5.5024452 | AT20: =IF(ISBLANK(R20),"",IF(ISBLANK($O20),AF20,IF($J20="ANUAL",AF20*(1+Macroindicadores!C$7),IF(AND($I20="NOVO",MONTH($O20)=MONTH(AT$4)),AF20*(1+Macroindicadores!C$7),IF(AND($J20="PONTUAL",MONTH($O20)=MONTH(AT$4)),AF20*(1+Macroindicadores!C$7),IF(AND($J20="PONTUAL",MONTH($O20)<MONTH(AT$4)),MIN($AS20:AS20),IF(AND($I20="NOVO",MONTH($O20)>MONTH(AT$4)),AF20,IF(MONTH($O20)>MONTH(AT$4),AF20,IF(MONTH($O20)=MONTH(AT$4),AF20*(1+Macroindicadores!C$7),AS20))))))))) -> 5.5024452 | AU20: =IF(ISBLANK(S20),"",IF(ISBLANK($O20),AG20,IF($J20="ANUAL",AG20*(1+Macroindicadores!D$7),IF(AND($I20="NOVO",MONTH($O20)=MONTH(AU$4)),AG20*(1+Macroindicadores!D$7),IF(AND($J20="PONTUAL",MONTH($O20)=MONTH(AU$4)),AG20*(1+Macroindicadores!D$7),IF(AND($J20="PONTUAL",MONTH($O20)<MONTH(AU$4)),MIN($AS20:AT20),IF(AND($I20="NOVO",MONTH($O20)>MONTH(AU$4)),AG20,IF(MONTH($O20)>MONTH(AU$4),AG20,IF(MONTH($O20)=MONTH(AU$4),AG20*(1+Macroindicadores!D$7),AT20))))))))) -> 5.5024452 | AV20: =IF(ISBLANK(T20),"",IF(ISBLANK($O20),AH20,IF($J20="ANUAL",AH20*(1+Macroindicadores!E$7),IF(AND($I20="NOVO",MONTH($O20)=MONTH(AV$4)),AH20*(1+Macroindicadores!E$7),IF(AND($J20="PONTUAL",MONTH($O20)=MONTH(AV$4)),AH20*(1+Macroindicadores!E$7),IF(AND($J20="PONTUAL",MONTH($O20)<MONTH(AV$4)),MIN($AS20:AU20),IF(AND($I20="NOVO",MONTH($O20)>MONTH(AV$4)),AH20,IF(MONTH($O20)>MONTH(AV$4),AH20,IF(MONTH($O20)=MONTH(AV$4),AH20*(1+Macroindicadores!E$7),AU20))))))))) -> 5.5024452 | AW20: =IF(ISBLANK(U20),"",IF(ISBLANK($O20),AI20,IF($J20="ANUAL",AI20*(1+Macroindicadores!F$7),IF(AND($I20="NOVO",MONTH($O20)=MONTH(AW$4)),AI20*(1+Macroindicadores!F$7),IF(AND($J20="PONTUAL",MONTH($O20)=MONTH(AW$4)),AI20*(1+Macroindicadores!F$7),IF(AND($J20="PONTUAL",MONTH($O20)<MONTH(AW$4)),MIN($AS20:AV20),IF(AND($I20="NOVO",MONTH($O20)>MONTH(AW$4)),AI20,IF(MONTH($O20)>MONTH(AW$4),AI20,IF(MONTH($O20)=MONTH(AW$4),AI20*(1+Macroindicadores!F$7),AV20))))))))) -> 5.5024452 | AX20: =IF(ISBLANK(V20),"",IF(ISBLANK($O20),AJ20,IF($J20="ANUAL",AJ20*(1+Macroindicadores!G$7),IF(AND($I20="NOVO",MONTH($O20)=MONTH(AX$4)),AJ20*(1+Macroindicadores!G$7),IF(AND($J20="PONTUAL",MONTH($O20)=MONTH(AX$4)),AJ20*(1+Macroindicadores!G$7),IF(AND($J20="PONTUAL",MONTH($O20)<MONTH(AX$4)),MIN($AS20:AW20),IF(AND($I20="NOVO",MONTH($O20)>MONTH(AX$4)),AJ20,IF(MONTH($O20)>MONTH(AX$4),AJ20,IF(MONTH($O20)=MONTH(AX$4),AJ20*(1+Macroindicadores!G$7),AW20))))))))) -> 5.5024452 | AY20: =IF(ISBLANK(W20),"",IF(ISBLANK($O20),AK20,IF($J20="ANUAL",AK20*(1+Macroindicadores!H$7),IF(AND($I20="NOVO",MONTH($O20)=MONTH(AY$4)),AK20*(1+Macroindicadores!H$7),IF(AND($J20="PONTUAL",MONTH($O20)=MONTH(AY$4)),AK20*(1+Macroindicadores!H$7),IF(AND($J20="PONTUAL",MONTH($O20)<MONTH(AY$4)),MIN($AS20:AX20),IF(AND($I20="NOVO",MONTH($O20)>MONTH(AY$4)),AK20,IF(MONTH($O20)>MONTH(AY$4),AK20,IF(MONTH($O20)=MONTH(AY$4),AK20*(1+Macroindicadores!H$7),AX20))))))))) -> 5.5024452 | AZ20: =IF(ISBLANK(X20),"",IF(ISBLANK($O20),AL20,IF($J20="ANUAL",AL20*(1+Macroindicadores!I$7),IF(AND($I20="NOVO",MONTH($O20)=MONTH(AZ$4)),AL20*(1+Macroindicadores!I$7),IF(AND($J20="PONTUAL",MONTH($O20)=MONTH(AZ$4)),AL20*(1+Macroindicadores!I$7),IF(AND($J20="PONTUAL",MONTH($O20)<MONTH(AZ$4)),MIN($AS20:AY20),IF(AND($I20="NOVO",MONTH($O20)>MONTH(AZ$4)),AL20,IF(MONTH($O20)>MONTH(AZ$4),AL20,IF(MONTH($O20)=MONTH(AZ$4),AL20*(1+Macroindicadores!I$7),AY20))))))))) -> 5.5024452 | BA20: =IF(ISBLANK(Y20),"",IF(ISBLANK($O20),AM20,IF($J20="ANUAL",AM20*(1+Macroindicadores!J$7),IF(AND($I20="NOVO",MONTH($O20)=MONTH(BA$4)),AM20*(1+Macroindicadores!J$7),IF(AND($J20="PONTUAL",MONTH($O20)=MONTH(BA$4)),AM20*(1+Macroindicadores!J$7),IF(AND($J20="PONTUAL",MONTH($O20)<MONTH(BA$4)),MIN($AS20:AZ20),IF(AND($I20="NOVO",MONTH($O20)>MONTH(BA$4)),AM20,IF(MONTH($O20)>MONTH(BA$4),AM20,IF(MONTH($O20)=MONTH(BA$4),AM20*(1+Macroindicadores!J$7),AZ20))))))))) -> 5.5024452 | ... BD20: =IF(ISBLANK(AB20),"",IF(ISBLANK($O20),AP20,IF($J20="ANUAL",AP20*(1+Macroindicadores!M$7),IF(AND($I20="NOVO",MONTH($O20)=MONTH(BD$4)),AP20*(1+Macroindicadores!M$7),IF(AND($J20="PONTUAL",MONTH($O20)=MONTH(BD$4)),AP20*(1+Macroindicadores!M$7),IF(AND($J20="PONTUAL",MONTH($O20)<MONTH(BD$4)),MIN($AS20:BC20),IF(AND($I20="NOVO",MONTH($O20)>MONTH(BD$4)),AP20,IF(MONTH($O20)>MONTH(BD$4),AP20,IF(MONTH($O20)=MONTH(BD$4),AP20*(1+Macroindicadores!M$7),BC20))))))))) -> 5.5024452 | BE20: =IF(AND(ISBLANK($Q20),ISBLANK($R20),ISBLANK($S20),ISBLANK($T20),ISBLANK($U20),ISBLANK($V20),ISBLANK($W20),ISBLANK($X20),ISBLANK($Y20),ISBLANK($Z20),ISBLANK($AA20),ISBLANK($AB20)),"",SUM(AS20:BD20)) -> 66.029342 | BG20: =IF(ISBLANK(Q20),"",AS20/Macroindicadores!B$2) -> 0.93579 | BH20: =IF(ISBLANK(R20),"",AT20/Macroindicadores!C$2) -> 0.93579 | BI20: =IF(ISBLANK(S20),"",AU20/Macroindicadores!D$2) -> 0.93579 | BJ20: =IF(ISBLANK(T20),"",AV20/Macroindicadores!E$2) -> 0.93579 | BK20: =IF(ISBLANK(U20),"",AW20/Macroindicadores!F$2) -> 0.93579 | BL20: =IF(ISBLANK(V20),"",AX20/Macroindicadores!G$2) -> 0.93579 | BM20: =IF(ISBLANK(W20),"",AY20/Macroindicadores!H$2) -> 0.93579 | BN20: =IF(ISBLANK(X20),"",AZ20/Macroindicadores!I$2) -> 0.93579 | ... BR20: =IF(ISBLANK(AB20),"",BD20/Macroindicadores!M$2) -> 0.93579 | BS20: =IF(AND(ISBLANK($Q20),ISBLANK($R20),ISBLANK($S20),ISBLANK($T20),ISBLANK($U20),ISBLANK($V20),ISBLANK($W20),ISBLANK($X20),ISBLANK($Y20),ISBLANK($Z20),ISBLANK($AA20),ISBLANK($AB20)),"",SUM(BG20:BR20)) -> 11.22948 | BT20: =IF(ISBLANK($L20),"",_xlfn.XLOOKUP($L20,'CENTRO CUSTO'!$A:$A,'CENTRO CUSTO'!$E:$E,FALSE,0)) -> G&A BU
A21: =IF(ISBLANK($F21),"","Budget") -> Budget | B21: =IF(ISBLANK($F21),"",$F$1) -> 2026 | C21: =IF(ISBLANK($L21),"",_xlfn.XLOOKUP($L21,'CENTRO CUSTO'!$A:$A,'CENTRO CUSTO'!F:F,FALSE,0)) -> Rio de Janeiro | D21: =IF(ISBLANK($L21),"",_xlfn.XLOOKUP($L21,'CENTRO CUSTO'!$A:$A,'CENTRO CUSTO'!G:G,FALSE,0)) -> BU-RJ | E21: =IF(ISBLANK($L21),"",_xlfn.XLOOKUP($L21,'CENTRO CUSTO'!$A:$A,'CENTRO CUSTO'!H:H,FALSE,0)) -> G&A | F21: SEIDOR | G21: Applications support and maintenance | H21: SAP S4 - AMS | I21: Existente | J21: Mensal | K21: Contrato em Curso | L21: BU-RJ | TI | M21: =IF(ISBLANK($L21),"",_xlfn.XLOOKUP($L21,'CENTRO CUSTO'!$A:$A,'CENTRO CUSTO'!D:D,FALSE,0)) -> Alexandre Ayabe | N21: Manutenção de Informática | P21: USD | Q21: =187158*Rateio!$E$56/12 -> 311.93 | R21: =187158*Rateio!$E$56/12 -> 311.93 | S21: =187158*Rateio!$E$56/12 -> 311.93 | T21: =187158*Rateio!$E$56/12 -> 311.93 | U21: =187158*Rateio!$E$56/12 -> 311.93 | V21: =187158*Rateio!$E$56/12 -> 311.93 | W21: =187158*Rateio!$E$56/12 -> 311.93 | X21: =187158*Rateio!$E$56/12 -> 311.93 | ... AB21: =187158*Rateio!$E$56/12 -> 311.93 | AC21: =IF(AND(ISBLANK($Q21),ISBLANK($R21),ISBLANK($S21),ISBLANK($T21),ISBLANK($U21),ISBLANK($V21),ISBLANK($W21),ISBLANK($X21),ISBLANK($Y21),ISBLANK($Z21),ISBLANK($AA21),ISBLANK($AB21)),"",SUM(Q21:AB21)) -> 3743.16 | AE21: =IF(ISBLANK(Q21),"",IF($P21="BRL",Q21,Q21*Macroindicadores!B$2)/1000) -> 1.8341484 | AF21: =IF(ISBLANK(R21),"",IF($P21="BRL",R21,R21*Macroindicadores!C$2)/1000) -> 1.8341484 | AG21: =IF(ISBLANK(S21),"",IF($P21="BRL",S21,S21*Macroindicadores!D$2)/1000) -> 1.8341484 | AH21: =IF(ISBLANK(T21),"",IF($P21="BRL",T21,T21*Macroindicadores!E$2)/1000) -> 1.8341484 | AI21: =IF(ISBLANK(U21),"",IF($P21="BRL",U21,U21*Macroindicadores!F$2)/1000) -> 1.8341484 | AJ21: =IF(ISBLANK(V21),"",IF($P21="BRL",V21,V21*Macroindicadores!G$2)/1000) -> 1.8341484 | AK21: =IF(ISBLANK(W21),"",IF($P21="BRL",W21,W21*Macroindicadores!H$2)/1000) -> 1.8341484 | AL21: =IF(ISBLANK(X21),"",IF($P21="BRL",X21,X21*Macroindicadores!I$2)/1000) -> 1.8341484 | ... AP21: =IF(ISBLANK(AB21),"",IF($P21="BRL",AB21,AB21*Macroindicadores!M$2)/1000) -> 1.8341484 | AQ21: =IF(AND(ISBLANK($Q21),ISBLANK($R21),ISBLANK($S21),ISBLANK($T21),ISBLANK($U21),ISBLANK($V21),ISBLANK($W21),ISBLANK($X21),ISBLANK($Y21),ISBLANK($Z21),ISBLANK($AA21),ISBLANK($AB21)),"",SUM(AE21:AP21)) -> 22.009781 | AS21: =IF(ISBLANK(Q21),"",IF(ISBLANK($O21),AE21,IF($J21="ANUAL",AE21*(1+Macroindicadores!B$7),IF(AND($I21="NOVO",MONTH($O21)=MONTH(AS$4)),AE21*(1+Macroindicadores!B$7),IF(AND($J21="PONTUAL",MONTH($O21)=MONTH(AS$4)),AE21*(1+Macroindicadores!B$7),IF(AND($J21="PONTUAL",MONTH($O21)<MONTH(AS$4)),MIN(AR21:$AS21),IF(AND($I21="NOVO",MONTH($O21)>MONTH(AS$4)),AE21,IF(MONTH($O21)>MONTH(AS$4),AE21,IF(MONTH($O21)=MONTH(AS$4),AE21*(1+Macroindicadores!B$7),AR21))))))))) -> 1.8341484 | AT21: =IF(ISBLANK(R21),"",IF(ISBLANK($O21),AF21,IF($J21="ANUAL",AF21*(1+Macroindicadores!C$7),IF(AND($I21="NOVO",MONTH($O21)=MONTH(AT$4)),AF21*(1+Macroindicadores!C$7),IF(AND($J21="PONTUAL",MONTH($O21)=MONTH(AT$4)),AF21*(1+Macroindicadores!C$7),IF(AND($J21="PONTUAL",MONTH($O21)<MONTH(AT$4)),MIN($AS21:AS21),IF(AND($I21="NOVO",MONTH($O21)>MONTH(AT$4)),AF21,IF(MONTH($O21)>MONTH(AT$4),AF21,IF(MONTH($O21)=MONTH(AT$4),AF21*(1+Macroindicadores!C$7),AS21))))))))) -> 1.8341484 | AU21: =IF(ISBLANK(S21),"",IF(ISBLANK($O21),AG21,IF($J21="ANUAL",AG21*(1+Macroindicadores!D$7),IF(AND($I21="NOVO",MONTH($O21)=MONTH(AU$4)),AG21*(1+Macroindicadores!D$7),IF(AND($J21="PONTUAL",MONTH($O21)=MONTH(AU$4)),AG21*(1+Macroindicadores!D$7),IF(AND($J21="PONTUAL",MONTH($O21)<MONTH(AU$4)),MIN($AS21:AT21),IF(AND($I21="NOVO",MONTH($O21)>MONTH(AU$4)),AG21,IF(MONTH($O21)>MONTH(AU$4),AG21,IF(MONTH($O21)=MONTH(AU$4),AG21*(1+Macroindicadores!D$7),AT21))))))))) -> 1.8341484 | AV21: =IF(ISBLANK(T21),"",IF(ISBLANK($O21),AH21,IF($J21="ANUAL",AH21*(1+Macroindicadores!E$7),IF(AND($I21="NOVO",MONTH($O21)=MONTH(AV$4)),AH21*(1+Macroindicadores!E$7),IF(AND($J21="PONTUAL",MONTH($O21)=MONTH(AV$4)),AH21*(1+Macroindicadores!E$7),IF(AND($J21="PONTUAL",MONTH($O21)<MONTH(AV$4)),MIN($AS21:AU21),IF(AND($I21="NOVO",MONTH($O21)>MONTH(AV$4)),AH21,IF(MONTH($O21)>MONTH(AV$4),AH21,IF(MONTH($O21)=MONTH(AV$4),AH21*(1+Macroindicadores!E$7),AU21))))))))) -> 1.8341484 | AW21: =IF(ISBLANK(U21),"",IF(ISBLANK($O21),AI21,IF($J21="ANUAL",AI21*(1+Macroindicadores!F$7),IF(AND($I21="NOVO",MONTH($O21)=MONTH(AW$4)),AI21*(1+Macroindicadores!F$7),IF(AND($J21="PONTUAL",MONTH($O21)=MONTH(AW$4)),AI21*(1+Macroindicadores!F$7),IF(AND($J21="PONTUAL",MONTH($O21)<MONTH(AW$4)),MIN($AS21:AV21),IF(AND($I21="NOVO",MONTH($O21)>MONTH(AW$4)),AI21,IF(MONTH($O21)>MONTH(AW$4),AI21,IF(MONTH($O21)=MONTH(AW$4),AI21*(1+Macroindicadores!F$7),AV21))))))))) -> 1.8341484 | AX21: =IF(ISBLANK(V21),"",IF(ISBLANK($O21),AJ21,IF($J21="ANUAL",AJ21*(1+Macroindicadores!G$7),IF(AND($I21="NOVO",MONTH($O21)=MONTH(AX$4)),AJ21*(1+Macroindicadores!G$7),IF(AND($J21="PONTUAL",MONTH($O21)=MONTH(AX$4)),AJ21*(1+Macroindicadores!G$7),IF(AND($J21="PONTUAL",MONTH($O21)<MONTH(AX$4)),MIN($AS21:AW21),IF(AND($I21="NOVO",MONTH($O21)>MONTH(AX$4)),AJ21,IF(MONTH($O21)>MONTH(AX$4),AJ21,IF(MONTH($O21)=MONTH(AX$4),AJ21*(1+Macroindicadores!G$7),AW21))))))))) -> 1.8341484 | AY21: =IF(ISBLANK(W21),"",IF(ISBLANK($O21),AK21,IF($J21="ANUAL",AK21*(1+Macroindicadores!H$7),IF(AND($I21="NOVO",MONTH($O21)=MONTH(AY$4)),AK21*(1+Macroindicadores!H$7),IF(AND($J21="PONTUAL",MONTH($O21)=MONTH(AY$4)),AK21*(1+Macroindicadores!H$7),IF(AND($J21="PONTUAL",MONTH($O21)<MONTH(AY$4)),MIN($AS21:AX21),IF(AND($I21="NOVO",MONTH($O21)>MONTH(AY$4)),AK21,IF(MONTH($O21)>MONTH(AY$4),AK21,IF(MONTH($O21)=MONTH(AY$4),AK21*(1+Macroindicadores!H$7),AX21))))))))) -> 1.8341484 | AZ21: =IF(ISBLANK(X21),"",IF(ISBLANK($O21),AL21,IF($J21="ANUAL",AL21*(1+Macroindicadores!I$7),IF(AND($I21="NOVO",MONTH($O21)=MONTH(AZ$4)),AL21*(1+Macroindicadores!I$7),IF(AND($J21="PONTUAL",MONTH($O21)=MONTH(AZ$4)),AL21*(1+Macroindicadores!I$7),IF(AND($J21="PONTUAL",MONTH($O21)<MONTH(AZ$4)),MIN($AS21:AY21),IF(AND($I21="NOVO",MONTH($O21)>MONTH(AZ$4)),AL21,IF(MONTH($O21)>MONTH(AZ$4),AL21,IF(MONTH($O21)=MONTH(AZ$4),AL21*(1+Macroindicadores!I$7),AY21))))))))) -> 1.8341484 | BA21: =IF(ISBLANK(Y21),"",IF(ISBLANK($O21),AM21,IF($J21="ANUAL",AM21*(1+Macroindicadores!J$7),IF(AND($I21="NOVO",MONTH($O21)=MONTH(BA$4)),AM21*(1+Macroindicadores!J$7),IF(AND($J21="PONTUAL",MONTH($O21)=MONTH(BA$4)),AM21*(1+Macroindicadores!J$7),IF(AND($J21="PONTUAL",MONTH($O21)<MONTH(BA$4)),MIN($AS21:AZ21),IF(AND($I21="NOVO",MONTH($O21)>MONTH(BA$4)),AM21,IF(MONTH($O21)>MONTH(BA$4),AM21,IF(MONTH($O21)=MONTH(BA$4),AM21*(1+Macroindicadores!J$7),AZ21))))))))) -> 1.8341484 | ... BD21: =IF(ISBLANK(AB21),"",IF(ISBLANK($O21),AP21,IF($J21="ANUAL",AP21*(1+Macroindicadores!M$7),IF(AND($I21="NOVO",MONTH($O21)=MONTH(BD$4)),AP21*(1+Macroindicadores!M$7),IF(AND($J21="PONTUAL",MONTH($O21)=MONTH(BD$4)),AP21*(1+Macroindicadores!M$7),IF(AND($J21="PONTUAL",MONTH($O21)<MONTH(BD$4)),MIN($AS21:BC21),IF(AND($I21="NOVO",MONTH($O21)>MONTH(BD$4)),AP21,IF(MONTH($O21)>MONTH(BD$4),AP21,IF(MONTH($O21)=MONTH(BD$4),AP21*(1+Macroindicadores!M$7),BC21))))))))) -> 1.8341484 | BE21: =IF(AND(ISBLANK($Q21),ISBLANK($R21),ISBLANK($S21),ISBLANK($T21),ISBLANK($U21),ISBLANK($V21),ISBLANK($W21),ISBLANK($X21),ISBLANK($Y21),ISBLANK($Z21),ISBLANK($AA21),ISBLANK($AB21)),"",SUM(AS21:BD21)) -> 22.009781 | BG21: =IF(ISBLANK(Q21),"",AS21/Macroindicadores!B$2) -> 0.31193 | BH21: =IF(ISBLANK(R21),"",AT21/Macroindicadores!C$2) -> 0.31193 | BI21: =IF(ISBLANK(S21),"",AU21/Macroindicadores!D$2) -> 0.31193 | BJ21: =IF(ISBLANK(T21),"",AV21/Macroindicadores!E$2) -> 0.31193 | BK21: =IF(ISBLANK(U21),"",AW21/Macroindicadores!F$2) -> 0.31193 | BL21: =IF(ISBLANK(V21),"",AX21/Macroindicadores!G$2) -> 0.31193 | BM21: =IF(ISBLANK(W21),"",AY21/Macroindicadores!H$2) -> 0.31193 | BN21: =IF(ISBLANK(X21),"",AZ21/Macroindicadores!I$2) -> 0.31193 | ... BR21: =IF(ISBLANK(AB21),"",BD21/Macroindicadores!M$2) -> 0.31193 | BS21: =IF(AND(ISBLANK($Q21),ISBLANK($R21),ISBLANK($S21),ISBLANK($T21),ISBLANK($U21),ISBLANK($V21),ISBLANK($W21),ISBLANK($X21),ISBLANK($Y21),ISBLANK($Z21),ISBLANK($AA21),ISBLANK($AB21)),"",SUM(BG21:BR21)) -> 3.74316 | BT21: =IF(ISBLANK($L21),"",_xlfn.XLOOKUP($L21,'CENTRO CUSTO'!$A:$A,'CENTRO CUSTO'!$E:$E,FALSE,0)) -> G&A BU
A22: =IF(ISBLANK($F22),"","Budget") -> Budget | B22: =IF(ISBLANK($F22),"",$F$1) -> 2026 | C22: =IF(ISBLANK($L22),"",_xlfn.XLOOKUP($L22,'CENTRO CUSTO'!$A:$A,'CENTRO CUSTO'!F:F,FALSE,0)) -> Cone Sul | D22: =IF(ISBLANK($L22),"",_xlfn.XLOOKUP($L22,'CENTRO CUSTO'!$A:$A,'CENTRO CUSTO'!G:G,FALSE,0)) -> Plataforma | E22: =IF(ISBLANK($L22),"",_xlfn.XLOOKUP($L22,'CENTRO CUSTO'!$A:$A,'CENTRO CUSTO'!H:H,FALSE,0)) -> G&A | F22: SEIDOR | G22: Applications support and maintenance | H22: SAP S4 - AMS | I22: Novo | J22: Mensal | K22: Contrato em Curso | L22: PL | TI | M22: =IF(ISBLANK($L22),"",_xlfn.XLOOKUP($L22,'CENTRO CUSTO'!$A:$A,'CENTRO CUSTO'!D:D,FALSE,0)) -> Alexandre Ayabe | N22: Manutenção de Informática | P22: USD | Q22: =187158*Rateio!$E$58/12 -> 2495.44 | R22: =187158*Rateio!$E$58/12 -> 2495.44 | S22: =187158*Rateio!$E$58/12 -> 2495.44 | T22: =187158*Rateio!$E$58/12 -> 2495.44 | U22: =187158*Rateio!$E$58/12 -> 2495.44 | V22: =187158*Rateio!$E$58/12 -> 2495.44 | W22: =187158*Rateio!$E$58/12 -> 2495.44 | X22: =187158*Rateio!$E$58/12 -> 2495.44 | ... AB22: =187158*Rateio!$E$58/12 -> 2495.44 | AC22: =IF(AND(ISBLANK($Q22),ISBLANK($R22),ISBLANK($S22),ISBLANK($T22),ISBLANK($U22),ISBLANK($V22),ISBLANK($W22),ISBLANK($X22),ISBLANK($Y22),ISBLANK($Z22),ISBLANK($AA22),ISBLANK($AB22)),"",SUM(Q22:AB22)) -> 29945.28 | AE22: =IF(ISBLANK(Q22),"",IF($P22="BRL",Q22,Q22*Macroindicadores!B$2)/1000) -> 14.673187 | AF22: =IF(ISBLANK(R22),"",IF($P22="BRL",R22,R22*Macroindicadores!C$2)/1000) -> 14.673187 | AG22: =IF(ISBLANK(S22),"",IF($P22="BRL",S22,S22*Macroindicadores!D$2)/1000) -> 14.673187 | AH22: =IF(ISBLANK(T22),"",IF($P22="BRL",T22,T22*Macroindicadores!E$2)/1000) -> 14.673187 | AI22: =IF(ISBLANK(U22),"",IF($P22="BRL",U22,U22*Macroindicadores!F$2)/1000) -> 14.673187 | AJ22: =IF(ISBLANK(V22),"",IF($P22="BRL",V22,V22*Macroindicadores!G$2)/1000) -> 14.673187 | AK22: =IF(ISBLANK(W22),"",IF($P22="BRL",W22,W22*Macroindicadores!H$2)/1000) -> 14.673187 | AL22: =IF(ISBLANK(X22),"",IF($P22="BRL",X22,X22*Macroindicadores!I$2)/1000) -> 14.673187 | ... AP22: =IF(ISBLANK(AB22),"",IF($P22="BRL",AB22,AB22*Macroindicadores!M$2)/1000) -> 14.673187 | AQ22: =IF(AND(ISBLANK($Q22),ISBLANK($R22),ISBLANK($S22),ISBLANK($T22),ISBLANK($U22),ISBLANK($V22),ISBLANK($W22),ISBLANK($X22),ISBLANK($Y22),ISBLANK($Z22),ISBLANK($AA22),ISBLANK($AB22)),"",SUM(AE22:AP22)) -> 176.07825 | AS22: =IF(ISBLANK(Q22),"",IF(ISBLANK($O22),AE22,IF($J22="ANUAL",AE22*(1+Macroindicadores!B$7),IF(AND($I22="NOVO",MONTH($O22)=MONTH(AS$4)),AE22*(1+Macroindicadores!B$7),IF(AND($J22="PONTUAL",MONTH($O22)=MONTH(AS$4)),AE22*(1+Macroindicadores!B$7),IF(AND($J22="PONTUAL",MONTH($O22)<MONTH(AS$4)),MIN(AR22:$AS22),IF(AND($I22="NOVO",MONTH($O22)>MONTH(AS$4)),AE22,IF(MONTH($O22)>MONTH(AS$4),AE22,IF(MONTH($O22)=MONTH(AS$4),AE22*(1+Macroindicadores!B$7),AR22))))))))) -> 14.673187 | AT22: =IF(ISBLANK(R22),"",IF(ISBLANK($O22),AF22,IF($J22="ANUAL",AF22*(1+Macroindicadores!C$7),IF(AND($I22="NOVO",MONTH($O22)=MONTH(AT$4)),AF22*(1+Macroindicadores!C$7),IF(AND($J22="PONTUAL",MONTH($O22)=MONTH(AT$4)),AF22*(1+Macroindicadores!C$7),IF(AND($J22="PONTUAL",MONTH($O22)<MONTH(AT$4)),MIN($AS22:AS22),IF(AND($I22="NOVO",MONTH($O22)>MONTH(AT$4)),AF22,IF(MONTH($O22)>MONTH(AT$4),AF22,IF(MONTH($O22)=MONTH(AT$4),AF22*(1+Macroindicadores!C$7),AS22))))))))) -> 14.673187 | AU22: =IF(ISBLANK(S22),"",IF(ISBLANK($O22),AG22,IF($J22="ANUAL",AG22*(1+Macroindicadores!D$7),IF(AND($I22="NOVO",MONTH($O22)=MONTH(AU$4)),AG22*(1+Macroindicadores!D$7),IF(AND($J22="PONTUAL",MONTH($O22)=MONTH(AU$4)),AG22*(1+Macroindicadores!D$7),IF(AND($J22="PONTUAL",MONTH($O22)<MONTH(AU$4)),MIN($AS22:AT22),IF(AND($I22="NOVO",MONTH($O22)>MONTH(AU$4)),AG22,IF(MONTH($O22)>MONTH(AU$4),AG22,IF(MONTH($O22)=MONTH(AU$4),AG22*(1+Macroindicadores!D$7),AT22))))))))) -> 14.673187 | AV22: =IF(ISBLANK(T22),"",IF(ISBLANK($O22),AH22,IF($J22="ANUAL",AH22*(1+Macroindicadores!E$7),IF(AND($I22="NOVO",MONTH($O22)=MONTH(AV$4)),AH22*(1+Macroindicadores!E$7),IF(AND($J22="PONTUAL",MONTH($O22)=MONTH(AV$4)),AH22*(1+Macroindicadores!E$7),IF(AND($J22="PONTUAL",MONTH($O22)<MONTH(AV$4)),MIN($AS22:AU22),IF(AND($I22="NOVO",MONTH($O22)>MONTH(AV$4)),AH22,IF(MONTH($O22)>MONTH(AV$4),AH22,IF(MONTH($O22)=MONTH(AV$4),AH22*(1+Macroindicadores!E$7),AU22))))))))) -> 14.673187 | AW22: =IF(ISBLANK(U22),"",IF(ISBLANK($O22),AI22,IF($J22="ANUAL",AI22*(1+Macroindicadores!F$7),IF(AND($I22="NOVO",MONTH($O22)=MONTH(AW$4)),AI22*(1+Macroindicadores!F$7),IF(AND($J22="PONTUAL",MONTH($O22)=MONTH(AW$4)),AI22*(1+Macroindicadores!F$7),IF(AND($J22="PONTUAL",MONTH($O22)<MONTH(AW$4)),MIN($AS22:AV22),IF(AND($I22="NOVO",MONTH($O22)>MONTH(AW$4)),AI22,IF(MONTH($O22)>MONTH(AW$4),AI22,IF(MONTH($O22)=MONTH(AW$4),AI22*(1+Macroindicadores!F$7),AV22))))))))) -> 14.673187 | AX22: =IF(ISBLANK(V22),"",IF(ISBLANK($O22),AJ22,IF($J22="ANUAL",AJ22*(1+Macroindicadores!G$7),IF(AND($I22="NOVO",MONTH($O22)=MONTH(AX$4)),AJ22*(1+Macroindicadores!G$7),IF(AND($J22="PONTUAL",MONTH($O22)=MONTH(AX$4)),AJ22*(1+Macroindicadores!G$7),IF(AND($J22="PONTUAL",MONTH($O22)<MONTH(AX$4)),MIN($AS22:AW22),IF(AND($I22="NOVO",MONTH($O22)>MONTH(AX$4)),AJ22,IF(MONTH($O22)>MONTH(AX$4),AJ22,IF(MONTH($O22)=MONTH(AX$4),AJ22*(1+Macroindicadores!G$7),AW22))))))))) -> 14.673187 | AY22: =IF(ISBLANK(W22),"",IF(ISBLANK($O22),AK22,IF($J22="ANUAL",AK22*(1+Macroindicadores!H$7),IF(AND($I22="NOVO",MONTH($O22)=MONTH(AY$4)),AK22*(1+Macroindicadores!H$7),IF(AND($J22="PONTUAL",MONTH($O22)=MONTH(AY$4)),AK22*(1+Macroindicadores!H$7),IF(AND($J22="PONTUAL",MONTH($O22)<MONTH(AY$4)),MIN($AS22:AX22),IF(AND($I22="NOVO",MONTH($O22)>MONTH(AY$4)),AK22,IF(MONTH($O22)>MONTH(AY$4),AK22,IF(MONTH($O22)=MONTH(AY$4),AK22*(1+Macroindicadores!H$7),AX22))))))))) -> 14.673187 | AZ22: =IF(ISBLANK(X22),"",IF(ISBLANK($O22),AL22,IF($J22="ANUAL",AL22*(1+Macroindicadores!I$7),IF(AND($I22="NOVO",MONTH($O22)=MONTH(AZ$4)),AL22*(1+Macroindicadores!I$7),IF(AND($J22="PONTUAL",MONTH($O22)=MONTH(AZ$4)),AL22*(1+Macroindicadores!I$7),IF(AND($J22="PONTUAL",MONTH($O22)<MONTH(AZ$4)),MIN($AS22:AY22),IF(AND($I22="NOVO",MONTH($O22)>MONTH(AZ$4)),AL22,IF(MONTH($O22)>MONTH(AZ$4),AL22,IF(MONTH($O22)=MONTH(AZ$4),AL22*(1+Macroindicadores!I$7),AY22))))))))) -> 14.673187 | BA22: =IF(ISBLANK(Y22),"",IF(ISBLANK($O22),AM22,IF($J22="ANUAL",AM22*(1+Macroindicadores!J$7),IF(AND($I22="NOVO",MONTH($O22)=MONTH(BA$4)),AM22*(1+Macroindicadores!J$7),IF(AND($J22="PONTUAL",MONTH($O22)=MONTH(BA$4)),AM22*(1+Macroindicadores!J$7),IF(AND($J22="PONTUAL",MONTH($O22)<MONTH(BA$4)),MIN($AS22:AZ22),IF(AND($I22="NOVO",MONTH($O22)>MONTH(BA$4)),AM22,IF(MONTH($O22)>MONTH(BA$4),AM22,IF(MONTH($O22)=MONTH(BA$4),AM22*(1+Macroindicadores!J$7),AZ22))))))))) -> 14.673187 | ... BD22: =IF(ISBLANK(AB22),"",IF(ISBLANK($O22),AP22,IF($J22="ANUAL",AP22*(1+Macroindicadores!M$7),IF(AND($I22="NOVO",MONTH($O22)=MONTH(BD$4)),AP22*(1+Macroindicadores!M$7),IF(AND($J22="PONTUAL",MONTH($O22)=MONTH(BD$4)),AP22*(1+Macroindicadores!M$7),IF(AND($J22="PONTUAL",MONTH($O22)<MONTH(BD$4)),MIN($AS22:BC22),IF(AND($I22="NOVO",MONTH($O22)>MONTH(BD$4)),AP22,IF(MONTH($O22)>MONTH(BD$4),AP22,IF(MONTH($O22)=MONTH(BD$4),AP22*(1+Macroindicadores!M$7),BC22))))))))) -> 14.673187 | BE22: =IF(AND(ISBLANK($Q22),ISBLANK($R22),ISBLANK($S22),ISBLANK($T22),ISBLANK($U22),ISBLANK($V22),ISBLANK($W22),ISBLANK($X22),ISBLANK($Y22),ISBLANK($Z22),ISBLANK($AA22),ISBLANK($AB22)),"",SUM(AS22:BD22)) -> 176.07825 | BG22: =IF(ISBLANK(Q22),"",AS22/Macroindicadores!B$2) -> 2.49544 | BH22: =IF(ISBLANK(R22),"",AT22/Macroindicadores!C$2) -> 2.49544 | BI22: =IF(ISBLANK(S22),"",AU22/Macroindicadores!D$2) -> 2.49544 | BJ22: =IF(ISBLANK(T22),"",AV22/Macroindicadores!E$2) -> 2.49544 | BK22: =IF(ISBLANK(U22),"",AW22/Macroindicadores!F$2) -> 2.49544 | BL22: =IF(ISBLANK(V22),"",AX22/Macroindicadores!G$2) -> 2.49544 | BM22: =IF(ISBLANK(W22),"",AY22/Macroindicadores!H$2) -> 2.49544 | BN22: =IF(ISBLANK(X22),"",AZ22/Macroindicadores!I$2) -> 2.49544 | ... BR22: =IF(ISBLANK(AB22),"",BD22/Macroindicadores!M$2) -> 2.49544 | BS22: =IF(AND(ISBLANK($Q22),ISBLANK($R22),ISBLANK($S22),ISBLANK($T22),ISBLANK($U22),ISBLANK($V22),ISBLANK($W22),ISBLANK($X22),ISBLANK($Y22),ISBLANK($Z22),ISBLANK($AA22),ISBLANK($AB22)),"",SUM(BG22:BR22)) -> 29.94528 | BT22: =IF(ISBLANK($L22),"",_xlfn.XLOOKUP($L22,'CENTRO CUSTO'!$A:$A,'CENTRO CUSTO'!$E:$E,FALSE,0)) -> G&A PL
A23: =IF(ISBLANK($F23),"","Budget") -> Budget | B23: =IF(ISBLANK($F23),"",$F$1) -> 2026 | C23: =IF(ISBLANK($L23),"",_xlfn.XLOOKUP($L23,'CENTRO CUSTO'!$A:$A,'CENTRO CUSTO'!F:F,FALSE,0)) -> LATAM | D23: =IF(ISBLANK($L23),"",_xlfn.XLOOKUP($L23,'CENTRO CUSTO'!$A:$A,'CENTRO CUSTO'!G:G,FALSE,0)) -> Corporativo | E23: =IF(ISBLANK($L23),"",_xlfn.XLOOKUP($L23,'CENTRO CUSTO'!$A:$A,'CENTRO CUSTO'!H:H,FALSE,0)) -> G&A | F23: SEIDOR | G23: Applications support and maintenance | H23: SAP S4 - AMS | I23: Novo | J23: Mensal | K23: Contrato em Curso | L23: CP | TI | M23: =IF(ISBLANK($L23),"",_xlfn.XLOOKUP($L23,'CENTRO CUSTO'!$A:$A,'CENTRO CUSTO'!D:D,FALSE,0)) -> Jimmy Espinosa | N23: Manutenção de Informática | P23: USD | Q23: =187158*Rateio!$E$59/12 -> 779.825 | R23: =187158*Rateio!$E$59/12 -> 779.825 | S23: =187158*Rateio!$E$59/12 -> 779.825 | T23: =187158*Rateio!$E$59/12 -> 779.825 | U23: =187158*Rateio!$E$59/12 -> 779.825 | V23: =187158*Rateio!$E$59/12 -> 779.825 | W23: =187158*Rateio!$E$59/12 -> 779.825 | X23: =187158*Rateio!$E$59/12 -> 779.825 | ... AB23: =187158*Rateio!$E$59/12 -> 779.825 | AC23: =IF(AND(ISBLANK($Q23),ISBLANK($R23),ISBLANK($S23),ISBLANK($T23),ISBLANK($U23),ISBLANK($V23),ISBLANK($W23),ISBLANK($X23),ISBLANK($Y23),ISBLANK($Z23),ISBLANK($AA23),ISBLANK($AB23)),"",SUM(Q23:AB23)) -> 9357.9 | AE23: =IF(ISBLANK(Q23),"",IF($P23="BRL",Q23,Q23*Macroindicadores!B$2)/1000) -> 4.585371 | AF23: =IF(ISBLANK(R23),"",IF($P23="BRL",R23,R23*Macroindicadores!C$2)/1000) -> 4.585371 | AG23: =IF(ISBLANK(S23),"",IF($P23="BRL",S23,S23*Macroindicadores!D$2)/1000) -> 4.585371 | AH23: =IF(ISBLANK(T23),"",IF($P23="BRL",T23,T23*Macroindicadores!E$2)/1000) -> 4.585371 | AI23: =IF(ISBLANK(U23),"",IF($P23="BRL",U23,U23*Macroindicadores!F$2)/1000) -> 4.585371 | AJ23: =IF(ISBLANK(V23),"",IF($P23="BRL",V23,V23*Macroindicadores!G$2)/1000) -> 4.585371 | AK23: =IF(ISBLANK(W23),"",IF($P23="BRL",W23,W23*Macroindicadores!H$2)/1000) -> 4.585371 | AL23: =IF(ISBLANK(X23),"",IF($P23="BRL",X23,X23*Macroindicadores!I$2)/1000) -> 4.585371 | ... AP23: =IF(ISBLANK(AB23),"",IF($P23="BRL",AB23,AB23*Macroindicadores!M$2)/1000) -> 4.585371 | AQ23: =IF(AND(ISBLANK($Q23),ISBLANK($R23),ISBLANK($S23),ISBLANK($T23),ISBLANK($U23),ISBLANK($V23),ISBLANK($W23),ISBLANK($X23),ISBLANK($Y23),ISBLANK($Z23),ISBLANK($AA23),ISBLANK($AB23)),"",SUM(AE23:AP23)) -> 55.024452 | AS23: =IF(ISBLANK(Q23),"",IF(ISBLANK($O23),AE23,IF($J23="ANUAL",AE23*(1+Macroindicadores!B$7),IF(AND($I23="NOVO",MONTH($O23)=MONTH(AS$4)),AE23*(1+Macroindicadores!B$7),IF(AND($J23="PONTUAL",MONTH($O23)=MONTH(AS$4)),AE23*(1+Macroindicadores!B$7),IF(AND($J23="PONTUAL",MONTH($O23)<MONTH(AS$4)),MIN(AR23:$AS23),IF(AND($I23="NOVO",MONTH($O23)>MONTH(AS$4)),AE23,IF(MONTH($O23)>MONTH(AS$4),AE23,IF(MONTH($O23)=MONTH(AS$4),AE23*(1+Macroindicadores!B$7),AR23))))))))) -> 4.585371 | AT23: =IF(ISBLANK(R23),"",IF(ISBLANK($O23),AF23,IF($J23="ANUAL",AF23*(1+Macroindicadores!C$7),IF(AND($I23="NOVO",MONTH($O23)=MONTH(AT$4)),AF23*(1+Macroindicadores!C$7),IF(AND($J23="PONTUAL",MONTH($O23)=MONTH(AT$4)),AF23*(1+Macroindicadores!C$7),IF(AND($J23="PONTUAL",MONTH($O23)<MONTH(AT$4)),MIN($AS23:AS23),IF(AND($I23="NOVO",MONTH($O23)>MONTH(AT$4)),AF23,IF(MONTH($O23)>MONTH(AT$4),AF23,IF(MONTH($O23)=MONTH(AT$4),AF23*(1+Macroindicadores!C$7),AS23))))))))) -> 4.585371 | AU23: =IF(ISBLANK(S23),"",IF(ISBLANK($O23),AG23,IF($J23="ANUAL",AG23*(1+Macroindicadores!D$7),IF(AND($I23="NOVO",MONTH($O23)=MONTH(AU$4)),AG23*(1+Macroindicadores!D$7),IF(AND($J23="PONTUAL",MONTH($O23)=MONTH(AU$4)),AG23*(1+Macroindicadores!D$7),IF(AND($J23="PONTUAL",MONTH($O23)<MONTH(AU$4)),MIN($AS23:AT23),IF(AND($I23="NOVO",MONTH($O23)>MONTH(AU$4)),AG23,IF(MONTH($O23)>MONTH(AU$4),AG23,IF(MONTH($O23)=MONTH(AU$4),AG23*(1+Macroindicadores!D$7),AT23))))))))) -> 4.585371 | AV23: =IF(ISBLANK(T23),"",IF(ISBLANK($O23),AH23,IF($J23="ANUAL",AH23*(1+Macroindicadores!E$7),IF(AND($I23="NOVO",MONTH($O23)=MONTH(AV$4)),AH23*(1+Macroindicadores!E$7),IF(AND($J23="PONTUAL",MONTH($O23)=MONTH(AV$4)),AH23*(1+Macroindicadores!E$7),IF(AND($J23="PONTUAL",MONTH($O23)<MONTH(AV$4)),MIN($AS23:AU23),IF(AND($I23="NOVO",MONTH($O23)>MONTH(AV$4)),AH23,IF(MONTH($O23)>MONTH(AV$4),AH23,IF(MONTH($O23)=MONTH(AV$4),AH23*(1+Macroindicadores!E$7),AU23))))))))) -> 4.585371 | AW23: =IF(ISBLANK(U23),"",IF(ISBLANK($O23),AI23,IF($J23="ANUAL",AI23*(1+Macroindicadores!F$7),IF(AND($I23="NOVO",MONTH($O23)=MONTH(AW$4)),AI23*(1+Macroindicadores!F$7),IF(AND($J23="PONTUAL",MONTH($O23)=MONTH(AW$4)),AI23*(1+Macroindicadores!F$7),IF(AND($J23="PONTUAL",MONTH($O23)<MONTH(AW$4)),MIN($AS23:AV23),IF(AND($I23="NOVO",MONTH($O23)>MONTH(AW$4)),AI23,IF(MONTH($O23)>MONTH(AW$4),AI23,IF(MONTH($O23)=MONTH(AW$4),AI23*(1+Macroindicadores!F$7),AV23))))))))) -> 4.585371 | AX23: =IF(ISBLANK(V23),"",IF(ISBLANK($O23),AJ23,IF($J23="ANUAL",AJ23*(1+Macroindicadores!G$7),IF(AND($I23="NOVO",MONTH($O23)=MONTH(AX$4)),AJ23*(1+Macroindicadores!G$7),IF(AND($J23="PONTUAL",MONTH($O23)=MONTH(AX$4)),AJ23*(1+Macroindicadores!G$7),IF(AND($J23="PONTUAL",MONTH($O23)<MONTH(AX$4)),MIN($AS23:AW23),IF(AND($I23="NOVO",MONTH($O23)>MONTH(AX$4)),AJ23,IF(MONTH($O23)>MONTH(AX$4),AJ23,IF(MONTH($O23)=MONTH(AX$4),AJ23*(1+Macroindicadores!G$7),AW23))))))))) -> 4.585371 | AY23: =IF(ISBLANK(W23),"",IF(ISBLANK($O23),AK23,IF($J23="ANUAL",AK23*(1+Macroindicadores!H$7),IF(AND($I23="NOVO",MONTH($O23)=MONTH(AY$4)),AK23*(1+Macroindicadores!H$7),IF(AND($J23="PONTUAL",MONTH($O23)=MONTH(AY$4)),AK23*(1+Macroindicadores!H$7),IF(AND($J23="PONTUAL",MONTH($O23)<MONTH(AY$4)),MIN($AS23:AX23),IF(AND($I23="NOVO",MONTH($O23)>MONTH(AY$4)),AK23,IF(MONTH($O23)>MONTH(AY$4),AK23,IF(MONTH($O23)=MONTH(AY$4),AK23*(1+Macroindicadores!H$7),AX23))))))))) -> 4.585371 | AZ23: =IF(ISBLANK(X23),"",IF(ISBLANK($O23),AL23,IF($J23="ANUAL",AL23*(1+Macroindicadores!I$7),IF(AND($I23="NOVO",MONTH($O23)=MONTH(AZ$4)),AL23*(1+Macroindicadores!I$7),IF(AND($J23="PONTUAL",MONTH($O23)=MONTH(AZ$4)),AL23*(1+Macroindicadores!I$7),IF(AND($J23="PONTUAL",MONTH($O23)<MONTH(AZ$4)),MIN($AS23:AY23),IF(AND($I23="NOVO",MONTH($O23)>MONTH(AZ$4)),AL23,IF(MONTH($O23)>MONTH(AZ$4),AL23,IF(MONTH($O23)=MONTH(AZ$4),AL23*(1+Macroindicadores!I$7),AY23))))))))) -> 4.585371 | BA23: =IF(ISBLANK(Y23),"",IF(ISBLANK($O23),AM23,IF($J23="ANUAL",AM23*(1+Macroindicadores!J$7),IF(AND($I23="NOVO",MONTH($O23)=MONTH(BA$4)),AM23*(1+Macroindicadores!J$7),IF(AND($J23="PONTUAL",MONTH($O23)=MONTH(BA$4)),AM23*(1+Macroindicadores!J$7),IF(AND($J23="PONTUAL",MONTH($O23)<MONTH(BA$4)),MIN($AS23:AZ23),IF(AND($I23="NOVO",MONTH($O23)>MONTH(BA$4)),AM23,IF(MONTH($O23)>MONTH(BA$4),AM23,IF(MONTH($O23)=MONTH(BA$4),AM23*(1+Macroindicadores!J$7),AZ23))))))))) -> 4.585371 | ... BD23: =IF(ISBLANK(AB23),"",IF(ISBLANK($O23),AP23,IF($J23="ANUAL",AP23*(1+Macroindicadores!M$7),IF(AND($I23="NOVO",MONTH($O23)=MONTH(BD$4)),AP23*(1+Macroindicadores!M$7),IF(AND($J23="PONTUAL",MONTH($O23)=MONTH(BD$4)),AP23*(1+Macroindicadores!M$7),IF(AND($J23="PONTUAL",MONTH($O23)<MONTH(BD$4)),MIN($AS23:BC23),IF(AND($I23="NOVO",MONTH($O23)>MONTH(BD$4)),AP23,IF(MONTH($O23)>MONTH(BD$4),AP23,IF(MONTH($O23)=MONTH(BD$4),AP23*(1+Macroindicadores!M$7),BC23))))))))) -> 4.585371 | BE23: =IF(AND(ISBLANK($Q23),ISBLANK($R23),ISBLANK($S23),ISBLANK($T23),ISBLANK($U23),ISBLANK($V23),ISBLANK($W23),ISBLANK($X23),ISBLANK($Y23),ISBLANK($Z23),ISBLANK($AA23),ISBLANK($AB23)),"",SUM(AS23:BD23)) -> 55.024452 | BG23: =IF(ISBLANK(Q23),"",AS23/Macroindicadores!B$2) -> 0.779825 | BH23: =IF(ISBLANK(R23),"",AT23/Macroindicadores!C$2) -> 0.779825 | BI23: =IF(ISBLANK(S23),"",AU23/Macroindicadores!D$2) -> 0.779825 | BJ23: =IF(ISBLANK(T23),"",AV23/Macroindicadores!E$2) -> 0.779825 | BK23: =IF(ISBLANK(U23),"",AW23/Macroindicadores!F$2) -> 0.779825 | BL23: =IF(ISBLANK(V23),"",AX23/Macroindicadores!G$2) -> 0.779825 | BM23: =IF(ISBLANK(W23),"",AY23/Macroindicadores!H$2) -> 0.779825 | BN23: =IF(ISBLANK(X23),"",AZ23/Macroindicadores!I$2) -> 0.779825 | ... BR23: =IF(ISBLANK(AB23),"",BD23/Macroindicadores!M$2) -> 0.779825 | BS23: =IF(AND(ISBLANK($Q23),ISBLANK($R23),ISBLANK($S23),ISBLANK($T23),ISBLANK($U23),ISBLANK($V23),ISBLANK($W23),ISBLANK($X23),ISBLANK($Y23),ISBLANK($Z23),ISBLANK($AA23),ISBLANK($AB23)),"",SUM(BG23:BR23)) -> 9.3579 | BT23: =IF(ISBLANK($L23),"",_xlfn.XLOOKUP($L23,'CENTRO CUSTO'!$A:$A,'CENTRO CUSTO'!$E:$E,FALSE,0)) -> G&A CP
A24: =IF(ISBLANK($F24),"","Budget") -> Budget | B24: =IF(ISBLANK($F24),"",$F$1) -> 2026 | C24: =IF(ISBLANK($L24),"",_xlfn.XLOOKUP($L24,'CENTRO CUSTO'!$A:$A,'CENTRO CUSTO'!F:F,FALSE,0)) -> Martini Meat | D24: =IF(ISBLANK($L24),"",_xlfn.XLOOKUP($L24,'CENTRO CUSTO'!$A:$A,'CENTRO CUSTO'!G:G,FALSE,0)) -> BU-MMAZ | E24: =IF(ISBLANK($L24),"",_xlfn.XLOOKUP($L24,'CENTRO CUSTO'!$A:$A,'CENTRO CUSTO'!H:H,FALSE,0)) -> G&A | F24: SEIDOR | G24: Applications support and maintenance | H24: SAP S4 - VPN | I24: Novo | J24: Mensal | K24: Contrato em Curso | L24: BU-MMAZ | TI | M24: =IF(ISBLANK($L24),"",_xlfn.XLOOKUP($L24,'CENTRO CUSTO'!$A:$A,'CENTRO CUSTO'!D:D,FALSE,0)) -> Alexandre Ayabe | N24: Manutenção de Informática | P24: USD | Q24: =100*4 -> 400 | R24: =100*4 -> 400 | S24: =100*4 -> 400 | T24: =100*4 -> 400 | U24: =100*4 -> 400 | V24: =100*4 -> 400 | W24: =100*4 -> 400 | X24: =100*4 -> 400 | ... AB24: =100*4 -> 400 | AC24: =IF(AND(ISBLANK($Q24),ISBLANK($R24),ISBLANK($S24),ISBLANK($T24),ISBLANK($U24),ISBLANK($V24),ISBLANK($W24),ISBLANK($X24),ISBLANK($Y24),ISBLANK($Z24),ISBLANK($AA24),ISBLANK($AB24)),"",SUM(Q24:AB24)) -> 4800 | AE24: =IF(ISBLANK(Q24),"",IF($P24="BRL",Q24,Q24*Macroindicadores!B$2)/1000) -> 2.352 | AF24: =IF(ISBLANK(R24),"",IF($P24="BRL",R24,R24*Macroindicadores!C$2)/1000) -> 2.352 | AG24: =IF(ISBLANK(S24),"",IF($P24="BRL",S24,S24*Macroindicadores!D$2)/1000) -> 2.352 | AH24: =IF(ISBLANK(T24),"",IF($P24="BRL",T24,T24*Macroindicadores!E$2)/1000) -> 2.352 | AI24: =IF(ISBLANK(U24),"",IF($P24="BRL",U24,U24*Macroindicadores!F$2)/1000) -> 2.352 | AJ24: =IF(ISBLANK(V24),"",IF($P24="BRL",V24,V24*Macroindicadores!G$2)/1000) -> 2.352 | AK24: =IF(ISBLANK(W24),"",IF($P24="BRL",W24,W24*Macroindicadores!H$2)/1000) -> 2.352 | AL24: =IF(ISBLANK(X24),"",IF($P24="BRL",X24,X24*Macroindicadores!I$2)/1000) -> 2.352 | ... AP24: =IF(ISBLANK(AB24),"",IF($P24="BRL",AB24,AB24*Macroindicadores!M$2)/1000) -> 2.352 | AQ24: =IF(AND(ISBLANK($Q24),ISBLANK($R24),ISBLANK($S24),ISBLANK($T24),ISBLANK($U24),ISBLANK($V24),ISBLANK($W24),ISBLANK($X24),ISBLANK($Y24),ISBLANK($Z24),ISBLANK($AA24),ISBLANK($AB24)),"",SUM(AE24:AP24)) -> 28.224 | AS24: =IF(ISBLANK(Q24),"",IF(ISBLANK($O24),AE24,IF($J24="ANUAL",AE24*(1+Macroindicadores!B$7),IF(AND($I24="NOVO",MONTH($O24)=MONTH(AS$4)),AE24*(1+Macroindicadores!B$7),IF(AND($J24="PONTUAL",MONTH($O24)=MONTH(AS$4)),AE24*(1+Macroindicadores!B$7),IF(AND($J24="PONTUAL",MONTH($O24)<MONTH(AS$4)),MIN(AR24:$AS24),IF(AND($I24="NOVO",MONTH($O24)>MONTH(AS$4)),AE24,IF(MONTH($O24)>MONTH(AS$4),AE24,IF(MONTH($O24)=MONTH(AS$4),AE24*(1+Macroindicadores!B$7),AR24))))))))) -> 2.352 | AT24: =IF(ISBLANK(R24),"",IF(ISBLANK($O24),AF24,IF($J24="ANUAL",AF24*(1+Macroindicadores!C$7),IF(AND($I24="NOVO",MONTH($O24)=MONTH(AT$4)),AF24*(1+Macroindicadores!C$7),IF(AND($J24="PONTUAL",MONTH($O24)=MONTH(AT$4)),AF24*(1+Macroindicadores!C$7),IF(AND($J24="PONTUAL",MONTH($O24)<MONTH(AT$4)),MIN($AS24:AS24),IF(AND($I24="NOVO",MONTH($O24)>MONTH(AT$4)),AF24,IF(MONTH($O24)>MONTH(AT$4),AF24,IF(MONTH($O24)=MONTH(AT$4),AF24*(1+Macroindicadores!C$7),AS24))))))))) -> 2.352 | AU24: =IF(ISBLANK(S24),"",IF(ISBLANK($O24),AG24,IF($J24="ANUAL",AG24*(1+Macroindicadores!D$7),IF(AND($I24="NOVO",MONTH($O24)=MONTH(AU$4)),AG24*(1+Macroindicadores!D$7),IF(AND($J24="PONTUAL",MONTH($O24)=MONTH(AU$4)),AG24*(1+Macroindicadores!D$7),IF(AND($J24="PONTUAL",MONTH($O24)<MONTH(AU$4)),MIN($AS24:AT24),IF(AND($I24="NOVO",MONTH($O24)>MONTH(AU$4)),AG24,IF(MONTH($O24)>MONTH(AU$4),AG24,IF(MONTH($O24)=MONTH(AU$4),AG24*(1+Macroindicadores!D$7),AT24))))))))) -> 2.352 | AV24: =IF(ISBLANK(T24),"",IF(ISBLANK($O24),AH24,IF($J24="ANUAL",AH24*(1+Macroindicadores!E$7),IF(AND($I24="NOVO",MONTH($O24)=MONTH(AV$4)),AH24*(1+Macroindicadores!E$7),IF(AND($J24="PONTUAL",MONTH($O24)=MONTH(AV$4)),AH24*(1+Macroindicadores!E$7),IF(AND($J24="PONTUAL",MONTH($O24)<MONTH(AV$4)),MIN($AS24:AU24),IF(AND($I24="NOVO",MONTH($O24)>MONTH(AV$4)),AH24,IF(MONTH($O24)>MONTH(AV$4),AH24,IF(MONTH($O24)=MONTH(AV$4),AH24*(1+Macroindicadores!E$7),AU24))))))))) -> 2.352 | AW24: =IF(ISBLANK(U24),"",IF(ISBLANK($O24),AI24,IF($J24="ANUAL",AI24*(1+Macroindicadores!F$7),IF(AND($I24="NOVO",MONTH($O24)=MONTH(AW$4)),AI24*(1+Macroindicadores!F$7),IF(AND($J24="PONTUAL",MONTH($O24)=MONTH(AW$4)),AI24*(1+Macroindicadores!F$7),IF(AND($J24="PONTUAL",MONTH($O24)<MONTH(AW$4)),MIN($AS24:AV24),IF(AND($I24="NOVO",MONTH($O24)>MONTH(AW$4)),AI24,IF(MONTH($O24)>MONTH(AW$4),AI24,IF(MONTH($O24)=MONTH(AW$4),AI24*(1+Macroindicadores!F$7),AV24))))))))) -> 2.352 | AX24: =IF(ISBLANK(V24),"",IF(ISBLANK($O24),AJ24,IF($J24="ANUAL",AJ24*(1+Macroindicadores!G$7),IF(AND($I24="NOVO",MONTH($O24)=MONTH(AX$4)),AJ24*(1+Macroindicadores!G$7),IF(AND($J24="PONTUAL",MONTH($O24)=MONTH(AX$4)),AJ24*(1+Macroindicadores!G$7),IF(AND($J24="PONTUAL",MONTH($O24)<MONTH(AX$4)),MIN($AS24:AW24),IF(AND($I24="NOVO",MONTH($O24)>MONTH(AX$4)),AJ24,IF(MONTH($O24)>MONTH(AX$4),AJ24,IF(MONTH($O24)=MONTH(AX$4),AJ24*(1+Macroindicadores!G$7),AW24))))))))) -> 2.352 | AY24: =IF(ISBLANK(W24),"",IF(ISBLANK($O24),AK24,IF($J24="ANUAL",AK24*(1+Macroindicadores!H$7),IF(AND($I24="NOVO",MONTH($O24)=MONTH(AY$4)),AK24*(1+Macroindicadores!H$7),IF(AND($J24="PONTUAL",MONTH($O24)=MONTH(AY$4)),AK24*(1+Macroindicadores!H$7),IF(AND($J24="PONTUAL",MONTH($O24)<MONTH(AY$4)),MIN($AS24:AX24),IF(AND($I24="NOVO",MONTH($O24)>MONTH(AY$4)),AK24,IF(MONTH($O24)>MONTH(AY$4),AK24,IF(MONTH($O24)=MONTH(AY$4),AK24*(1+Macroindicadores!H$7),AX24))))))))) -> 2.352 | AZ24: =IF(ISBLANK(X24),"",IF(ISBLANK($O24),AL24,IF($J24="ANUAL",AL24*(1+Macroindicadores!I$7),IF(AND($I24="NOVO",MONTH($O24)=MONTH(AZ$4)),AL24*(1+Macroindicadores!I$7),IF(AND($J24="PONTUAL",MONTH($O24)=MONTH(AZ$4)),AL24*(1+Macroindicadores!I$7),IF(AND($J24="PONTUAL",MONTH($O24)<MONTH(AZ$4)),MIN($AS24:AY24),IF(AND($I24="NOVO",MONTH($O24)>MONTH(AZ$4)),AL24,IF(MONTH($O24)>MONTH(AZ$4),AL24,IF(MONTH($O24)=MONTH(AZ$4),AL24*(1+Macroindicadores!I$7),AY24))))))))) -> 2.352 | BA24: =IF(ISBLANK(Y24),"",IF(ISBLANK($O24),AM24,IF($J24="ANUAL",AM24*(1+Macroindicadores!J$7),IF(AND($I24="NOVO",MONTH($O24)=MONTH(BA$4)),AM24*(1+Macroindicadores!J$7),IF(AND($J24="PONTUAL",MONTH($O24)=MONTH(BA$4)),AM24*(1+Macroindicadores!J$7),IF(AND($J24="PONTUAL",MONTH($O24)<MONTH(BA$4)),MIN($AS24:AZ24),IF(AND($I24="NOVO",MONTH($O24)>MONTH(BA$4)),AM24,IF(MONTH($O24)>MONTH(BA$4),AM24,IF(MONTH($O24)=MONTH(BA$4),AM24*(1+Macroindicadores!J$7),AZ24))))))))) -> 2.352 | ... BD24: =IF(ISBLANK(AB24),"",IF(ISBLANK($O24),AP24,IF($J24="ANUAL",AP24*(1+Macroindicadores!M$7),IF(AND($I24="NOVO",MONTH($O24)=MONTH(BD$4)),AP24*(1+Macroindicadores!M$7),IF(AND($J24="PONTUAL",MONTH($O24)=MONTH(BD$4)),AP24*(1+Macroindicadores!M$7),IF(AND($J24="PONTUAL",MONTH($O24)<MONTH(BD$4)),MIN($AS24:BC24),IF(AND($I24="NOVO",MONTH($O24)>MONTH(BD$4)),AP24,IF(MONTH($O24)>MONTH(BD$4),AP24,IF(MONTH($O24)=MONTH(BD$4),AP24*(1+Macroindicadores!M$7),BC24))))))))) -> 2.352 | BE24: =IF(AND(ISBLANK($Q24),ISBLANK($R24),ISBLANK($S24),ISBLANK($T24),ISBLANK($U24),ISBLANK($V24),ISBLANK($W24),ISBLANK($X24),ISBLANK($Y24),ISBLANK($Z24),ISBLANK($AA24),ISBLANK($AB24)),"",SUM(AS24:BD24)) -> 28.224 | BG24: =IF(ISBLANK(Q24),"",AS24/Macroindicadores!B$2) -> 0.4 | BH24: =IF(ISBLANK(R24),"",AT24/Macroindicadores!C$2) -> 0.4 | BI24: =IF(ISBLANK(S24),"",AU24/Macroindicadores!D$2) -> 0.4 | BJ24: =IF(ISBLANK(T24),"",AV24/Macroindicadores!E$2) -> 0.4 | BK24: =IF(ISBLANK(U24),"",AW24/Macroindicadores!F$2) -> 0.4 | BL24: =IF(ISBLANK(V24),"",AX24/Macroindicadores!G$2) -> 0.4 | BM24: =IF(ISBLANK(W24),"",AY24/Macroindicadores!H$2) -> 0.4 | BN24: =IF(ISBLANK(X24),"",AZ24/Macroindicadores!I$2) -> 0.4 | ... BR24: =IF(ISBLANK(AB24),"",BD24/Macroindicadores!M$2) -> 0.4 | BS24: =IF(AND(ISBLANK($Q24),ISBLANK($R24),ISBLANK($S24),ISBLANK($T24),ISBLANK($U24),ISBLANK($V24),ISBLANK($W24),ISBLANK($X24),ISBLANK($Y24),ISBLANK($Z24),ISBLANK($AA24),ISBLANK($AB24)),"",SUM(BG24:BR24)) -> 4.8 | BT24: =IF(ISBLANK($L24),"",_xlfn.XLOOKUP($L24,'CENTRO CUSTO'!$A:$A,'CENTRO CUSTO'!$E:$E,FALSE,0)) -> G&A BU
A25: =IF(ISBLANK($F25),"","Budget") -> Budget | B25: =IF(ISBLANK($F25),"",$F$1) -> 2026 | C25: =IF(ISBLANK($L25),"",_xlfn.XLOOKUP($L25,'CENTRO CUSTO'!$A:$A,'CENTRO CUSTO'!F:F,FALSE,0)) -> MRV | D25: =IF(ISBLANK($L25),"",_xlfn.XLOOKUP($L25,'CENTRO CUSTO'!$A:$A,'CENTRO CUSTO'!G:G,FALSE,0)) -> BU-MRV | E25: =IF(ISBLANK($L25),"",_xlfn.XLOOKUP($L25,'CENTRO CUSTO'!$A:$A,'CENTRO CUSTO'!H:H,FALSE,0)) -> G&A | F25: SEIDOR | G25: Applications support and maintenance | H25: SAP S4 - VPN | I25: Novo | J25: Mensal | K25: Contrato em Curso | L25: BU-MRV | TI | M25: =IF(ISBLANK($L25),"",_xlfn.XLOOKUP($L25,'CENTRO CUSTO'!$A:$A,'CENTRO CUSTO'!D:D,FALSE,0)) -> Alexandre Ayabe | N25: Manutenção de Informática | P25: USD | Q25: =100*1 -> 100 | R25: =100*1 -> 100 | S25: =100*1 -> 100 | T25: =100*1 -> 100 | U25: =100*1 -> 100 | V25: =100*1 -> 100 | W25: =100*1 -> 100 | X25: =100*1 -> 100 | ... AB25: =100*1 -> 100 | AC25: =IF(AND(ISBLANK($Q25),ISBLANK($R25),ISBLANK($S25),ISBLANK($T25),ISBLANK($U25),ISBLANK($V25),ISBLANK($W25),ISBLANK($X25),ISBLANK($Y25),ISBLANK($Z25),ISBLANK($AA25),ISBLANK($AB25)),"",SUM(Q25:AB25)) -> 1200 | AE25: =IF(ISBLANK(Q25),"",IF($P25="BRL",Q25,Q25*Macroindicadores!B$2)/1000) -> 0.588 | AF25: =IF(ISBLANK(R25),"",IF($P25="BRL",R25,R25*Macroindicadores!C$2)/1000) -> 0.588 | AG25: =IF(ISBLANK(S25),"",IF($P25="BRL",S25,S25*Macroindicadores!D$2)/1000) -> 0.588 | AH25: =IF(ISBLANK(T25),"",IF($P25="BRL",T25,T25*Macroindicadores!E$2)/1000) -> 0.588 | AI25: =IF(ISBLANK(U25),"",IF($P25="BRL",U25,U25*Macroindicadores!F$2)/1000) -> 0.588 | AJ25: =IF(ISBLANK(V25),"",IF($P25="BRL",V25,V25*Macroindicadores!G$2)/1000) -> 0.588 | AK25: =IF(ISBLANK(W25),"",IF($P25="BRL",W25,W25*Macroindicadores!H$2)/1000) -> 0.588 | AL25: =IF(ISBLANK(X25),"",IF($P25="BRL",X25,X25*Macroindicadores!I$2)/1000) -> 0.588 | ... AP25: =IF(ISBLANK(AB25),"",IF($P25="BRL",AB25,AB25*Macroindicadores!M$2)/1000) -> 0.588 | AQ25: =IF(AND(ISBLANK($Q25),ISBLANK($R25),ISBLANK($S25),ISBLANK($T25),ISBLANK($U25),ISBLANK($V25),ISBLANK($W25),ISBLANK($X25),ISBLANK($Y25),ISBLANK($Z25),ISBLANK($AA25),ISBLANK($AB25)),"",SUM(AE25:AP25)) -> 7.056 | AS25: =IF(ISBLANK(Q25),"",IF(ISBLANK($O25),AE25,IF($J25="ANUAL",AE25*(1+Macroindicadores!B$7),IF(AND($I25="NOVO",MONTH($O25)=MONTH(AS$4)),AE25*(1+Macroindicadores!B$7),IF(AND($J25="PONTUAL",MONTH($O25)=MONTH(AS$4)),AE25*(1+Macroindicadores!B$7),IF(AND($J25="PONTUAL",MONTH($O25)<MONTH(AS$4)),MIN(AR25:$AS25),IF(AND($I25="NOVO",MONTH($O25)>MONTH(AS$4)),AE25,IF(MONTH($O25)>MONTH(AS$4),AE25,IF(MONTH($O25)=MONTH(AS$4),AE25*(1+Macroindicadores!B$7),AR25))))))))) -> 0.588 | AT25: =IF(ISBLANK(R25),"",IF(ISBLANK($O25),AF25,IF($J25="ANUAL",AF25*(1+Macroindicadores!C$7),IF(AND($I25="NOVO",MONTH($O25)=MONTH(AT$4)),AF25*(1+Macroindicadores!C$7),IF(AND($J25="PONTUAL",MONTH($O25)=MONTH(AT$4)),AF25*(1+Macroindicadores!C$7),IF(AND($J25="PONTUAL",MONTH($O25)<MONTH(AT$4)),MIN($AS25:AS25),IF(AND($I25="NOVO",MONTH($O25)>MONTH(AT$4)),AF25,IF(MONTH($O25)>MONTH(AT$4),AF25,IF(MONTH($O25)=MONTH(AT$4),AF25*(1+Macroindicadores!C$7),AS25))))))))) -> 0.588 | AU25: =IF(ISBLANK(S25),"",IF(ISBLANK($O25),AG25,IF($J25="ANUAL",AG25*(1+Macroindicadores!D$7),IF(AND($I25="NOVO",MONTH($O25)=MONTH(AU$4)),AG25*(1+Macroindicadores!D$7),IF(AND($J25="PONTUAL",MONTH($O25)=MONTH(AU$4)),AG25*(1+Macroindicadores!D$7),IF(AND($J25="PONTUAL",MONTH($O25)<MONTH(AU$4)),MIN($AS25:AT25),IF(AND($I25="NOVO",MONTH($O25)>MONTH(AU$4)),AG25,IF(MONTH($O25)>MONTH(AU$4),AG25,IF(MONTH($O25)=MONTH(AU$4),AG25*(1+Macroindicadores!D$7),AT25))))))))) -> 0.588 | AV25: =IF(ISBLANK(T25),"",IF(ISBLANK($O25),AH25,IF($J25="ANUAL",AH25*(1+Macroindicadores!E$7),IF(AND($I25="NOVO",MONTH($O25)=MONTH(AV$4)),AH25*(1+Macroindicadores!E$7),IF(AND($J25="PONTUAL",MONTH($O25)=MONTH(AV$4)),AH25*(1+Macroindicadores!E$7),IF(AND($J25="PONTUAL",MONTH($O25)<MONTH(AV$4)),MIN($AS25:AU25),IF(AND($I25="NOVO",MONTH($O25)>MONTH(AV$4)),AH25,IF(MONTH($O25)>MONTH(AV$4),AH25,IF(MONTH($O25)=MONTH(AV$4),AH25*(1+Macroindicadores!E$7),AU25))))))))) -> 0.588 | AW25: =IF(ISBLANK(U25),"",IF(ISBLANK($O25),AI25,IF($J25="ANUAL",AI25*(1+Macroindicadores!F$7),IF(AND($I25="NOVO",MONTH($O25)=MONTH(AW$4)),AI25*(1+Macroindicadores!F$7),IF(AND($J25="PONTUAL",MONTH($O25)=MONTH(AW$4)),AI25*(1+Macroindicadores!F$7),IF(AND($J25="PONTUAL",MONTH($O25)<MONTH(AW$4)),MIN($AS25:AV25),IF(AND($I25="NOVO",MONTH($O25)>MONTH(AW$4)),AI25,IF(MONTH($O25)>MONTH(AW$4),AI25,IF(MONTH($O25)=MONTH(AW$4),AI25*(1+Macroindicadores!F$7),AV25))))))))) -> 0.588 | AX25: =IF(ISBLANK(V25),"",IF(ISBLANK($O25),AJ25,IF($J25="ANUAL",AJ25*(1+Macroindicadores!G$7),IF(AND($I25="NOVO",MONTH($O25)=MONTH(AX$4)),AJ25*(1+Macroindicadores!G$7),IF(AND($J25="PONTUAL",MONTH($O25)=MONTH(AX$4)),AJ25*(1+Macroindicadores!G$7),IF(AND($J25="PONTUAL",MONTH($O25)<MONTH(AX$4)),MIN($AS25:AW25),IF(AND($I25="NOVO",MONTH($O25)>MONTH(AX$4)),AJ25,IF(MONTH($O25)>MONTH(AX$4),AJ25,IF(MONTH($O25)=MONTH(AX$4),AJ25*(1+Macroindicadores!G$7),AW25))))))))) -> 0.588 | AY25: =IF(ISBLANK(W25),"",IF(ISBLANK($O25),AK25,IF($J25="ANUAL",AK25*(1+Macroindicadores!H$7),IF(AND($I25="NOVO",MONTH($O25)=MONTH(AY$4)),AK25*(1+Macroindicadores!H$7),IF(AND($J25="PONTUAL",MONTH($O25)=MONTH(AY$4)),AK25*(1+Macroindicadores!H$7),IF(AND($J25="PONTUAL",MONTH($O25)<MONTH(AY$4)),MIN($AS25:AX25),IF(AND($I25="NOVO",MONTH($O25)>MONTH(AY$4)),AK25,IF(MONTH($O25)>MONTH(AY$4),AK25,IF(MONTH($O25)=MONTH(AY$4),AK25*(1+Macroindicadores!H$7),AX25))))))))) -> 0.588 | AZ25: =IF(ISBLANK(X25),"",IF(ISBLANK($O25),AL25,IF($J25="ANUAL",AL25*(1+Macroindicadores!I$7),IF(AND($I25="NOVO",MONTH($O25)=MONTH(AZ$4)),AL25*(1+Macroindicadores!I$7),IF(AND($J25="PONTUAL",MONTH($O25)=MONTH(AZ$4)),AL25*(1+Macroindicadores!I$7),IF(AND($J25="PONTUAL",MONTH($O25)<MONTH(AZ$4)),MIN($AS25:AY25),IF(AND($I25="NOVO",MONTH($O25)>MONTH(AZ$4)),AL25,IF(MONTH($O25)>MONTH(AZ$4),AL25,IF(MONTH($O25)=MONTH(AZ$4),AL25*(1+Macroindicadores!I$7),AY25))))))))) -> 0.588 | BA25: =IF(ISBLANK(Y25),"",IF(ISBLANK($O25),AM25,IF($J25="ANUAL",AM25*(1+Macroindicadores!J$7),IF(AND($I25="NOVO",MONTH($O25)=MONTH(BA$4)),AM25*(1+Macroindicadores!J$7),IF(AND($J25="PONTUAL",MONTH($O25)=MONTH(BA$4)),AM25*(1+Macroindicadores!J$7),IF(AND($J25="PONTUAL",MONTH($O25)<MONTH(BA$4)),MIN($AS25:AZ25),IF(AND($I25="NOVO",MONTH($O25)>MONTH(BA$4)),AM25,IF(MONTH($O25)>MONTH(BA$4),AM25,IF(MONTH($O25)=MONTH(BA$4),AM25*(1+Macroindicadores!J$7),AZ25))))))))) -> 0.588 | ... BD25: =IF(ISBLANK(AB25),"",IF(ISBLANK($O25),AP25,IF($J25="ANUAL",AP25*(1+Macroindicadores!M$7),IF(AND($I25="NOVO",MONTH($O25)=MONTH(BD$4)),AP25*(1+Macroindicadores!M$7),IF(AND($J25="PONTUAL",MONTH($O25)=MONTH(BD$4)),AP25*(1+Macroindicadores!M$7),IF(AND($J25="PONTUAL",MONTH($O25)<MONTH(BD$4)),MIN($AS25:BC25),IF(AND($I25="NOVO",MONTH($O25)>MONTH(BD$4)),AP25,IF(MONTH($O25)>MONTH(BD$4),AP25,IF(MONTH($O25)=MONTH(BD$4),AP25*(1+Macroindicadores!M$7),BC25))))))))) -> 0.588 | BE25: =IF(AND(ISBLANK($Q25),ISBLANK($R25),ISBLANK($S25),ISBLANK($T25),ISBLANK($U25),ISBLANK($V25),ISBLANK($W25),ISBLANK($X25),ISBLANK($Y25),ISBLANK($Z25),ISBLANK($AA25),ISBLANK($AB25)),"",SUM(AS25:BD25)) -> 7.056 | BG25: =IF(ISBLANK(Q25),"",AS25/Macroindicadores!B$2) -> 0.1 | BH25: =IF(ISBLANK(R25),"",AT25/Macroindicadores!C$2) -> 0.1 | BI25: =IF(ISBLANK(S25),"",AU25/Macroindicadores!D$2) -> 0.1 | BJ25: =IF(ISBLANK(T25),"",AV25/Macroindicadores!E$2) -> 0.1 | BK25: =IF(ISBLANK(U25),"",AW25/Macroindicadores!F$2) -> 0.1 | BL25: =IF(ISBLANK(V25),"",AX25/Macroindicadores!G$2) -> 0.1 | BM25: =IF(ISBLANK(W25),"",AY25/Macroindicadores!H$2) -> 0.1 | BN25: =IF(ISBLANK(X25),"",AZ25/Macroindicadores!I$2) -> 0.1 | ... BR25: =IF(ISBLANK(AB25),"",BD25/Macroindicadores!M$2) -> 0.1 | BS25: =IF(AND(ISBLANK($Q25),ISBLANK($R25),ISBLANK($S25),ISBLANK($T25),ISBLANK($U25),ISBLANK($V25),ISBLANK($W25),ISBLANK($X25),ISBLANK($Y25),ISBLANK($Z25),ISBLANK($AA25),ISBLANK($AB25)),"",SUM(BG25:BR25)) -> 1.2 | BT25: =IF(ISBLANK($L25),"",_xlfn.XLOOKUP($L25,'CENTRO CUSTO'!$A:$A,'CENTRO CUSTO'!$E:$E,FALSE,0)) -> G&A BU
A26: =IF(ISBLANK($F26),"","Budget") -> Budget | B26: =IF(ISBLANK($F26),"",$F$1) -> 2026 | C26: =IF(ISBLANK($L26),"",_xlfn.XLOOKUP($L26,'CENTRO CUSTO'!$A:$A,'CENTRO CUSTO'!F:F,FALSE,0)) -> SKM | D26: =IF(ISBLANK($L26),"",_xlfn.XLOOKUP($L26,'CENTRO CUSTO'!$A:$A,'CENTRO CUSTO'!G:G,FALSE,0)) -> BU-SKM | E26: =IF(ISBLANK($L26),"",_xlfn.XLOOKUP($L26,'CENTRO CUSTO'!$A:$A,'CENTRO CUSTO'!H:H,FALSE,0)) -> G&A | F26: SEIDOR | G26: Applications support and maintenance | H26: SAP S4 - VPN | I26: Novo | J26: Mensal | K26: Contrato em Curso | L26: BU-GRU | TI | M26: =IF(ISBLANK($L26),"",_xlfn.XLOOKUP($L26,'CENTRO CUSTO'!$A:$A,'CENTRO CUSTO'!D:D,FALSE,0)) -> Alexandre Ayabe | N26: Manutenção de Informática | P26: USD | Q26: =100*1 -> 100 | R26: =100*1 -> 100 | S26: =100*1 -> 100 | T26: =100*1 -> 100 | U26: =100*1 -> 100 | V26: =100*1 -> 100 | W26: =100*1 -> 100 | X26: =100*1 -> 100 | ... AB26: =100*1 -> 100 | AC26: =IF(AND(ISBLANK($Q26),ISBLANK($R26),ISBLANK($S26),ISBLANK($T26),ISBLANK($U26),ISBLANK($V26),ISBLANK($W26),ISBLANK($X26),ISBLANK($Y26),ISBLANK($Z26),ISBLANK($AA26),ISBLANK($AB26)),"",SUM(Q26:AB26)) -> 1200 | AE26: =IF(ISBLANK(Q26),"",IF($P26="BRL",Q26,Q26*Macroindicadores!B$2)/1000) -> 0.588 | AF26: =IF(ISBLANK(R26),"",IF($P26="BRL",R26,R26*Macroindicadores!C$2)/1000) -> 0.588 | AG26: =IF(ISBLANK(S26),"",IF($P26="BRL",S26,S26*Macroindicadores!D$2)/1000) -> 0.588 | AH26: =IF(ISBLANK(T26),"",IF($P26="BRL",T26,T26*Macroindicadores!E$2)/1000) -> 0.588 | AI26: =IF(ISBLANK(U26),"",IF($P26="BRL",U26,U26*Macroindicadores!F$2)/1000) -> 0.588 | AJ26: =IF(ISBLANK(V26),"",IF($P26="BRL",V26,V26*Macroindicadores!G$2)/1000) -> 0.588 | AK26: =IF(ISBLANK(W26),"",IF($P26="BRL",W26,W26*Macroindicadores!H$2)/1000) -> 0.588 | AL26: =IF(ISBLANK(X26),"",IF($P26="BRL",X26,X26*Macroindicadores!I$2)/1000) -> 0.588 | ... AP26: =IF(ISBLANK(AB26),"",IF($P26="BRL",AB26,AB26*Macroindicadores!M$2)/1000) -> 0.588 | AQ26: =IF(AND(ISBLANK($Q26),ISBLANK($R26),ISBLANK($S26),ISBLANK($T26),ISBLANK($U26),ISBLANK($V26),ISBLANK($W26),ISBLANK($X26),ISBLANK($Y26),ISBLANK($Z26),ISBLANK($AA26),ISBLANK($AB26)),"",SUM(AE26:AP26)) -> 7.056 | AS26: =IF(ISBLANK(Q26),"",IF(ISBLANK($O26),AE26,IF($J26="ANUAL",AE26*(1+Macroindicadores!B$7),IF(AND($I26="NOVO",MONTH($O26)=MONTH(AS$4)),AE26*(1+Macroindicadores!B$7),IF(AND($J26="PONTUAL",MONTH($O26)=MONTH(AS$4)),AE26*(1+Macroindicadores!B$7),IF(AND($J26="PONTUAL",MONTH($O26)<MONTH(AS$4)),MIN(AR26:$AS26),IF(AND($I26="NOVO",MONTH($O26)>MONTH(AS$4)),AE26,IF(MONTH($O26)>MONTH(AS$4),AE26,IF(MONTH($O26)=MONTH(AS$4),AE26*(1+Macroindicadores!B$7),AR26))))))))) -> 0.588 | AT26: =IF(ISBLANK(R26),"",IF(ISBLANK($O26),AF26,IF($J26="ANUAL",AF26*(1+Macroindicadores!C$7),IF(AND($I26="NOVO",MONTH($O26)=MONTH(AT$4)),AF26*(1+Macroindicadores!C$7),IF(AND($J26="PONTUAL",MONTH($O26)=MONTH(AT$4)),AF26*(1+Macroindicadores!C$7),IF(AND($J26="PONTUAL",MONTH($O26)<MONTH(AT$4)),MIN($AS26:AS26),IF(AND($I26="NOVO",MONTH($O26)>MONTH(AT$4)),AF26,IF(MONTH($O26)>MONTH(AT$4),AF26,IF(MONTH($O26)=MONTH(AT$4),AF26*(1+Macroindicadores!C$7),AS26))))))))) -> 0.588 | AU26: =IF(ISBLANK(S26),"",IF(ISBLANK($O26),AG26,IF($J26="ANUAL",AG26*(1+Macroindicadores!D$7),IF(AND($I26="NOVO",MONTH($O26)=MONTH(AU$4)),AG26*(1+Macroindicadores!D$7),IF(AND($J26="PONTUAL",MONTH($O26)=MONTH(AU$4)),AG26*(1+Macroindicadores!D$7),IF(AND($J26="PONTUAL",MONTH($O26)<MONTH(AU$4)),MIN($AS26:AT26),IF(AND($I26="NOVO",MONTH($O26)>MONTH(AU$4)),AG26,IF(MONTH($O26)>MONTH(AU$4),AG26,IF(MONTH($O26)=MONTH(AU$4),AG26*(1+Macroindicadores!D$7),AT26))))))))) -> 0.588 | AV26: =IF(ISBLANK(T26),"",IF(ISBLANK($O26),AH26,IF($J26="ANUAL",AH26*(1+Macroindicadores!E$7),IF(AND($I26="NOVO",MONTH($O26)=MONTH(AV$4)),AH26*(1+Macroindicadores!E$7),IF(AND($J26="PONTUAL",MONTH($O26)=MONTH(AV$4)),AH26*(1+Macroindicadores!E$7),IF(AND($J26="PONTUAL",MONTH($O26)<MONTH(AV$4)),MIN($AS26:AU26),IF(AND($I26="NOVO",MONTH($O26)>MONTH(AV$4)),AH26,IF(MONTH($O26)>MONTH(AV$4),AH26,IF(MONTH($O26)=MONTH(AV$4),AH26*(1+Macroindicadores!E$7),AU26))))))))) -> 0.588 | AW26: =IF(ISBLANK(U26),"",IF(ISBLANK($O26),AI26,IF($J26="ANUAL",AI26*(1+Macroindicadores!F$7),IF(AND($I26="NOVO",MONTH($O26)=MONTH(AW$4)),AI26*(1+Macroindicadores!F$7),IF(AND($J26="PONTUAL",MONTH($O26)=MONTH(AW$4)),AI26*(1+Macroindicadores!F$7),IF(AND($J26="PONTUAL",MONTH($O26)<MONTH(AW$4)),MIN($AS26:AV26),IF(AND($I26="NOVO",MONTH($O26)>MONTH(AW$4)),AI26,IF(MONTH($O26)>MONTH(AW$4),AI26,IF(MONTH($O26)=MONTH(AW$4),AI26*(1+Macroindicadores!F$7),AV26))))))))) -> 0.588 | AX26: =IF(ISBLANK(V26),"",IF(ISBLANK($O26),AJ26,IF($J26="ANUAL",AJ26*(1+Macroindicadores!G$7),IF(AND($I26="NOVO",MONTH($O26)=MONTH(AX$4)),AJ26*(1+Macroindicadores!G$7),IF(AND($J26="PONTUAL",MONTH($O26)=MONTH(AX$4)),AJ26*(1+Macroindicadores!G$7),IF(AND($J26="PONTUAL",MONTH($O26)<MONTH(AX$4)),MIN($AS26:AW26),IF(AND($I26="NOVO",MONTH($O26)>MONTH(AX$4)),AJ26,IF(MONTH($O26)>MONTH(AX$4),AJ26,IF(MONTH($O26)=MONTH(AX$4),AJ26*(1+Macroindicadores!G$7),AW26))))))))) -> 0.588 | AY26: =IF(ISBLANK(W26),"",IF(ISBLANK($O26),AK26,IF($J26="ANUAL",AK26*(1+Macroindicadores!H$7),IF(AND($I26="NOVO",MONTH($O26)=MONTH(AY$4)),AK26*(1+Macroindicadores!H$7),IF(AND($J26="PONTUAL",MONTH($O26)=MONTH(AY$4)),AK26*(1+Macroindicadores!H$7),IF(AND($J26="PONTUAL",MONTH($O26)<MONTH(AY$4)),MIN($AS26:AX26),IF(AND($I26="NOVO",MONTH($O26)>MONTH(AY$4)),AK26,IF(MONTH($O26)>MONTH(AY$4),AK26,IF(MONTH($O26)=MONTH(AY$4),AK26*(1+Macroindicadores!H$7),AX26))))))))) -> 0.588 | AZ26: =IF(ISBLANK(X26),"",IF(ISBLANK($O26),AL26,IF($J26="ANUAL",AL26*(1+Macroindicadores!I$7),IF(AND($I26="NOVO",MONTH($O26)=MONTH(AZ$4)),AL26*(1+Macroindicadores!I$7),IF(AND($J26="PONTUAL",MONTH($O26)=MONTH(AZ$4)),AL26*(1+Macroindicadores!I$7),IF(AND($J26="PONTUAL",MONTH($O26)<MONTH(AZ$4)),MIN($AS26:AY26),IF(AND($I26="NOVO",MONTH($O26)>MONTH(AZ$4)),AL26,IF(MONTH($O26)>MONTH(AZ$4),AL26,IF(MONTH($O26)=MONTH(AZ$4),AL26*(1+Macroindicadores!I$7),AY26))))))))) -> 0.588 | BA26: =IF(ISBLANK(Y26),"",IF(ISBLANK($O26),AM26,IF($J26="ANUAL",AM26*(1+Macroindicadores!J$7),IF(AND($I26="NOVO",MONTH($O26)=MONTH(BA$4)),AM26*(1+Macroindicadores!J$7),IF(AND($J26="PONTUAL",MONTH($O26)=MONTH(BA$4)),AM26*(1+Macroindicadores!J$7),IF(AND($J26="PONTUAL",MONTH($O26)<MONTH(BA$4)),MIN($AS26:AZ26),IF(AND($I26="NOVO",MONTH($O26)>MONTH(BA$4)),AM26,IF(MONTH($O26)>MONTH(BA$4),AM26,IF(MONTH($O26)=MONTH(BA$4),AM26*(1+Macroindicadores!J$7),AZ26))))))))) -> 0.588 | ... BD26: =IF(ISBLANK(AB26),"",IF(ISBLANK($O26),AP26,IF($J26="ANUAL",AP26*(1+Macroindicadores!M$7),IF(AND($I26="NOVO",MONTH($O26)=MONTH(BD$4)),AP26*(1+Macroindicadores!M$7),IF(AND($J26="PONTUAL",MONTH($O26)=MONTH(BD$4)),AP26*(1+Macroindicadores!M$7),IF(AND($J26="PONTUAL",MONTH($O26)<MONTH(BD$4)),MIN($AS26:BC26),IF(AND($I26="NOVO",MONTH($O26)>MONTH(BD$4)),AP26,IF(MONTH($O26)>MONTH(BD$4),AP26,IF(MONTH($O26)=MONTH(BD$4),AP26*(1+Macroindicadores!M$7),BC26))))))))) -> 0.588 | BE26: =IF(AND(ISBLANK($Q26),ISBLANK($R26),ISBLANK($S26),ISBLANK($T26),ISBLANK($U26),ISBLANK($V26),ISBLANK($W26),ISBLANK($X26),ISBLANK($Y26),ISBLANK($Z26),ISBLANK($AA26),ISBLANK($AB26)),"",SUM(AS26:BD26)) -> 7.056 | BG26: =IF(ISBLANK(Q26),"",AS26/Macroindicadores!B$2) -> 0.1 | BH26: =IF(ISBLANK(R26),"",AT26/Macroindicadores!C$2) -> 0.1 | BI26: =IF(ISBLANK(S26),"",AU26/Macroindicadores!D$2) -> 0.1 | BJ26: =IF(ISBLANK(T26),"",AV26/Macroindicadores!E$2) -> 0.1 | BK26: =IF(ISBLANK(U26),"",AW26/Macroindicadores!F$2) -> 0.1 | BL26: =IF(ISBLANK(V26),"",AX26/Macroindicadores!G$2) -> 0.1 | BM26: =IF(ISBLANK(W26),"",AY26/Macroindicadores!H$2) -> 0.1 | BN26: =IF(ISBLANK(X26),"",AZ26/Macroindicadores!I$2) -> 0.1 | ... BR26: =IF(ISBLANK(AB26),"",BD26/Macroindicadores!M$2) -> 0.1 | BS26: =IF(AND(ISBLANK($Q26),ISBLANK($R26),ISBLANK($S26),ISBLANK($T26),ISBLANK($U26),ISBLANK($V26),ISBLANK($W26),ISBLANK($X26),ISBLANK($Y26),ISBLANK($Z26),ISBLANK($AA26),ISBLANK($AB26)),"",SUM(BG26:BR26)) -> 1.2 | BT26: =IF(ISBLANK($L26),"",_xlfn.XLOOKUP($L26,'CENTRO CUSTO'!$A:$A,'CENTRO CUSTO'!$E:$E,FALSE,0)) -> G&A BU
A27: =IF(ISBLANK($F27),"","Budget") -> Budget | B27: =IF(ISBLANK($F27),"",$F$1) -> 2026 | C27: =IF(ISBLANK($L27),"",_xlfn.XLOOKUP($L27,'CENTRO CUSTO'!$A:$A,'CENTRO CUSTO'!F:F,FALSE,0)) -> Martini Meat | D27: =IF(ISBLANK($L27),"",_xlfn.XLOOKUP($L27,'CENTRO CUSTO'!$A:$A,'CENTRO CUSTO'!G:G,FALSE,0)) -> Paranaguá | E27: =IF(ISBLANK($L27),"",_xlfn.XLOOKUP($L27,'CENTRO CUSTO'!$A:$A,'CENTRO CUSTO'!H:H,FALSE,0)) -> Frigorífico | F27: INFIOS US,INC | G27: Applications support and maintenance | H27: Licença WMS (%Net Sales) | I27: Existente | J27: Mensal | K27: Contrato em Curso | L27: FG-PNG | TI | M27: =IF(ISBLANK($L27),"",_xlfn.XLOOKUP($L27,'CENTRO CUSTO'!$A:$A,'CENTRO CUSTO'!D:D,FALSE,0)) -> Alexandre Ayabe | N27: Licença WMS-KORBER | P27: USD | Q27: =55214*Rateio!$E$66/12 -> 1288.3267 | R27: =55214*Rateio!$E$66/12 -> 1288.3267 | S27: =55214*Rateio!$E$66/12 -> 1288.3267 | T27: =55214*Rateio!$E$66/12 -> 1288.3267 | U27: =55214*Rateio!$E$66/12 -> 1288.3267 | V27: =55214*Rateio!$E$66/12 -> 1288.3267 | W27: =55214*Rateio!$E$66/12 -> 1288.3267 | X27: =55214*Rateio!$E$66/12 -> 1288.3267 | ... AB27: =55214*Rateio!$E$66/12 -> 1288.3267 | AC27: =IF(AND(ISBLANK($Q27),ISBLANK($R27),ISBLANK($S27),ISBLANK($T27),ISBLANK($U27),ISBLANK($V27),ISBLANK($W27),ISBLANK($X27),ISBLANK($Y27),ISBLANK($Z27),ISBLANK($AA27),ISBLANK($AB27)),"",SUM(Q27:AB27)) -> 15459.92 | AE27: =IF(ISBLANK(Q27),"",IF($P27="BRL",Q27,Q27*Macroindicadores!B$2)/1000) -> 7.5753608 | AF27: =IF(ISBLANK(R27),"",IF($P27="BRL",R27,R27*Macroindicadores!C$2)/1000) -> 7.5753608 | AG27: =IF(ISBLANK(S27),"",IF($P27="BRL",S27,S27*Macroindicadores!D$2)/1000) -> 7.5753608 | AH27: =IF(ISBLANK(T27),"",IF($P27="BRL",T27,T27*Macroindicadores!E$2)/1000) -> 7.5753608 | AI27: =IF(ISBLANK(U27),"",IF($P27="BRL",U27,U27*Macroindicadores!F$2)/1000) -> 7.5753608 | AJ27: =IF(ISBLANK(V27),"",IF($P27="BRL",V27,V27*Macroindicadores!G$2)/1000) -> 7.5753608 | AK27: =IF(ISBLANK(W27),"",IF($P27="BRL",W27,W27*Macroindicadores!H$2)/1000) -> 7.5753608 | AL27: =IF(ISBLANK(X27),"",IF($P27="BRL",X27,X27*Macroindicadores!I$2)/1000) -> 7.5753608 | ... AP27: =IF(ISBLANK(AB27),"",IF($P27="BRL",AB27,AB27*Macroindicadores!M$2)/1000) -> 7.5753608 | AQ27: =IF(AND(ISBLANK($Q27),ISBLANK($R27),ISBLANK($S27),ISBLANK($T27),ISBLANK($U27),ISBLANK($V27),ISBLANK($W27),ISBLANK($X27),ISBLANK($Y27),ISBLANK($Z27),ISBLANK($AA27),ISBLANK($AB27)),"",SUM(AE27:AP27)) -> 90.90433 | AS27: =IF(ISBLANK(Q27),"",IF(ISBLANK($O27),AE27,IF($J27="ANUAL",AE27*(1+Macroindicadores!B$7),IF(AND($I27="NOVO",MONTH($O27)=MONTH(AS$4)),AE27*(1+Macroindicadores!B$7),IF(AND($J27="PONTUAL",MONTH($O27)=MONTH(AS$4)),AE27*(1+Macroindicadores!B$7),IF(AND($J27="PONTUAL",MONTH($O27)<MONTH(AS$4)),MIN(AR27:$AS27),IF(AND($I27="NOVO",MONTH($O27)>MONTH(AS$4)),AE27,IF(MONTH($O27)>MONTH(AS$4),AE27,IF(MONTH($O27)=MONTH(AS$4),AE27*(1+Macroindicadores!B$7),AR27))))))))) -> 7.5753608 | AT27: =IF(ISBLANK(R27),"",IF(ISBLANK($O27),AF27,IF($J27="ANUAL",AF27*(1+Macroindicadores!C$7),IF(AND($I27="NOVO",MONTH($O27)=MONTH(AT$4)),AF27*(1+Macroindicadores!C$7),IF(AND($J27="PONTUAL",MONTH($O27)=MONTH(AT$4)),AF27*(1+Macroindicadores!C$7),IF(AND($J27="PONTUAL",MONTH($O27)<MONTH(AT$4)),MIN($AS27:AS27),IF(AND($I27="NOVO",MONTH($O27)>MONTH(AT$4)),AF27,IF(MONTH($O27)>MONTH(AT$4),AF27,IF(MONTH($O27)=MONTH(AT$4),AF27*(1+Macroindicadores!C$7),AS27))))))))) -> 7.5753608 | AU27: =IF(ISBLANK(S27),"",IF(ISBLANK($O27),AG27,IF($J27="ANUAL",AG27*(1+Macroindicadores!D$7),IF(AND($I27="NOVO",MONTH($O27)=MONTH(AU$4)),AG27*(1+Macroindicadores!D$7),IF(AND($J27="PONTUAL",MONTH($O27)=MONTH(AU$4)),AG27*(1+Macroindicadores!D$7),IF(AND($J27="PONTUAL",MONTH($O27)<MONTH(AU$4)),MIN($AS27:AT27),IF(AND($I27="NOVO",MONTH($O27)>MONTH(AU$4)),AG27,IF(MONTH($O27)>MONTH(AU$4),AG27,IF(MONTH($O27)=MONTH(AU$4),AG27*(1+Macroindicadores!D$7),AT27))))))))) -> 7.5753608 | AV27: =IF(ISBLANK(T27),"",IF(ISBLANK($O27),AH27,IF($J27="ANUAL",AH27*(1+Macroindicadores!E$7),IF(AND($I27="NOVO",MONTH($O27)=MONTH(AV$4)),AH27*(1+Macroindicadores!E$7),IF(AND($J27="PONTUAL",MONTH($O27)=MONTH(AV$4)),AH27*(1+Macroindicadores!E$7),IF(AND($J27="PONTUAL",MONTH($O27)<MONTH(AV$4)),MIN($AS27:AU27),IF(AND($I27="NOVO",MONTH($O27)>MONTH(AV$4)),AH27,IF(MONTH($O27)>MONTH(AV$4),AH27,IF(MONTH($O27)=MONTH(AV$4),AH27*(1+Macroindicadores!E$7),AU27))))))))) -> 7.5753608 | AW27: =IF(ISBLANK(U27),"",IF(ISBLANK($O27),AI27,IF($J27="ANUAL",AI27*(1+Macroindicadores!F$7),IF(AND($I27="NOVO",MONTH($O27)=MONTH(AW$4)),AI27*(1+Macroindicadores!F$7),IF(AND($J27="PONTUAL",MONTH($O27)=MONTH(AW$4)),AI27*(1+Macroindicadores!F$7),IF(AND($J27="PONTUAL",MONTH($O27)<MONTH(AW$4)),MIN($AS27:AV27),IF(AND($I27="NOVO",MONTH($O27)>MONTH(AW$4)),AI27,IF(MONTH($O27)>MONTH(AW$4),AI27,IF(MONTH($O27)=MONTH(AW$4),AI27*(1+Macroindicadores!F$7),AV27))))))))) -> 7.5753608 | AX27: =IF(ISBLANK(V27),"",IF(ISBLANK($O27),AJ27,IF($J27="ANUAL",AJ27*(1+Macroindicadores!G$7),IF(AND($I27="NOVO",MONTH($O27)=MONTH(AX$4)),AJ27*(1+Macroindicadores!G$7),IF(AND($J27="PONTUAL",MONTH($O27)=MONTH(AX$4)),AJ27*(1+Macroindicadores!G$7),IF(AND($J27="PONTUAL",MONTH($O27)<MONTH(AX$4)),MIN($AS27:AW27),IF(AND($I27="NOVO",MONTH($O27)>MONTH(AX$4)),AJ27,IF(MONTH($O27)>MONTH(AX$4),AJ27,IF(MONTH($O27)=MONTH(AX$4),AJ27*(1+Macroindicadores!G$7),AW27))))))))) -> 7.5753608 | AY27: =IF(ISBLANK(W27),"",IF(ISBLANK($O27),AK27,IF($J27="ANUAL",AK27*(1+Macroindicadores!H$7),IF(AND($I27="NOVO",MONTH($O27)=MONTH(AY$4)),AK27*(1+Macroindicadores!H$7),IF(AND($J27="PONTUAL",MONTH($O27)=MONTH(AY$4)),AK27*(1+Macroindicadores!H$7),IF(AND($J27="PONTUAL",MONTH($O27)<MONTH(AY$4)),MIN($AS27:AX27),IF(AND($I27="NOVO",MONTH($O27)>MONTH(AY$4)),AK27,IF(MONTH($O27)>MONTH(AY$4),AK27,IF(MONTH($O27)=MONTH(AY$4),AK27*(1+Macroindicadores!H$7),AX27))))))))) -> 7.5753608 | AZ27: =IF(ISBLANK(X27),"",IF(ISBLANK($O27),AL27,IF($J27="ANUAL",AL27*(1+Macroindicadores!I$7),IF(AND($I27="NOVO",MONTH($O27)=MONTH(AZ$4)),AL27*(1+Macroindicadores!I$7),IF(AND($J27="PONTUAL",MONTH($O27)=MONTH(AZ$4)),AL27*(1+Macroindicadores!I$7),IF(AND($J27="PONTUAL",MONTH($O27)<MONTH(AZ$4)),MIN($AS27:AY27),IF(AND($I27="NOVO",MONTH($O27)>MONTH(AZ$4)),AL27,IF(MONTH($O27)>MONTH(AZ$4),AL27,IF(MONTH($O27)=MONTH(AZ$4),AL27*(1+Macroindicadores!I$7),AY27))))))))) -> 7.5753608 | BA27: =IF(ISBLANK(Y27),"",IF(ISBLANK($O27),AM27,IF($J27="ANUAL",AM27*(1+Macroindicadores!J$7),IF(AND($I27="NOVO",MONTH($O27)=MONTH(BA$4)),AM27*(1+Macroindicadores!J$7),IF(AND($J27="PONTUAL",MONTH($O27)=MONTH(BA$4)),AM27*(1+Macroindicadores!J$7),IF(AND($J27="PONTUAL",MONTH($O27)<MONTH(BA$4)),MIN($AS27:AZ27),IF(AND($I27="NOVO",MONTH($O27)>MONTH(BA$4)),AM27,IF(MONTH($O27)>MONTH(BA$4),AM27,IF(MONTH($O27)=MONTH(BA$4),AM27*(1+Macroindicadores!J$7),AZ27))))))))) -> 7.5753608 | ... BD27: =IF(ISBLANK(AB27),"",IF(ISBLANK($O27),AP27,IF($J27="ANUAL",AP27*(1+Macroindicadores!M$7),IF(AND($I27="NOVO",MONTH($O27)=MONTH(BD$4)),AP27*(1+Macroindicadores!M$7),IF(AND($J27="PONTUAL",MONTH($O27)=MONTH(BD$4)),AP27*(1+Macroindicadores!M$7),IF(AND($J27="PONTUAL",MONTH($O27)<MONTH(BD$4)),MIN($AS27:BC27),IF(AND($I27="NOVO",MONTH($O27)>MONTH(BD$4)),AP27,IF(MONTH($O27)>MONTH(BD$4),AP27,IF(MONTH($O27)=MONTH(BD$4),AP27*(1+Macroindicadores!M$7),BC27))))))))) -> 7.5753608 | BE27: =IF(AND(ISBLANK($Q27),ISBLANK($R27),ISBLANK($S27),ISBLANK($T27),ISBLANK($U27),ISBLANK($V27),ISBLANK($W27),ISBLANK($X27),ISBLANK($Y27),ISBLANK($Z27),ISBLANK($AA27),ISBLANK($AB27)),"",SUM(AS27:BD27)) -> 90.90433 | BG27: =IF(ISBLANK(Q27),"",AS27/Macroindicadores!B$2) -> 1.2883267 | BH27: =IF(ISBLANK(R27),"",AT27/Macroindicadores!C$2) -> 1.2883267 | BI27: =IF(ISBLANK(S27),"",AU27/Macroindicadores!D$2) -> 1.2883267 | BJ27: =IF(ISBLANK(T27),"",AV27/Macroindicadores!E$2) -> 1.2883267 | BK27: =IF(ISBLANK(U27),"",AW27/Macroindicadores!F$2) -> 1.2883267 | BL27: =IF(ISBLANK(V27),"",AX27/Macroindicadores!G$2) -> 1.2883267 | BM27: =IF(ISBLANK(W27),"",AY27/Macroindicadores!H$2) -> 1.2883267 | BN27: =IF(ISBLANK(X27),"",AZ27/Macroindicadores!I$2) -> 1.2883267 | ... BR27: =IF(ISBLANK(AB27),"",BD27/Macroindicadores!M$2) -> 1.2883267 | BS27: =IF(AND(ISBLANK($Q27),ISBLANK($R27),ISBLANK($S27),ISBLANK($T27),ISBLANK($U27),ISBLANK($V27),ISBLANK($W27),ISBLANK($X27),ISBLANK($Y27),ISBLANK($Z27),ISBLANK($AA27),ISBLANK($AB27)),"",SUM(BG27:BR27)) -> 15.45992 | BT27: =IF(ISBLANK($L27),"",_xlfn.XLOOKUP($L27,'CENTRO CUSTO'!$A:$A,'CENTRO CUSTO'!$E:$E,FALSE,0)) -> Custo Fixo
A28: =IF(ISBLANK($F28),"","Budget") -> Budget | B28: =IF(ISBLANK($F28),"",$F$1) -> 2026 | C28: =IF(ISBLANK($L28),"",_xlfn.XLOOKUP($L28,'CENTRO CUSTO'!$A:$A,'CENTRO CUSTO'!F:F,FALSE,0)) -> Martini Meat | D28: =IF(ISBLANK($L28),"",_xlfn.XLOOKUP($L28,'CENTRO CUSTO'!$A:$A,'CENTRO CUSTO'!G:G,FALSE,0)) -> Paranaguá | E28: =IF(ISBLANK($L28),"",_xlfn.XLOOKUP($L28,'CENTRO CUSTO'!$A:$A,'CENTRO CUSTO'!H:H,FALSE,0)) -> Carga Geral | F28: INFIOS US,INC | G28: Applications support and maintenance | H28: Licença WMS (%Net Sales) | I28: Existente | J28: Mensal | K28: Contrato em Curso | L28: CG-PNG | TI | M28: =IF(ISBLANK($L28),"",_xlfn.XLOOKUP($L28,'CENTRO CUSTO'!$A:$A,'CENTRO CUSTO'!D:D,FALSE,0)) -> Alexandre Ayabe | N28: Licença WMS-KORBER | P28: USD | Q28: =55214*Rateio!$E$65/12 -> 322.08167 | R28: =55214*Rateio!$E$65/12 -> 322.08167 | S28: =55214*Rateio!$E$65/12 -> 322.08167 | T28: =55214*Rateio!$E$65/12 -> 322.08167 | U28: =55214*Rateio!$E$65/12 -> 322.08167 | V28: =55214*Rateio!$E$65/12 -> 322.08167 | W28: =55214*Rateio!$E$65/12 -> 322.08167 | X28: =55214*Rateio!$E$65/12 -> 322.08167 | ... AB28: =55214*Rateio!$E$65/12 -> 322.08167 | AC28: =IF(AND(ISBLANK($Q28),ISBLANK($R28),ISBLANK($S28),ISBLANK($T28),ISBLANK($U28),ISBLANK($V28),ISBLANK($W28),ISBLANK($X28),ISBLANK($Y28),ISBLANK($Z28),ISBLANK($AA28),ISBLANK($AB28)),"",SUM(Q28:AB28)) -> 3864.98 | AE28: =IF(ISBLANK(Q28),"",IF($P28="BRL",Q28,Q28*Macroindicadores!B$2)/1000) -> 1.8938402 | AF28: =IF(ISBLANK(R28),"",IF($P28="BRL",R28,R28*Macroindicadores!C$2)/1000) -> 1.8938402 | AG28: =IF(ISBLANK(S28),"",IF($P28="BRL",S28,S28*Macroindicadores!D$2)/1000) -> 1.8938402 | AH28: =IF(ISBLANK(T28),"",IF($P28="BRL",T28,T28*Macroindicadores!E$2)/1000) -> 1.8938402 | AI28: =IF(ISBLANK(U28),"",IF($P28="BRL",U28,U28*Macroindicadores!F$2)/1000) -> 1.8938402 | AJ28: =IF(ISBLANK(V28),"",IF($P28="BRL",V28,V28*Macroindicadores!G$2)/1000) -> 1.8938402 | AK28: =IF(ISBLANK(W28),"",IF($P28="BRL",W28,W28*Macroindicadores!H$2)/1000) -> 1.8938402 | AL28: =IF(ISBLANK(X28),"",IF($P28="BRL",X28,X28*Macroindicadores!I$2)/1000) -> 1.8938402 | ... AP28: =IF(ISBLANK(AB28),"",IF($P28="BRL",AB28,AB28*Macroindicadores!M$2)/1000) -> 1.8938402 | AQ28: =IF(AND(ISBLANK($Q28),ISBLANK($R28),ISBLANK($S28),ISBLANK($T28),ISBLANK($U28),ISBLANK($V28),ISBLANK($W28),ISBLANK($X28),ISBLANK($Y28),ISBLANK($Z28),ISBLANK($AA28),ISBLANK($AB28)),"",SUM(AE28:AP28)) -> 22.726082 | AS28: =IF(ISBLANK(Q28),"",IF(ISBLANK($O28),AE28,IF($J28="ANUAL",AE28*(1+Macroindicadores!B$7),IF(AND($I28="NOVO",MONTH($O28)=MONTH(AS$4)),AE28*(1+Macroindicadores!B$7),IF(AND($J28="PONTUAL",MONTH($O28)=MONTH(AS$4)),AE28*(1+Macroindicadores!B$7),IF(AND($J28="PONTUAL",MONTH($O28)<MONTH(AS$4)),MIN(AR28:$AS28),IF(AND($I28="NOVO",MONTH($O28)>MONTH(AS$4)),AE28,IF(MONTH($O28)>MONTH(AS$4),AE28,IF(MONTH($O28)=MONTH(AS$4),AE28*(1+Macroindicadores!B$7),AR28))))))))) -> 1.8938402 | AT28: =IF(ISBLANK(R28),"",IF(ISBLANK($O28),AF28,IF($J28="ANUAL",AF28*(1+Macroindicadores!C$7),IF(AND($I28="NOVO",MONTH($O28)=MONTH(AT$4)),AF28*(1+Macroindicadores!C$7),IF(AND($J28="PONTUAL",MONTH($O28)=MONTH(AT$4)),AF28*(1+Macroindicadores!C$7),IF(AND($J28="PONTUAL",MONTH($O28)<MONTH(AT$4)),MIN($AS28:AS28),IF(AND($I28="NOVO",MONTH($O28)>MONTH(AT$4)),AF28,IF(MONTH($O28)>MONTH(AT$4),AF28,IF(MONTH($O28)=MONTH(AT$4),AF28*(1+Macroindicadores!C$7),AS28))))))))) -> 1.8938402 | AU28: =IF(ISBLANK(S28),"",IF(ISBLANK($O28),AG28,IF($J28="ANUAL",AG28*(1+Macroindicadores!D$7),IF(AND($I28="NOVO",MONTH($O28)=MONTH(AU$4)),AG28*(1+Macroindicadores!D$7),IF(AND($J28="PONTUAL",MONTH($O28)=MONTH(AU$4)),AG28*(1+Macroindicadores!D$7),IF(AND($J28="PONTUAL",MONTH($O28)<MONTH(AU$4)),MIN($AS28:AT28),IF(AND($I28="NOVO",MONTH($O28)>MONTH(AU$4)),AG28,IF(MONTH($O28)>MONTH(AU$4),AG28,IF(MONTH($O28)=MONTH(AU$4),AG28*(1+Macroindicadores!D$7),AT28))))))))) -> 1.8938402 | AV28: =IF(ISBLANK(T28),"",IF(ISBLANK($O28),AH28,IF($J28="ANUAL",AH28*(1+Macroindicadores!E$7),IF(AND($I28="NOVO",MONTH($O28)=MONTH(AV$4)),AH28*(1+Macroindicadores!E$7),IF(AND($J28="PONTUAL",MONTH($O28)=MONTH(AV$4)),AH28*(1+Macroindicadores!E$7),IF(AND($J28="PONTUAL",MONTH($O28)<MONTH(AV$4)),MIN($AS28:AU28),IF(AND($I28="NOVO",MONTH($O28)>MONTH(AV$4)),AH28,IF(MONTH($O28)>MONTH(AV$4),AH28,IF(MONTH($O28)=MONTH(AV$4),AH28*(1+Macroindicadores!E$7),AU28))))))))) -> 1.8938402 | AW28: =IF(ISBLANK(U28),"",IF(ISBLANK($O28),AI28,IF($J28="ANUAL",AI28*(1+Macroindicadores!F$7),IF(AND($I28="NOVO",MONTH($O28)=MONTH(AW$4)),AI28*(1+Macroindicadores!F$7),IF(AND($J28="PONTUAL",MONTH($O28)=MONTH(AW$4)),AI28*(1+Macroindicadores!F$7),IF(AND($J28="PONTUAL",MONTH($O28)<MONTH(AW$4)),MIN($AS28:AV28),IF(AND($I28="NOVO",MONTH($O28)>MONTH(AW$4)),AI28,IF(MONTH($O28)>MONTH(AW$4),AI28,IF(MONTH($O28)=MONTH(AW$4),AI28*(1+Macroindicadores!F$7),AV28))))))))) -> 1.8938402 | AX28: =IF(ISBLANK(V28),"",IF(ISBLANK($O28),AJ28,IF($J28="ANUAL",AJ28*(1+Macroindicadores!G$7),IF(AND($I28="NOVO",MONTH($O28)=MONTH(AX$4)),AJ28*(1+Macroindicadores!G$7),IF(AND($J28="PONTUAL",MONTH($O28)=MONTH(AX$4)),AJ28*(1+Macroindicadores!G$7),IF(AND($J28="PONTUAL",MONTH($O28)<MONTH(AX$4)),MIN($AS28:AW28),IF(AND($I28="NOVO",MONTH($O28)>MONTH(AX$4)),AJ28,IF(MONTH($O28)>MONTH(AX$4),AJ28,IF(MONTH($O28)=MONTH(AX$4),AJ28*(1+Macroindicadores!G$7),AW28))))))))) -> 1.8938402 | AY28: =IF(ISBLANK(W28),"",IF(ISBLANK($O28),AK28,IF($J28="ANUAL",AK28*(1+Macroindicadores!H$7),IF(AND($I28="NOVO",MONTH($O28)=MONTH(AY$4)),AK28*(1+Macroindicadores!H$7),IF(AND($J28="PONTUAL",MONTH($O28)=MONTH(AY$4)),AK28*(1+Macroindicadores!H$7),IF(AND($J28="PONTUAL",MONTH($O28)<MONTH(AY$4)),MIN($AS28:AX28),IF(AND($I28="NOVO",MONTH($O28)>MONTH(AY$4)),AK28,IF(MONTH($O28)>MONTH(AY$4),AK28,IF(MONTH($O28)=MONTH(AY$4),AK28*(1+Macroindicadores!H$7),AX28))))))))) -> 1.8938402 | AZ28: =IF(ISBLANK(X28),"",IF(ISBLANK($O28),AL28,IF($J28="ANUAL",AL28*(1+Macroindicadores!I$7),IF(AND($I28="NOVO",MONTH($O28)=MONTH(AZ$4)),AL28*(1+Macroindicadores!I$7),IF(AND($J28="PONTUAL",MONTH($O28)=MONTH(AZ$4)),AL28*(1+Macroindicadores!I$7),IF(AND($J28="PONTUAL",MONTH($O28)<MONTH(AZ$4)),MIN($AS28:AY28),IF(AND($I28="NOVO",MONTH($O28)>MONTH(AZ$4)),AL28,IF(MONTH($O28)>MONTH(AZ$4),AL28,IF(MONTH($O28)=MONTH(AZ$4),AL28*(1+Macroindicadores!I$7),AY28))))))))) -> 1.8938402 | BA28: =IF(ISBLANK(Y28),"",IF(ISBLANK($O28),AM28,IF($J28="ANUAL",AM28*(1+Macroindicadores!J$7),IF(AND($I28="NOVO",MONTH($O28)=MONTH(BA$4)),AM28*(1+Macroindicadores!J$7),IF(AND($J28="PONTUAL",MONTH($O28)=MONTH(BA$4)),AM28*(1+Macroindicadores!J$7),IF(AND($J28="PONTUAL",MONTH($O28)<MONTH(BA$4)),MIN($AS28:AZ28),IF(AND($I28="NOVO",MONTH($O28)>MONTH(BA$4)),AM28,IF(MONTH($O28)>MONTH(BA$4),AM28,IF(MONTH($O28)=MONTH(BA$4),AM28*(1+Macroindicadores!J$7),AZ28))))))))) -> 1.8938402 | ... BD28: =IF(ISBLANK(AB28),"",IF(ISBLANK($O28),AP28,IF($J28="ANUAL",AP28*(1+Macroindicadores!M$7),IF(AND($I28="NOVO",MONTH($O28)=MONTH(BD$4)),AP28*(1+Macroindicadores!M$7),IF(AND($J28="PONTUAL",MONTH($O28)=MONTH(BD$4)),AP28*(1+Macroindicadores!M$7),IF(AND($J28="PONTUAL",MONTH($O28)<MONTH(BD$4)),MIN($AS28:BC28),IF(AND($I28="NOVO",MONTH($O28)>MONTH(BD$4)),AP28,IF(MONTH($O28)>MONTH(BD$4),AP28,IF(MONTH($O28)=MONTH(BD$4),AP28*(1+Macroindicadores!M$7),BC28))))))))) -> 1.8938402 | BE28: =IF(AND(ISBLANK($Q28),ISBLANK($R28),ISBLANK($S28),ISBLANK($T28),ISBLANK($U28),ISBLANK($V28),ISBLANK($W28),ISBLANK($X28),ISBLANK($Y28),ISBLANK($Z28),ISBLANK($AA28),ISBLANK($AB28)),"",SUM(AS28:BD28)) -> 22.726082 | BG28: =IF(ISBLANK(Q28),"",AS28/Macroindicadores!B$2) -> 0.32208167 | BH28: =IF(ISBLANK(R28),"",AT28/Macroindicadores!C$2) -> 0.32208167 | BI28: =IF(ISBLANK(S28),"",AU28/Macroindicadores!D$2) -> 0.32208167 | BJ28: =IF(ISBLANK(T28),"",AV28/Macroindicadores!E$2) -> 0.32208167 | BK28: =IF(ISBLANK(U28),"",AW28/Macroindicadores!F$2) -> 0.32208167 | BL28: =IF(ISBLANK(V28),"",AX28/Macroindicadores!G$2) -> 0.32208167 | BM28: =IF(ISBLANK(W28),"",AY28/Macroindicadores!H$2) -> 0.32208167 | BN28: =IF(ISBLANK(X28),"",AZ28/Macroindicadores!I$2) -> 0.32208167 | ... BR28: =IF(ISBLANK(AB28),"",BD28/Macroindicadores!M$2) -> 0.32208167 | BS28: =IF(AND(ISBLANK($Q28),ISBLANK($R28),ISBLANK($S28),ISBLANK($T28),ISBLANK($U28),ISBLANK($V28),ISBLANK($W28),ISBLANK($X28),ISBLANK($Y28),ISBLANK($Z28),ISBLANK($AA28),ISBLANK($AB28)),"",SUM(BG28:BR28)) -> 3.86498 | BT28: =IF(ISBLANK($L28),"",_xlfn.XLOOKUP($L28,'CENTRO CUSTO'!$A:$A,'CENTRO CUSTO'!$E:$E,FALSE,0)) -> Custo Fixo
